Workbook
Name EnemyHPSlider: '敌人计算器'!$D$2
Name DPS_Range_Stat: 'DPS计算器'!$G$8
Name Enemy_Endless_Curse_DMG: '敌人计算'!$E$39
Name DPS_Graph_True_Speed: 'DPS计算器'!$A$21
Name Enemy_Wave: '敌人计算'!$D$3
Name Enemy_HP_Per_Wave: '敌人计算'!$J$16
Name DPS_Pumpkin: 'DPS计算器'!$B$11
Name DPS_Reload_Cooldown: 'DPS计算器'!$V$8
Name DPS_Frozen_Heart: 'DPS计算器'!$G$11
Name DPS_Spawn_Final_Crit: 'DPS计算器'!$K$33
Name Enemy_Endless_HP: '敌人计算'!$A$39
Name Shop_Wave: '数值设定'!$D$9
Name DPS_ATK_TYPE: 'DPS计算器'!$O$20
Name Shop_Life_Steal: '数值设定'!$B$16
Name DPS_Spawn_T_Bounces: 'DPS计算器'!$T$14
Name Enemy_Character_DMG: '敌人计算'!$D$31
Name Enemy_Boost_Speed: '敌人计算'!$C$37
Name Shop_Dodge: '数值设定'!$B$2
Name DPS_Back_Dur: 'DPS计算器'!$E$33
Name DPS_Range_Factor: 'DPS计算器'!$F$33
Name DPS_Spawn_Stat: 'DPS计算器'!$J$33
Name Enemy_Danger_DMG: '敌人计算'!$B$31
Name Enemy_Base_DMG: '敌人计算'!$K$14
Name EnemyJackDMG: '敌人计算器'!$O$2
Name Enemy_Buffed: '敌人计算'!$E$3
Name DPS_Weapon_Range: 'DPS计算器'!$M$20
Name DPS_INC_WPN_SPD: 'DPS计算器'!$D$31
Name Shop_Crit: '数值设定'!$B$6
Name DPS_Melee_Damage: 'DPS计算器'!$A$8
Name DPS_Base_Wpn_Spd: 'DPS计算器'!$B$31
Name DPS_Bandana: 'DPS计算器'!$A$11
Name DPS_Crit_DPS_Inc: 'DPS计算器'!$P$8
Name DPS_Projectiles: 'DPS计算器'!$Q$23
Name DPS_Renegade: 'DPS计算器'!$F$11
Name DPS_Bounce_Falloff: 'DPS计算器'!$P$23
Name Enemy_Type: '敌人计算'!$I$3
Name DPS_Graph_Max: 'DPS计算器'!$D$21
Name Enemy_Character_Speed: '敌人计算'!$E$31
Name Enemy_Consumable_Guaranteed: '敌人计算'!$L$19
Name DPS_Graph_Speed_Min: 'DPS计算器'!$C$21
Name Shop_Engineering: '数值设定'!$B$15
Name DPS_Ricochet: 'DPS计算器'!$C$11
Name Shop_Atk_Spd: '数值设定'!$B$13
Name Shop_Melee_Dmg: '数值设定'!$B$7
Name Enemy_Endless_DMG: '敌人计算'!$B$39
Name DPS_Creature: 'DPS计算器'!$I$11
Name DPS_Sharp_Bullet: 'DPS计算器'!$E$11
Name DPS_Base_Burn_DMG: 'DPS计算器'!$M$11
Name DPS_Burn_Ticks: 'DPS计算器'!$O$11
Name EnemyDMGDanger: '敌人计算器'!$N$2
Name EnemyHPDanger: '敌人计算器'!$M$2
Name Enemy_Boost_Damage: '敌人计算'!$B$37
Name DPS_Base_Range: 'DPS计算器'!$I$14
Name Enemy_Base_HP: '敌人计算'!$J$14
Name Enemy_Endless_Curse_HP: '敌人计算'!$D$39
Name DPS_Special_Stat: 'DPS计算器'!$J$8
Name DPS_Eyes_Surgery: 'DPS计算器'!$D$11
Name EnemyJackHP: '敌人计算器'!$P$2
Name Shop_Weapon_Price: '数值设定'!$F$11
Name DPS_Nail: 'DPS计算器'!$H$11

Sheet 简介
A1: 简介 | B1: 道具性价比 | C1: 数值设定 | D1: DPS计算器 | E1: 计算器 | F1: 敌人计算器 | G1: 无尽模式 | I1: 模组制作
B2: 本页计算道具的性价比。你可以通过"数值设定"页修改各属性的价值，以及通过波数修改通胀。 | C2: 在这里你可以修改各属性的价值。例如玩猎人时可将采集设为0，玩骑士时将攻速减半。你也可以修改波数，从而改变通胀。越便宜的道具受通胀影响越大。默认值为第11波，正好是中间点，也是不错的平均值。 | D2: 本计算器可计算任意武器在任意属性与穿透/弹射数量下的DPS。它使用游戏代码中的公式。 | E2: 这是我制作的各种计算器。每一个都附有文字说明。请下载本文档的副本后再编辑数字。只修改蓝色文字的数字！ | F2: 本页主要是无尽模式数值成长的数据表，对大多数玩家用处不大。建议改为阅读我写的无尽模式 Wiki 页面。 | G2: 本页主要是无尽模式数值成长的数据表，对大多数玩家用处不大。建议改为阅读我写的无尽模式 Wiki 页面。 | I2: 如果你为 Brotato 制作了模组，可以轻松地将你的道具和武器添加到计算器中。
A3: 你好，欢迎使用我的多功能工具。它可以计算 Brotato 中的大部分内容。本工具针对PC版游戏制作。我会定期更新本文档，记得偶尔下载新版本。如果你发现任何错误，请联系我以便修正。 | E3: DPS计算器 | F3: Brotato Wiki 无尽模式 | G3: Brotato Wiki 无尽模式
C4: 我制作的指南与资料 | D4: 我参与制作的模组： | E4: 敌人计算器
C5: Brotato 通用指南 | D5: DarkTwinge 的平衡模组 | E5: 采集计算器
C6: 全角色指南 | D6: Kana's Pototos | E6: % Run 计算器
C7: 厌倦了危险5？来挑战吧 | E7: 刷新计算器
C8: 我的无尽模式指南 | E8: 道具价格计算器
C9: 制作 Brotato 强度榜 | E9: 有效生命值计算器
C10: %Run 记录
B12: 官方链接： | C12: 我的反馈与建议 | G12: 鸣谢与致谢
B13: 官方 Brotato Discord | C13: 关于新内容的建议 | G13: Darkly77 | H13: Vergir
B14: Brotato Wiki | C14: 关于Bug与平衡的反馈 | G14: northTip
B15: Brotato 子论坛 | C15: 工程学创意 - 陷阱 | G15: Ta1ha
C16: 关于更高危险等级的建议 | G16: DarkTwinge
C17: 关于 Brotato 多人模式的建议 | G17: Mastabambou
G18: Imoartel
G19: otDan
G20: tauKhan
G21: WL
C22: 要完整使用本文档（可编辑数值），请将其副本保存到你的云端硬盘！(在普通 Excel 中格式可能会出问题)
A29: 更新日志
A30: 1.01
A31: 1.02
A32: 1.03
A33: 1.04
A34: 1.05
A35: 1.06
A36: 1.07
A37: 1.1 | B37: 旧版 1.0.1.3，联机与DLC补丁之前
A38: 1.2
A39: 1.22
A40: 1.24
A41: 1.25
A42: 1.26
A43: 1.27
A44: 1.3
A45: 1.31
A46: 1.4
A47: 1.41

Sheet DPS计算器
A1: DPS计算器 | K1: 武器备注
A2: 使用方法（请阅读此处批注） | C2: 基本信息 | F2: 已知问题 | H2: {=_xlfn.XLOOKUP(DPS_Weapon,武器数据!$A:$A,武器数据!B:B)} | K2: {=_xlfn.XLOOKUP(DPS_Weapon,武器数据!$A:$A,武器数据!AU:AU)}
A5: 冲锋枪1 | M5: 真实冷却 | N5: 提示框冷却 | O5: 每秒攻击次数
A6: 属性 - 添加你想纳入计算的属性 | M6: =If(DPS_Weapon_Type="远程",(DPS_INC_WPN_SPD+1)/60+(ROUNDDOWN(DPS_Inc_Recoil*60+1,0)/60)*2,(ROUNDDOWN((DPS_INC_WPN_SPD+1)+ROUNDDOWN(DPS_Inc_Recoil*60+1,0)+ROUNDDOWN(DPS_Atk_Dur/2*60+1,0)+ROUNDDOWN(DPS_Back_Dur*60+1,0)+1,0))/60+If(DPS_ATK_TYPE="挥砍",1/60)+If(DPS_ATK_TYPE="挥砍/刺击",1/120))+DPS_Weapon_Randomization/60 -> 0.18833333 | N6: =If(DPS_Weapon_Type="远程",DPS_INC_WPN_SPD/60+DPS_Inc_Recoil*2,DPS_INC_WPN_SPD/60+DPS_Inc_Recoil+DPS_Atk_Dur/2+DPS_Back_Dur) -> 0.1452381 | O6: =1/M6 -> 5.3097345 | P6: =M6*60 -> 11.3 | U6: 装填型武器
A7: 近战伤害 | B7: 远程伤害 | C7: 元素伤害 | D7: 伤害% | E7: 攻击速度 | F7: 额外暴击率 | G7: 射程数值 | H7: 工程学 | I7: 最大生命值 | J7: {=_xlfn.XLOOKUP(DPS_Weapon,武器数据!$A:$A,武器数据!AH:AH)} -> 特殊成长 | K7: 诅咒 | M7: 每次命中伤害 | N7: 暴击伤害 | O7: 暴击率 | P7: 暴击DPS提升 | T7: 每次攻击帧数 | U7: 装填提示 | V7: 装填冷却 | W7: 平均冷却（含装填）
A8: 0 | B8: 0 | C8: 0 | D8: 0 | E8: 0.05 | F8: 0 | G8: 0 | H8: 0 | I8: 0 | J8: 0 | K8: 0 | M8: =Round(MAX(MAX(DPS_Base_DMG+ROUNDDOWN(A33*A14,0)+ROUNDDOWN(B33*B14,0)+ROUNDDOWN(C33*C14,0)+IF(DPS_Frozen_Heart=True,0.1*DPS_Elemental_Damage,0)+IF(DPS_Creature=True,0.35*DPS_Curse,0)+IF(DPS_Nail=True,0.2*DPS_Engineering,0),1)*(1+DPS_DMG_Percent),1),0) -> 3 | N8: =Round($M$8*$H$14,0) -> 5 | O8: =MAX(MIN(DPS_Crit_WPN_Base+DPS_Crit_Chance_Stat,1),0) -> 0.01 | P8: =IFERROR(O8*(N8/M8-1),0) -> 0.0066666667 | T8: =M6*60 -> 11.3 | U8: =IF(DPS_ReloadX_Shots>0, ((DPS_INC_WPN_SPD*DPS_Reload_Multiplier)/60+ROUNDDOWN(DPS_Inc_Recoil*60,0)/60*2), 0) -> 0 | V8: =IF(DPS_ReloadX_Shots>0, ((DPS_INC_WPN_SPD*DPS_Reload_Multiplier+1)/60+ROUNDDOWN(DPS_Inc_Recoil*60+1,0)/60*2), 0) -> 0 | W8: =IF(DPS_ReloadX_Shots>0,DPS_Cooldown_W_Bonus+(DPS_Reload_Cooldown-DPS_Cooldown_W_Bonus)/DPS_ReloadX_Shots,0) -> 0
A9: 输入道具数量。
A10: 头巾s | B10: 南瓜s | C10: 跳弹 | D10: 眼部手术 | E10: 锋利子弹 | F10: 叛徒 | G10: 冰封之心 | H10: 钉子 | I10: 生物 | J10: 潜水员 +200% 暴击 | M10: 基础燃烧伤害 | N10: 强化燃烧伤害 | O10: 燃烧跳数 | P10: 燃烧DPS | Q10: 持续时间内总燃烧伤害
A11: 0 | B11: 0 | C11: 0 | D11: 0 | E11: FALSE | F11: FALSE | G11: FALSE | H11: FALSE | I11: FALSE | J11: FALSE | M11: {=_xlfn.XLOOKUP(DPS_Weapon,武器数据!$A:$A,武器数据!S:S)} -> 0 | N11: =ROUND(IF(DPS_Ice_Cube=True,1.1,1)*ROUND(IF(DPS_Base_Burn_DMG=0,0, (DPS_Base_Burn_DMG+DPS_Elemental_Damage)*(1+DPS_DMG_Percent)),0),0) -> 0 | O11: {=_xlfn.XLOOKUP(DPS_Weapon,武器数据!$A:$A,武器数据!T:T)} -> 0 | P11: =DPS_Buffed_Burn_DMG/(MAX(1-DPS_Eyes_Surgery/5,0.6)+IF(DPS_Frozen_Heart=TRUE,1,0)) -> 0 | Q11: =DPS_Burn_Ticks*DPS_Buffed_Burn_DMG -> 0
A12: 武器数据 - 所选武器的数值
A13: 固定伤害成长 | B13: 2点伤害成长 | C13: 3点伤害成长 | D13: 生成成长 | E13: 基础伤害 | F13: 基础冷却 | G13: 基础暴击率 | H13: 暴击倍率 | I13: 基础射程 | J13: 武器随机范围 | M13: 生成弹幕总数 | N13: 生成每次命中伤害 | O13: 生成DPS | P13: 含弹射与穿透的生成DPS | S13: 生成基础弹射次数 | T13: 生成总弹射次数 | U13: 生成弹射衰减 | V13: 生成基础穿透 | W13: 生成总穿透次数 | X13: 生成穿透衰减
A14: {=_xlfn.XLOOKUP(DPS_Weapon,武器数据!$A:$A,武器数据!AE:AE)} -> 0.5 | B14: {=_xlfn.XLOOKUP(DPS_Weapon,武器数据!$A:$A,武器数据!AF:AF)} | C14: {=_xlfn.XLOOKUP(DPS_Weapon,武器数据!$A:$A,武器数据!AG:AG)} | D14: {=_xlfn.XLOOKUP(DPS_Weapon,武器数据!$A:$A,武器数据!AC:AC)} -> 0 | E14: {=_xlfn.XLOOKUP(DPS_Weapon,武器数据!$A:$A,武器数据!E:E)} -> 3 | F14: =If(DPS_Weapon_Type="远程",B31/60+C31*2,B31/60+C31+G33/2+H33) -> 0.16666667 | G14: {=_xlfn.XLOOKUP(DPS_Weapon,武器数据!$A:$A,武器数据!I:I)} -> 0.01 | H14: {=_xlfn.XLOOKUP(DPS_Weapon,武器数据!$A:$A,武器数据!J:J)} -> 1.5 | I14: {=_xlfn.XLOOKUP(DPS_Weapon,武器数据!$A:$A,武器数据!G:G)} -> 400 | J14: 6 | M14: {=_xlfn.XLOOKUP(DPS_Weapon,武器数据!$A:$A,武器数据!V:V)*If(A31="远程",1+DPS_Bounces+DPS_Pierce,1)*If(A31="远程",DPS_Projectiles,1)} -> 0 | N14: {=IF(_xlfn.XLOOKUP(DPS_Weapon,武器数据!$A:$A,武器数据!U:U)=0,0,ROUND((1+DPS_DMG_Percent)*RoundDown(Max(_xlfn.XLOOKUP(DPS_Weapon,武器数据!$A:$A,武器数据!U:U)+DPS_Spawn_Scaling*DPS_Spawn_Stat,1),0),0))} -> 0 | O14: =IFerror($M$14*DPS_Attacks_P_Sec*DPS_Spawn_DMG_Per_Hit*(1+((ROUND(DPS_SpawnCritMult*DPS_Spawn_DMG_Per_Hit,0)/DPS_Spawn_DMG_Per_Hit-1)*DPS_Spawn_Final_Crit)),0) -> 0 | P14: {=O14+M14*DPS_Attacks_P_Sec*((1-DPS_Spawn_Final_Crit)*SUM(G35:INdirect(ADDRESS(35+DPS_Spawn_T_Bounces,7)))+DPS_Spawn_Final_Crit*SUM(H35:INdirect(ADDRESS(35+DPS_Spawn_T_Bounces,8)))+(1-DPS_Spawn_Final_Crit)*SUM(J35:INdirect(ADDRESS(35+DPS_Spawn_T_Piercing,10)))+DPS_Spawn_Final_Crit*SUM(K35:INdirect(ADDRESS(35+DPS_Spawn_T_Piercing,11))))} -> 0 | S14: {=_xlfn.XLOOKUP(DPS_Weapon,武器数据!$A:$A,武器数据!W:W)} -> 0 | T14: =S14+DPS_Ricochet -> 0 | U14: {=Max(0,Min(1,_xlfn.XLOOKUP(DPS_Weapon,武器数据!$A:$A,武器数据!X:X)))} -> 0.5 | V14: {=_xlfn.XLOOKUP(DPS_Weapon,武器数据!$A:$A,武器数据!Y:Y)} -> 0 | W14: =V14+DPS_Bandana+IF(DPS_Renegade=True,1,0)+IF(DPS_Sharp_Bullet=True,1,0) -> 0 | X14: {=Max(0,Min(1,_xlfn.XLOOKUP(DPS_Weapon,武器数据!$A:$A,武器数据!Z:Z)-Max(0,B11*0.15)+IF(DPS_Sharp_Bullet=True, 0.2, 0)))} -> 0.5
A15: 武器数据·弹射/穿透
A16: 固有穿透 | B16: 基础穿透衰减 | C16: 固有弹射 | D16: 基础弹射衰减 | E16: 固有弹幕 | F16: 暴击额外命中 | G16: 每x发装填 | H16: 装填倍率 | M16: DPS | N16: 含弹射/穿透的DPS | P16: 含生成弹幕的总DPS | S16: 每次命中总弹射/穿透伤害
A17: {=_xlfn.XLOOKUP(DPS_Weapon,武器数据!$A:$A,武器数据!N:N)} -> 0 | B17: {=_xlfn.XLOOKUP(DPS_Weapon,武器数据!$A:$A,武器数据!O:O)} -> 0.5 | C17: {=_xlfn.XLOOKUP(DPS_Weapon,武器数据!$A:$A,武器数据!L:L)} -> 0 | D17: {=_xlfn.XLOOKUP(DPS_Weapon,武器数据!$A:$A,武器数据!M:M)} -> 0.5 | E17: {=_xlfn.XLOOKUP(DPS_Weapon,武器数据!$A:$A,武器数据!K:K)} -> 1 | F17: {=_xlfn.XLOOKUP(DPS_Weapon,武器数据!$A:$A,武器数据!P:P)} -> 0 | G17: {=_xlfn.XLOOKUP(DPS_Weapon,武器数据!$A:$A,武器数据!Q:Q)} -> 0 | H17: {=_xlfn.XLOOKUP(DPS_Weapon,武器数据!$A:$A,武器数据!R:R)} -> 0 | M17: =DPS_DMG_Per_Hit*(1+DPS_Crit_DPS_Inc)*DPS_Attacks_P_Sec*DPS_Projectiles/IF(DPS_ReloadX_Shots>0, 1+((DPS_Reload_Cooldown/DPS_Cooldown_W_Bonus-1)/DPS_ReloadX_Shots), 1) -> 16.035398 | N17: =DPS_DPS+IF(DPS_Weapon_Type="远程",DPS_Projectiles*DPS_Attacks_P_Sec*DPS_Total_BP_Per_Hit)/IF(DPS_ReloadX_Shots>0, 1+((DPS_Reload_Cooldown/DPS_Cooldown_W_Bonus-1)/DPS_ReloadX_Shots), 1) -> 16.035398 | P17: =N17+P14 -> 16.035398 | S17: =IFERROR(__xludf.DUMMYFUNCTION("IF(DPS_Weapon_Type=""远程"",(IF(REGEXMATCH(DPS_Weapon, ""十字弓""),If(DPS_Bounces>0,(1-DPS_Crit_Chance_Final)*INdirect(ADDRESS(35+DPS_Bounces,2))+DPS_Crit_Chance_Final*INdirect(ADDRESS(35+DPS_Bounces,3)),(DPS_Crit_Chance_Final*DPS_Crit_Hit_Dmg+(1-DPS_"&"Crit_Chance_Final)*DPS_DMG_Per_Hit)),(DPS_Crit_Chance_Final*DPS_Crit_Hit_Dmg+(1-DPS_Crit_Chance_Final)*DPS_DMG_Per_Hit))*SUM(F35:INdirect(ADDRESS(35+F17,6)))+(1-DPS_Crit_Chance_Final)*SUM(B35:INdirect(ADDRESS(35+DPS_Bounces,2)))+DPS_Crit_Chance_Final*SUM("&"C35:INdirect(ADDRESS(35+DPS_Bounces,3)))+(1-DPS_Crit_Chance_Final)*SUM(D35:INdirect(ADDRESS(35+DPS_Pierce,4)))+DPS_Crit_Chance_Final*SUM(E35:INdirect(ADDRESS(35+DPS_Pierce,5)))),0)"),0.0) -> 0
A19: 图表设置 | M19: 武器射程 | N19: 基础击退 | O19: 攻击类型 | P19: 爆炸范围 | Q19: 爆炸几率 | S19: 弹速 | T19: 基础价格 | U19: 武器精准 | V19: 武器扩散
A20: 真实攻速 | B20: 提示框攻速 | C20: 图表最小攻速 | D20: 图表最大攻速 | F20: 水手 +200% 伤害 | G20: 厨师 +200% 伤害 | H20: 潜水员 +300% 伤害 | I20: 铁球锁链 | J20: 冰块 | M20: =MAX(If(DPS_Weapon_Type="近战",DPS_Base_Range+DPS_Range_Stat*0.5,DPS_Base_Range+DPS_Range_Stat),25) -> 400 | N20: {=_xlfn.XLOOKUP(DPS_Weapon,武器数据!$A:$A,武器数据!AM:AM)} -> 0 | O20: {=_xlfn.XLOOKUP(DPS_Weapon,武器数据!$A:$A,武器数据!D:D)} -> 弹幕 | P20: {=_xlfn.XLOOKUP(DPS_Weapon,武器数据!$A:$A,武器数据!AR:AR)} -> 0 | Q20: {=_xlfn.XLOOKUP(DPS_Weapon,武器数据!$A:$A,武器数据!AQ:AQ)} -> 0 | S20: {=_xlfn.XLOOKUP(DPS_Weapon,武器数据!$A:$A,武器数据!AL:AL)} -> 3000 | T20: {=_xlfn.XLOOKUP(DPS_Weapon,武器数据!$A:$A,武器数据!AP:AP)} -> 20 | U20: {=_xlfn.XLOOKUP(DPS_Weapon,武器数据!$A:$A,武器数据!AN:AN)+IF(DPS_Weapon_Type="远程",IF(DPS_Renegade=True,-0.5,0),0)} -> 0.7 | V20: {=_xlfn.XLOOKUP(DPS_Weapon,武器数据!$A:$A,武器数据!AO:AO)} -> 0
A21: TRUE | B21: TRUE | C21: -1 | D21: 3 | F21: FALSE | G21: FALSE | H21: FALSE | I21: FALSE | J21: FALSE
M22: 总穿透次数 | N22: 总穿透衰减 | O22: 总弹射次数 | P22: 总弹射衰减 | Q22: 总弹幕数。
M23: =Max(0,A17+DPS_Bandana+IF(DPS_Renegade=True,1,0)+IF(DPS_Sharp_Bullet=True,1,0)) -> 0 | N23: =Max(0,Min(1,B17-Max(0,B11*0.15)+IF(DPS_Sharp_Bullet=True, 0.2, 0))) -> 0.5 | O23: =Max(0,C17+C11) -> 0 | P23: =D17 -> 0.5 | Q23: =E17+IF(DPS_Weapon_Type="远程",IF(DPS_Renegade=True,2,0),0) -> 1
A28: 武器数据 - 仅供编辑者。
A30: 武器类型 | B30: 基础武器速度 | C30: 基础后坐力 | D30: 武器速度增加 | E30: 后坐力增加 | F30: 加成属性折算的升级数 | I30: 生成暴击倍率 | K30: 生成基础暴击率
A31: {=_xlfn.XLOOKUP(DPS_Weapon,武器数据!$A:$A,武器数据!C:C)} -> 远程 | B31: {=_xlfn.XLOOKUP(DPS_Weapon,武器数据!$A:$A,武器数据!F:F)} -> 4 | C31: {=_xlfn.XLOOKUP(DPS_Weapon,武器数据!$A:$A,武器数据!H:H)} -> 0.05 | D31: =ROUNDDOWN(MAX(2,IF(DPS_Attack_Speed>=0, DPS_Base_Wpn_Spd/(1+DPS_Attack_Speed),DPS_Base_Wpn_Spd*(1+ABS(DPS_Attack_Speed)))),0) -> 3 | E31: =IF(DPS_Attack_Speed>=0, DPS_Base_Recoil/(1+DPS_Attack_Speed),DPS_Base_Recoil) -> 0.047619048 | F31: =A8/'数值设定'!B7+B8/'数值设定'!B14+C8/'数值设定'!B3+100*D8/'数值设定'!B17+100*E8/'数值设定'!B13+100*F8/'数值设定'!B6+G8/'数值设定'!B5 -> 1 | I31: {=_xlfn.XLOOKUP(DPS_Weapon,武器数据!$A:$A,武器数据!AA:AA)} -> 2 | K31: {=_xlfn.XLOOKUP(DPS_Weapon,武器数据!$A:$A,武器数据!AB:AB)} -> 0.03
A32: 主属性 | B32: 次要属性 | C32: 第三属性 | D32: 攻击持续时间 | E32: 后摇持续时间 | F32: 射程系数 | G32: 基础攻击持续时间 | H32: 基础后摇 | I32: 基础射程系数 | J32: 生成属性成长 | K32: 生成最终暴击率 | S32: 武器随机范围
A33: {=_xlfn.XLOOKUP(DPS_Weapon,武器数据!$A:$A,武器数据!AI:AI)} -> 0 | B33: {=_xlfn.XLOOKUP(DPS_Weapon,武器数据!$A:$A,武器数据!AJ:AJ)} -> 0 | C33: {=_xlfn.XLOOKUP(DPS_Weapon,武器数据!$A:$A,武器数据!AK:AK)} | D33: =MAX(0.01, 0.2 - (DPS_Attack_Speed / 10)) + (DPS_Range_Factor * 0.15) -> 1.0380913 | E33: =(0.2 / (1 + (Max(0,DPS_Attack_Speed) * 3))) -> 0.17391304 | F33: =MAX(0, Max(25,(DPS_Base_Range + ((DPS_Range_Stat) / 2))) / MIN(MAX(70, (70 * (1 + (DPS_Attack_Speed / 3)))), 120)) -> 5.6206089 | G33: =MAX(0.01, 0.2 - (0 / 10)) + (DPS_Range_Factor * 0.15) -> 1.0430913 | H33: =0.2 / (1 + (0 * 3)) -> 0.2 | I33: =MAX(0, Max(25,(DPS_Weapon_Range + ((DPS_Range_Stat) / 2))) / MIN(MAX(70, (70 * (1 + (0 / 3)))), 120)) -> 5.7142857 | J33: {=_xlfn.XLOOKUP(DPS_Weapon,武器数据!$A:$A,武器数据!AD:AD)} -> 0 | K33: =MAX(MIN(K31+DPS_Crit_Chance_Stat,1),0) -> 0.03 | S33: 武器数量 | T33: 随机% | U33: 武器冷却 | V33: 最小帧 | W33: 取整平均值
A34: 攻击 | B34: 弹射 | C34: 弹射暴击 | D34: 穿透 | E34: 穿透暴击 | F34: 暴击额外命中 | G34: 生成弹射 | H34: 生成基础暴击 | J34: 生成穿透 | K34: 生成穿透暴击 | S34: =J14 -> 6 | T34: =Min(20%*S34,1.2) -> 1.2 | U34: =D31 -> 3 | V34: 1 | W34: =If(T34=0,0,0.5) -> 0.5
A35: 0 | B35: 0 | C35: 0 | D35: 0 | E35: 0 | F35: 0 | G35: 0 | H35: 0 | J35: 0 | K35: 0 | S35: 帧间隔 | T35: 射程最小值 | U35: 射程最大值 | V35: 平均 | W35: 最终
A36: 1 | B36: =IF($A$31="远程", MAX(ROUNDDOWN(M8*(1-$P$23),0),1),0) -> 1 | C36: =Round(B36*$H$14,0) -> 2 | D36: {=IF($A$31="远程",MAX(IF(DPS_Bounces>=1, ROUNDDOWN((1-DPS_Piercing_Falloff)*INdirect(ADDRESS(MAX(35,34+DPS_Bounces),2)),0),ROUNDDOWN((1-DPS_Piercing_Falloff)*DPS_DMG_Per_Hit,0)),1),0)} -> 1 | E36: =Round(D36*$H$14,0) -> 2 | F36: =IF($A$31="远程",$O$8^A36,0) -> 0.01 | G36: =MAX(ROUNDDOWN(N14*(1-$U$14),0),1) -> 1 | H36: =Round(G36*DPS_SpawnCritMult,0) -> 2 | J36: {=MAX(IF(DPS_Spawn_T_Bounces>=1, (1-$X$14)*INdirect(ADDRESS(MAX(35,34+DPS_Spawn_T_Bounces),7)),ROUNDDOWN((1-$X$14)*DPS_Spawn_DMG_Per_Hit,0)),1)} -> 1 | K36: =Round(J36*DPS_SpawnCritMult,0) -> 2 | S36: =MIN(T34*U34,5*S34) -> 3.6 | T36: =MAX( 1,U34-S36) -> 1 | U36: =S36+U34 -> 6.6 | V36: =(T36+U36)/2 -> 3.8 | W36: =V36+W34-U34 -> 1.3
A37: 2 | B37: =IF($A$31="远程",MAX(ROUNDDOWN(B36*(1-$P$23),0),1),0) -> 1 | C37: =Round(B37*$H$14,0) -> 2 | D37: =IF($A$31="远程",MAX(ROUNDDOWN((1-DPS_Piercing_Falloff)*D36,0),1),0) -> 1 | E37: =Round(D37*$H$14,0) -> 2 | F37: =IF($A$31="远程",$O$8^A37,0) -> 0.0001 | G37: =MAX(ROUNDDOWN(G36*(1-$U$14),0),1) -> 1 | H37: =Round(G37*DPS_SpawnCritMult,0) -> 2 | J37: =MAX(ROUNDDOWN((1-$X$14)*J36,0),1) -> 1 | K37: =Round(J37*DPS_SpawnCritMult,0) -> 2
A38: 3 | B38: =IF($A$31="远程",MAX(ROUNDDOWN(B37*(1-$P$23),0),1),0) -> 1 | C38: =Round(B38*$H$14,0) -> 2 | D38: =IF($A$31="远程",MAX(ROUNDDOWN((1-DPS_Piercing_Falloff)*D37,0),1),0) -> 1 | E38: =Round(D38*$H$14,0) -> 2 | F38: =IF($A$31="远程",$O$8^A38,0) -> 1e-06 | G38: =MAX(ROUNDDOWN(G37*(1-$U$14),0),1) -> 1 | H38: =Round(G38*DPS_SpawnCritMult,0) -> 2 | J38: =MAX(ROUNDDOWN((1-$X$14)*J37,0),1) -> 1 | K38: =Round(J38*DPS_SpawnCritMult,0) -> 2
A39: 4 | B39: =IF($A$31="远程",MAX(ROUNDDOWN(B38*(1-$P$23),0),1),0) -> 1 | C39: =Round(B39*$H$14,0) -> 2 | D39: =IF($A$31="远程",MAX(ROUNDDOWN((1-DPS_Piercing_Falloff)*D38,0),1),0) -> 1 | E39: =Round(D39*$H$14,0) -> 2 | F39: =IF($A$31="远程",$O$8^A39,0) -> 1e-08 | G39: =MAX(ROUNDDOWN(G38*(1-$U$14),0),1) -> 1 | H39: =Round(G39*DPS_SpawnCritMult,0) -> 2 | J39: =MAX(ROUNDDOWN((1-$X$14)*J38,0),1) -> 1 | K39: =Round(J39*DPS_SpawnCritMult,0) -> 2
A40: 5 | B40: =IF($A$31="远程",MAX(ROUNDDOWN(B39*(1-$P$23),0),1),0) -> 1 | C40: =Round(B40*$H$14,0) -> 2 | D40: =IF($A$31="远程",MAX(ROUNDDOWN((1-DPS_Piercing_Falloff)*D39,0),1),0) -> 1 | E40: =Round(D40*$H$14,0) -> 2 | F40: =IF($A$31="远程",$O$8^A40,0) -> 1e-10 | G40: =MAX(ROUNDDOWN(G39*(1-$U$14),0),1) -> 1 | H40: =Round(G40*DPS_SpawnCritMult,0) -> 2 | J40: =MAX(ROUNDDOWN((1-$X$14)*J39,0),1) -> 1 | K40: =Round(J40*DPS_SpawnCritMult,0) -> 2
A41: 6 | B41: =IF($A$31="远程",MAX(ROUNDDOWN(B40*(1-$P$23),0),1),0) -> 1 | C41: =Round(B41*$H$14,0) -> 2 | D41: =IF($A$31="远程",MAX(ROUNDDOWN((1-DPS_Piercing_Falloff)*D40,0),1),0) -> 1 | E41: =Round(D41*$H$14,0) -> 2 | F41: =IF($A$31="远程",$O$8^A41,0) -> 0 | G41: =MAX(ROUNDDOWN(G40*(1-$U$14),0),1) -> 1 | H41: =Round(G41*DPS_SpawnCritMult,0) -> 2 | J41: =MAX(ROUNDDOWN((1-$X$14)*J40,0),1) -> 1 | K41: =Round(J41*DPS_SpawnCritMult,0) -> 2
A42: 7 | B42: =IF($A$31="远程",MAX(ROUNDDOWN(B41*(1-$P$23),0),1),0) -> 1 | C42: =Round(B42*$H$14,0) -> 2 | D42: =IF($A$31="远程",MAX(ROUNDDOWN((1-DPS_Piercing_Falloff)*D41,0),1),0) -> 1 | E42: =Round(D42*$H$14,0) -> 2 | F42: =IF($A$31="远程",$O$8^A42,0) -> 0 | G42: =MAX(ROUNDDOWN(G41*(1-$U$14),0),1) -> 1 | H42: =Round(G42*DPS_SpawnCritMult,0) -> 2 | J42: =MAX(ROUNDDOWN((1-$X$14)*J41,0),1) -> 1 | K42: =Round(J42*DPS_SpawnCritMult,0) -> 2
A43: 8 | B43: =IF($A$31="远程",MAX(ROUNDDOWN(B42*(1-$P$23),0),1),0) -> 1 | C43: =Round(B43*$H$14,0) -> 2 | D43: =IF($A$31="远程",MAX(ROUNDDOWN((1-DPS_Piercing_Falloff)*D42,0),1),0) -> 1 | E43: =Round(D43*$H$14,0) -> 2 | F43: =IF($A$31="远程",$O$8^A43,0) -> 0 | G43: =MAX(ROUNDDOWN(G42*(1-$U$14),0),1) -> 1 | H43: =Round(G43*DPS_SpawnCritMult,0) -> 2 | J43: =MAX(ROUNDDOWN((1-$X$14)*J42,0),1) -> 1 | K43: =Round(J43*DPS_SpawnCritMult,0) -> 2
A44: 9 | B44: =IF($A$31="远程",MAX(ROUNDDOWN(B43*(1-$P$23),0),1),0) -> 1 | C44: =Round(B44*$H$14,0) -> 2 | D44: =IF($A$31="远程",MAX(ROUNDDOWN((1-DPS_Piercing_Falloff)*D43,0),1),0) -> 1 | E44: =Round(D44*$H$14,0) -> 2 | F44: =IF($A$31="远程",$O$8^A44,0) -> 0 | G44: =MAX(ROUNDDOWN(G43*(1-$U$14),0),1) -> 1 | H44: =Round(G44*DPS_SpawnCritMult,0) -> 2 | J44: =MAX(ROUNDDOWN((1-$X$14)*J43,0),1) -> 1 | K44: =Round(J44*DPS_SpawnCritMult,0) -> 2
A45: 10 | B45: =IF($A$31="远程",MAX(ROUNDDOWN(B44*(1-$P$23),0),1),0) -> 1 | C45: =Round(B45*$H$14,0) -> 2 | D45: =IF($A$31="远程",MAX(ROUNDDOWN((1-DPS_Piercing_Falloff)*D44,0),1),0) -> 1 | E45: =Round(D45*$H$14,0) -> 2 | F45: =IF($A$31="远程",$O$8^A45,0) -> 0 | G45: =MAX(ROUNDDOWN(G44*(1-$U$14),0),1) -> 1 | H45: =Round(G45*DPS_SpawnCritMult,0) -> 2 | J45: =MAX(ROUNDDOWN((1-$X$14)*J44,0),1) -> 1 | K45: =Round(J45*DPS_SpawnCritMult,0) -> 2
A46: 11 | B46: =IF($A$31="远程",MAX(ROUNDDOWN(B45*(1-$P$23),0),1),0) -> 1 | C46: =Round(B46*$H$14,0) -> 2 | D46: =IF($A$31="远程",MAX(ROUNDDOWN((1-DPS_Piercing_Falloff)*D45,0),1),0) -> 1 | E46: =Round(D46*$H$14,0) -> 2 | F46: =IF($A$31="远程",$O$8^A46,0) -> 0 | G46: =MAX(ROUNDDOWN(G45*(1-$U$14),0),1) -> 1 | H46: =Round(G46*DPS_SpawnCritMult,0) -> 2 | J46: =MAX(ROUNDDOWN((1-$X$14)*J45,0),1) -> 1 | K46: =Round(J46*DPS_SpawnCritMult,0) -> 2
A47: 12 | B47: =IF($A$31="远程",MAX(ROUNDDOWN(B46*(1-$P$23),0),1),0) -> 1 | C47: =Round(B47*$H$14,0) -> 2 | D47: =IF($A$31="远程",MAX(ROUNDDOWN((1-DPS_Piercing_Falloff)*D46,0),1),0) -> 1 | E47: =Round(D47*$H$14,0) -> 2 | F47: =IF($A$31="远程",$O$8^A47,0) -> 0 | G47: =MAX(ROUNDDOWN(G46*(1-$U$14),0),1) -> 1 | H47: =Round(G47*DPS_SpawnCritMult,0) -> 2 | J47: =MAX(ROUNDDOWN((1-$X$14)*J46,0),1) -> 1 | K47: =Round(J47*DPS_SpawnCritMult,0) -> 2
A48: 13 | B48: =IF($A$31="远程",MAX(ROUNDDOWN(B47*(1-$P$23),0),1),0) -> 1 | C48: =Round(B48*$H$14,0) -> 2 | D48: =IF($A$31="远程",MAX(ROUNDDOWN((1-DPS_Piercing_Falloff)*D47,0),1),0) -> 1 | E48: =Round(D48*$H$14,0) -> 2 | F48: =IF($A$31="远程",$O$8^A48,0) -> 0 | G48: =MAX(ROUNDDOWN(G47*(1-$U$14),0),1) -> 1 | H48: =Round(G48*DPS_SpawnCritMult,0) -> 2 | J48: =MAX(ROUNDDOWN((1-$X$14)*J47,0),1) -> 1 | K48: =Round(J48*DPS_SpawnCritMult,0) -> 2
... A140: 105 | B140: =IF($A$31="远程",MAX(ROUNDDOWN(B139*(1-$P$23),0),1),0) -> 1 | C140: =Round(B140*$H$14,0) -> 2 | D140: =IF($A$31="远程",MAX(ROUNDDOWN((1-DPS_Piercing_Falloff)*D139,0),1),0) -> 1 | E140: =Round(D140*$H$14,0) -> 2 | F140: =IF($A$31="远程",$O$8^A140,0) -> 0 | G140: =MAX(ROUNDDOWN(G139*(1-$U$14),0),1) -> 1 | H140: =Round(G140*DPS_SpawnCritMult,0) -> 2 | J140: =MAX(ROUNDDOWN((1-$X$14)*J139,0),1) -> 1 | K140: =Round(J140*DPS_SpawnCritMult,0) -> 2
A142: 攻击速度 | B142: 图表·真实攻速 | E142: 武器速度增加 | F142: 后坐力增加 | G142: 攻击持续时间 | H142: 后摇持续时间 | J142: 射程系数 | K142: 区间内攻速 | M142: 提示框攻速
A143: -1 | B143: =If(DPS_Weapon_Type="远程",($E143+1)/60+(ROUNDDOWN($F143*60+1,0)/60)*2,(ROUNDDOWN(($E143+1)+ROUNDDOWN($F143*60+1,0)+ROUNDDOWN($G143/2*60+1,0)+ROUNDDOWN($H143*60+1,0)+1,0))/60+If(DPS_ATK_TYPE="挥砍",1/60)+If(DPS_ATK_TYPE="挥砍/刺击",1/120))+DPS_Weapon_Randomization/60 -> 0.305 | C143: =IF(DPS_Graph_True_Speed=TRUE,IF($A143<=DPS_Graph_Max,IF($A143>=DPS_Graph_Speed_Min,1/B143,),),) -> 3.2786885 | D143: =IF(DPS_Graph_True_Speed=TRUE,IF($E$8=$A143,DPS_Attacks_P_Sec,),) | E143: =ROUNDDOWN(MAX(2,IF(A143>=0, DPS_Base_Wpn_Spd/(1+A143),DPS_Base_Wpn_Spd*(1+ABS(A143)))),0) -> 8 | F143: =IF(A143>=0, DPS_Base_Recoil/(1+A143),DPS_Base_Recoil) -> 0.05 | G143: =MAX(0.01, 0.2 - ($A143 / 10)) + (J143 * 0.15) -> 1.1571429 | H143: =(0.2 / (1 + (Max(0,$A143) * 3))) -> 0.2 | J143: =MAX(0, Max(25,(DPS_Base_Range + ((DPS_Range_Stat) / 2))) / MIN(MAX(70, (70 * (1 + ($A143 / 3)))), 120)) -> 5.7142857 | K143: =IF(A143<=DPS_Graph_Max,IF(A143>=DPS_Graph_Speed_Min,A143,),) -> -1 | M143: =If(DPS_Weapon_Type="远程",$E143/60+$F143*2,$E143/60+$F143+$G143/2+$H143) -> 0.23333333 | N143: =IF(DPS_Graph_Tooltip_Speed=TRUE,IF($A143<=DPS_Graph_Max,IF($A143>=DPS_Graph_Speed_Min,1/M143,),),) -> 4.2857143 | R143: =IF(DPS_Graph_Tooltip_Speed=TRUE,IF($E$8=$A143,1/$N$6,),)
A144: -0.99 | B144: =If(DPS_Weapon_Type="远程",($E144+1)/60+(ROUNDDOWN($F144*60+1,0)/60)*2,(ROUNDDOWN(($E144+1)+ROUNDDOWN($F144*60+1,0)+ROUNDDOWN($G144/2*60+1,0)+ROUNDDOWN($H144*60+1,0)+1,0))/60+If(DPS_ATK_TYPE="挥砍",1/60)+If(DPS_ATK_TYPE="挥砍/刺击",1/120))+DPS_Weapon_Randomization/60 -> 0.28833333 | C144: =IF(DPS_Graph_True_Speed=TRUE,IF($A144<=DPS_Graph_Max,IF($A144>=DPS_Graph_Speed_Min,1/B144,),),) -> 3.4682081 | D144: =IF(DPS_Graph_True_Speed=TRUE,IF($E$8=$A144,DPS_Attacks_P_Sec,),) | E144: =ROUNDDOWN(MAX(2,IF(A144>=0, DPS_Base_Wpn_Spd/(1+A144),DPS_Base_Wpn_Spd*(1+ABS(A144)))),0) -> 7 | F144: =IF(A144>=0, DPS_Base_Recoil/(1+A144),DPS_Base_Recoil) -> 0.05 | G144: =MAX(0.01, 0.2 - ($A144 / 10)) + (J144 * 0.15) -> 1.1561429 | H144: =(0.2 / (1 + (Max(0,$A144) * 3))) -> 0.2 | J144: =MAX(0, Max(25,(DPS_Base_Range + ((DPS_Range_Stat) / 2))) / MIN(MAX(70, (70 * (1 + ($A144 / 3)))), 120)) -> 5.7142857 | K144: =IF(A144<=DPS_Graph_Max,IF(A144>=DPS_Graph_Speed_Min,A144,),) -> -0.99 | M144: =If(DPS_Weapon_Type="远程",$E144/60+$F144*2,$E144/60+$F144+$G144/2+$H144) -> 0.21666667 | N144: =IF(DPS_Graph_Tooltip_Speed=TRUE,IF($A144<=DPS_Graph_Max,IF($A144>=DPS_Graph_Speed_Min,1/M144,),),) -> 4.6153846 | R144: =IF(DPS_Graph_Tooltip_Speed=TRUE,IF($E$8=$A144,1/$N$6,),)
A145: -0.98 | B145: =If(DPS_Weapon_Type="远程",($E145+1)/60+(ROUNDDOWN($F145*60+1,0)/60)*2,(ROUNDDOWN(($E145+1)+ROUNDDOWN($F145*60+1,0)+ROUNDDOWN($G145/2*60+1,0)+ROUNDDOWN($H145*60+1,0)+1,0))/60+If(DPS_ATK_TYPE="挥砍",1/60)+If(DPS_ATK_TYPE="挥砍/刺击",1/120))+DPS_Weapon_Randomization/60 -> 0.28833333 | C145: =IF(DPS_Graph_True_Speed=TRUE,IF($A145<=DPS_Graph_Max,IF($A145>=DPS_Graph_Speed_Min,1/B145,),),) -> 3.4682081 | D145: =IF(DPS_Graph_True_Speed=TRUE,IF($E$8=$A145,DPS_Attacks_P_Sec,),) | E145: =ROUNDDOWN(MAX(2,IF(A145>=0, DPS_Base_Wpn_Spd/(1+A145),DPS_Base_Wpn_Spd*(1+ABS(A145)))),0) -> 7 | F145: =IF(A145>=0, DPS_Base_Recoil/(1+A145),DPS_Base_Recoil) -> 0.05 | G145: =MAX(0.01, 0.2 - ($A145 / 10)) + (J145 * 0.15) -> 1.1551429 | H145: =(0.2 / (1 + (Max(0,$A145) * 3))) -> 0.2 | J145: =MAX(0, Max(25,(DPS_Base_Range + ((DPS_Range_Stat) / 2))) / MIN(MAX(70, (70 * (1 + ($A145 / 3)))), 120)) -> 5.7142857 | K145: =IF(A145<=DPS_Graph_Max,IF(A145>=DPS_Graph_Speed_Min,A145,),) -> -0.98 | M145: =If(DPS_Weapon_Type="远程",$E145/60+$F145*2,$E145/60+$F145+$G145/2+$H145) -> 0.21666667 | N145: =IF(DPS_Graph_Tooltip_Speed=TRUE,IF($A145<=DPS_Graph_Max,IF($A145>=DPS_Graph_Speed_Min,1/M145,),),) -> 4.6153846 | R145: =IF(DPS_Graph_Tooltip_Speed=TRUE,IF($E$8=$A145,1/$N$6,),)
A146: -0.97 | B146: =If(DPS_Weapon_Type="远程",($E146+1)/60+(ROUNDDOWN($F146*60+1,0)/60)*2,(ROUNDDOWN(($E146+1)+ROUNDDOWN($F146*60+1,0)+ROUNDDOWN($G146/2*60+1,0)+ROUNDDOWN($H146*60+1,0)+1,0))/60+If(DPS_ATK_TYPE="挥砍",1/60)+If(DPS_ATK_TYPE="挥砍/刺击",1/120))+DPS_Weapon_Randomization/60 -> 0.28833333 | C146: =IF(DPS_Graph_True_Speed=TRUE,IF($A146<=DPS_Graph_Max,IF($A146>=DPS_Graph_Speed_Min,1/B146,),),) -> 3.4682081 | D146: =IF(DPS_Graph_True_Speed=TRUE,IF($E$8=$A146,DPS_Attacks_P_Sec,),) | E146: =ROUNDDOWN(MAX(2,IF(A146>=0, DPS_Base_Wpn_Spd/(1+A146),DPS_Base_Wpn_Spd*(1+ABS(A146)))),0) -> 7 | F146: =IF(A146>=0, DPS_Base_Recoil/(1+A146),DPS_Base_Recoil) -> 0.05 | G146: =MAX(0.01, 0.2 - ($A146 / 10)) + (J146 * 0.15) -> 1.1541429 | H146: =(0.2 / (1 + (Max(0,$A146) * 3))) -> 0.2 | J146: =MAX(0, Max(25,(DPS_Base_Range + ((DPS_Range_Stat) / 2))) / MIN(MAX(70, (70 * (1 + ($A146 / 3)))), 120)) -> 5.7142857 | K146: =IF(A146<=DPS_Graph_Max,IF(A146>=DPS_Graph_Speed_Min,A146,),) -> -0.97 | M146: =If(DPS_Weapon_Type="远程",$E146/60+$F146*2,$E146/60+$F146+$G146/2+$H146) -> 0.21666667 | N146: =IF(DPS_Graph_Tooltip_Speed=TRUE,IF($A146<=DPS_Graph_Max,IF($A146>=DPS_Graph_Speed_Min,1/M146,),),) -> 4.6153846 | R146: =IF(DPS_Graph_Tooltip_Speed=TRUE,IF($E$8=$A146,1/$N$6,),)
A147: -0.96 | B147: =If(DPS_Weapon_Type="远程",($E147+1)/60+(ROUNDDOWN($F147*60+1,0)/60)*2,(ROUNDDOWN(($E147+1)+ROUNDDOWN($F147*60+1,0)+ROUNDDOWN($G147/2*60+1,0)+ROUNDDOWN($H147*60+1,0)+1,0))/60+If(DPS_ATK_TYPE="挥砍",1/60)+If(DPS_ATK_TYPE="挥砍/刺击",1/120))+DPS_Weapon_Randomization/60 -> 0.28833333 | C147: =IF(DPS_Graph_True_Speed=TRUE,IF($A147<=DPS_Graph_Max,IF($A147>=DPS_Graph_Speed_Min,1/B147,),),) -> 3.4682081 | D147: =IF(DPS_Graph_True_Speed=TRUE,IF($E$8=$A147,DPS_Attacks_P_Sec,),) | E147: =ROUNDDOWN(MAX(2,IF(A147>=0, DPS_Base_Wpn_Spd/(1+A147),DPS_Base_Wpn_Spd*(1+ABS(A147)))),0) -> 7 | F147: =IF(A147>=0, DPS_Base_Recoil/(1+A147),DPS_Base_Recoil) -> 0.05 | G147: =MAX(0.01, 0.2 - ($A147 / 10)) + (J147 * 0.15) -> 1.1531429 | H147: =(0.2 / (1 + (Max(0,$A147) * 3))) -> 0.2 | J147: =MAX(0, Max(25,(DPS_Base_Range + ((DPS_Range_Stat) / 2))) / MIN(MAX(70, (70 * (1 + ($A147 / 3)))), 120)) -> 5.7142857 | K147: =IF(A147<=DPS_Graph_Max,IF(A147>=DPS_Graph_Speed_Min,A147,),) -> -0.96 | M147: =If(DPS_Weapon_Type="远程",$E147/60+$F147*2,$E147/60+$F147+$G147/2+$H147) -> 0.21666667 | N147: =IF(DPS_Graph_Tooltip_Speed=TRUE,IF($A147<=DPS_Graph_Max,IF($A147>=DPS_Graph_Speed_Min,1/M147,),),) -> 4.6153846 | R147: =IF(DPS_Graph_Tooltip_Speed=TRUE,IF($E$8=$A147,1/$N$6,),)
A148: -0.95 | B148: =If(DPS_Weapon_Type="远程",($E148+1)/60+(ROUNDDOWN($F148*60+1,0)/60)*2,(ROUNDDOWN(($E148+1)+ROUNDDOWN($F148*60+1,0)+ROUNDDOWN($G148/2*60+1,0)+ROUNDDOWN($H148*60+1,0)+1,0))/60+If(DPS_ATK_TYPE="挥砍",1/60)+If(DPS_ATK_TYPE="挥砍/刺击",1/120))+DPS_Weapon_Randomization/60 -> 0.28833333 | C148: =IF(DPS_Graph_True_Speed=TRUE,IF($A148<=DPS_Graph_Max,IF($A148>=DPS_Graph_Speed_Min,1/B148,),),) -> 3.4682081 | D148: =IF(DPS_Graph_True_Speed=TRUE,IF($E$8=$A148,DPS_Attacks_P_Sec,),) | E148: =ROUNDDOWN(MAX(2,IF(A148>=0, DPS_Base_Wpn_Spd/(1+A148),DPS_Base_Wpn_Spd*(1+ABS(A148)))),0) -> 7 | F148: =IF(A148>=0, DPS_Base_Recoil/(1+A148),DPS_Base_Recoil) -> 0.05 | G148: =MAX(0.01, 0.2 - ($A148 / 10)) + (J148 * 0.15) -> 1.1521429 | H148: =(0.2 / (1 + (Max(0,$A148) * 3))) -> 0.2 | J148: =MAX(0, Max(25,(DPS_Base_Range + ((DPS_Range_Stat) / 2))) / MIN(MAX(70, (70 * (1 + ($A148 / 3)))), 120)) -> 5.7142857 | K148: =IF(A148<=DPS_Graph_Max,IF(A148>=DPS_Graph_Speed_Min,A148,),) -> -0.95 | M148: =If(DPS_Weapon_Type="远程",$E148/60+$F148*2,$E148/60+$F148+$G148/2+$H148) -> 0.21666667 | N148: =IF(DPS_Graph_Tooltip_Speed=TRUE,IF($A148<=DPS_Graph_Max,IF($A148>=DPS_Graph_Speed_Min,1/M148,),),) -> 4.6153846 | R148: =IF(DPS_Graph_Tooltip_Speed=TRUE,IF($E$8=$A148,1/$N$6,),)
A149: -0.94 | B149: =If(DPS_Weapon_Type="远程",($E149+1)/60+(ROUNDDOWN($F149*60+1,0)/60)*2,(ROUNDDOWN(($E149+1)+ROUNDDOWN($F149*60+1,0)+ROUNDDOWN($G149/2*60+1,0)+ROUNDDOWN($H149*60+1,0)+1,0))/60+If(DPS_ATK_TYPE="挥砍",1/60)+If(DPS_ATK_TYPE="挥砍/刺击",1/120))+DPS_Weapon_Randomization/60 -> 0.28833333 | C149: =IF(DPS_Graph_True_Speed=TRUE,IF($A149<=DPS_Graph_Max,IF($A149>=DPS_Graph_Speed_Min,1/B149,),),) -> 3.4682081 | D149: =IF(DPS_Graph_True_Speed=TRUE,IF($E$8=$A149,DPS_Attacks_P_Sec,),) | E149: =ROUNDDOWN(MAX(2,IF(A149>=0, DPS_Base_Wpn_Spd/(1+A149),DPS_Base_Wpn_Spd*(1+ABS(A149)))),0) -> 7 | F149: =IF(A149>=0, DPS_Base_Recoil/(1+A149),DPS_Base_Recoil) -> 0.05 | G149: =MAX(0.01, 0.2 - ($A149 / 10)) + (J149 * 0.15) -> 1.1511429 | H149: =(0.2 / (1 + (Max(0,$A149) * 3))) -> 0.2 | J149: =MAX(0, Max(25,(DPS_Base_Range + ((DPS_Range_Stat) / 2))) / MIN(MAX(70, (70 * (1 + ($A149 / 3)))), 120)) -> 5.7142857 | K149: =IF(A149<=DPS_Graph_Max,IF(A149>=DPS_Graph_Speed_Min,A149,),) -> -0.94 | M149: =If(DPS_Weapon_Type="远程",$E149/60+$F149*2,$E149/60+$F149+$G149/2+$H149) -> 0.21666667 | N149: =IF(DPS_Graph_Tooltip_Speed=TRUE,IF($A149<=DPS_Graph_Max,IF($A149>=DPS_Graph_Speed_Min,1/M149,),),) -> 4.6153846 | R149: =IF(DPS_Graph_Tooltip_Speed=TRUE,IF($E$8=$A149,1/$N$6,),)
A150: -0.93 | B150: =If(DPS_Weapon_Type="远程",($E150+1)/60+(ROUNDDOWN($F150*60+1,0)/60)*2,(ROUNDDOWN(($E150+1)+ROUNDDOWN($F150*60+1,0)+ROUNDDOWN($G150/2*60+1,0)+ROUNDDOWN($H150*60+1,0)+1,0))/60+If(DPS_ATK_TYPE="挥砍",1/60)+If(DPS_ATK_TYPE="挥砍/刺击",1/120))+DPS_Weapon_Randomization/60 -> 0.28833333 | C150: =IF(DPS_Graph_True_Speed=TRUE,IF($A150<=DPS_Graph_Max,IF($A150>=DPS_Graph_Speed_Min,1/B150,),),) -> 3.4682081 | D150: =IF(DPS_Graph_True_Speed=TRUE,IF($E$8=$A150,DPS_Attacks_P_Sec,),) | E150: =ROUNDDOWN(MAX(2,IF(A150>=0, DPS_Base_Wpn_Spd/(1+A150),DPS_Base_Wpn_Spd*(1+ABS(A150)))),0) -> 7 | F150: =IF(A150>=0, DPS_Base_Recoil/(1+A150),DPS_Base_Recoil) -> 0.05 | G150: =MAX(0.01, 0.2 - ($A150 / 10)) + (J150 * 0.15) -> 1.1501429 | H150: =(0.2 / (1 + (Max(0,$A150) * 3))) -> 0.2 | J150: =MAX(0, Max(25,(DPS_Base_Range + ((DPS_Range_Stat) / 2))) / MIN(MAX(70, (70 * (1 + ($A150 / 3)))), 120)) -> 5.7142857 | K150: =IF(A150<=DPS_Graph_Max,IF(A150>=DPS_Graph_Speed_Min,A150,),) -> -0.93 | M150: =If(DPS_Weapon_Type="远程",$E150/60+$F150*2,$E150/60+$F150+$G150/2+$H150) -> 0.21666667 | N150: =IF(DPS_Graph_Tooltip_Speed=TRUE,IF($A150<=DPS_Graph_Max,IF($A150>=DPS_Graph_Speed_Min,1/M150,),),) -> 4.6153846 | R150: =IF(DPS_Graph_Tooltip_Speed=TRUE,IF($E$8=$A150,1/$N$6,),)
A151: -0.92 | B151: =If(DPS_Weapon_Type="远程",($E151+1)/60+(ROUNDDOWN($F151*60+1,0)/60)*2,(ROUNDDOWN(($E151+1)+ROUNDDOWN($F151*60+1,0)+ROUNDDOWN($G151/2*60+1,0)+ROUNDDOWN($H151*60+1,0)+1,0))/60+If(DPS_ATK_TYPE="挥砍",1/60)+If(DPS_ATK_TYPE="挥砍/刺击",1/120))+DPS_Weapon_Randomization/60 -> 0.28833333 | C151: =IF(DPS_Graph_True_Speed=TRUE,IF($A151<=DPS_Graph_Max,IF($A151>=DPS_Graph_Speed_Min,1/B151,),),) -> 3.4682081 | D151: =IF(DPS_Graph_True_Speed=TRUE,IF($E$8=$A151,DPS_Attacks_P_Sec,),) | E151: =ROUNDDOWN(MAX(2,IF(A151>=0, DPS_Base_Wpn_Spd/(1+A151),DPS_Base_Wpn_Spd*(1+ABS(A151)))),0) -> 7 | F151: =IF(A151>=0, DPS_Base_Recoil/(1+A151),DPS_Base_Recoil) -> 0.05 | G151: =MAX(0.01, 0.2 - ($A151 / 10)) + (J151 * 0.15) -> 1.1491429 | H151: =(0.2 / (1 + (Max(0,$A151) * 3))) -> 0.2 | J151: =MAX(0, Max(25,(DPS_Base_Range + ((DPS_Range_Stat) / 2))) / MIN(MAX(70, (70 * (1 + ($A151 / 3)))), 120)) -> 5.7142857 | K151: =IF(A151<=DPS_Graph_Max,IF(A151>=DPS_Graph_Speed_Min,A151,),) -> -0.92 | M151: =If(DPS_Weapon_Type="远程",$E151/60+$F151*2,$E151/60+$F151+$G151/2+$H151) -> 0.21666667 | N151: =IF(DPS_Graph_Tooltip_Speed=TRUE,IF($A151<=DPS_Graph_Max,IF($A151>=DPS_Graph_Speed_Min,1/M151,),),) -> 4.6153846 | R151: =IF(DPS_Graph_Tooltip_Speed=TRUE,IF($E$8=$A151,1/$N$6,),)
A152: -0.91 | B152: =If(DPS_Weapon_Type="远程",($E152+1)/60+(ROUNDDOWN($F152*60+1,0)/60)*2,(ROUNDDOWN(($E152+1)+ROUNDDOWN($F152*60+1,0)+ROUNDDOWN($G152/2*60+1,0)+ROUNDDOWN($H152*60+1,0)+1,0))/60+If(DPS_ATK_TYPE="挥砍",1/60)+If(DPS_ATK_TYPE="挥砍/刺击",1/120))+DPS_Weapon_Randomization/60 -> 0.28833333 | C152: =IF(DPS_Graph_True_Speed=TRUE,IF($A152<=DPS_Graph_Max,IF($A152>=DPS_Graph_Speed_Min,1/B152,),),) -> 3.4682081 | D152: =IF(DPS_Graph_True_Speed=TRUE,IF($E$8=$A152,DPS_Attacks_P_Sec,),) | E152: =ROUNDDOWN(MAX(2,IF(A152>=0, DPS_Base_Wpn_Spd/(1+A152),DPS_Base_Wpn_Spd*(1+ABS(A152)))),0) -> 7 | F152: =IF(A152>=0, DPS_Base_Recoil/(1+A152),DPS_Base_Recoil) -> 0.05 | G152: =MAX(0.01, 0.2 - ($A152 / 10)) + (J152 * 0.15) -> 1.1481429 | H152: =(0.2 / (1 + (Max(0,$A152) * 3))) -> 0.2 | J152: =MAX(0, Max(25,(DPS_Base_Range + ((DPS_Range_Stat) / 2))) / MIN(MAX(70, (70 * (1 + ($A152 / 3)))), 120)) -> 5.7142857 | K152: =IF(A152<=DPS_Graph_Max,IF(A152>=DPS_Graph_Speed_Min,A152,),) -> -0.91 | M152: =If(DPS_Weapon_Type="远程",$E152/60+$F152*2,$E152/60+$F152+$G152/2+$H152) -> 0.21666667 | N152: =IF(DPS_Graph_Tooltip_Speed=TRUE,IF($A152<=DPS_Graph_Max,IF($A152>=DPS_Graph_Speed_Min,1/M152,),),) -> 4.6153846 | R152: =IF(DPS_Graph_Tooltip_Speed=TRUE,IF($E$8=$A152,1/$N$6,),)
A153: -0.9 | B153: =If(DPS_Weapon_Type="远程",($E153+1)/60+(ROUNDDOWN($F153*60+1,0)/60)*2,(ROUNDDOWN(($E153+1)+ROUNDDOWN($F153*60+1,0)+ROUNDDOWN($G153/2*60+1,0)+ROUNDDOWN($H153*60+1,0)+1,0))/60+If(DPS_ATK_TYPE="挥砍",1/60)+If(DPS_ATK_TYPE="挥砍/刺击",1/120))+DPS_Weapon_Randomization/60 -> 0.28833333 | C153: =IF(DPS_Graph_True_Speed=TRUE,IF($A153<=DPS_Graph_Max,IF($A153>=DPS_Graph_Speed_Min,1/B153,),),) -> 3.4682081 | D153: =IF(DPS_Graph_True_Speed=TRUE,IF($E$8=$A153,DPS_Attacks_P_Sec,),) | E153: =ROUNDDOWN(MAX(2,IF(A153>=0, DPS_Base_Wpn_Spd/(1+A153),DPS_Base_Wpn_Spd*(1+ABS(A153)))),0) -> 7 | F153: =IF(A153>=0, DPS_Base_Recoil/(1+A153),DPS_Base_Recoil) -> 0.05 | G153: =MAX(0.01, 0.2 - ($A153 / 10)) + (J153 * 0.15) -> 1.1471429 | H153: =(0.2 / (1 + (Max(0,$A153) * 3))) -> 0.2 | J153: =MAX(0, Max(25,(DPS_Base_Range + ((DPS_Range_Stat) / 2))) / MIN(MAX(70, (70 * (1 + ($A153 / 3)))), 120)) -> 5.7142857 | K153: =IF(A153<=DPS_Graph_Max,IF(A153>=DPS_Graph_Speed_Min,A153,),) -> -0.9 | M153: =If(DPS_Weapon_Type="远程",$E153/60+$F153*2,$E153/60+$F153+$G153/2+$H153) -> 0.21666667 | N153: =IF(DPS_Graph_Tooltip_Speed=TRUE,IF($A153<=DPS_Graph_Max,IF($A153>=DPS_Graph_Speed_Min,1/M153,),),) -> 4.6153846 | R153: =IF(DPS_Graph_Tooltip_Speed=TRUE,IF($E$8=$A153,1/$N$6,),)
A154: -0.89 | B154: =If(DPS_Weapon_Type="远程",($E154+1)/60+(ROUNDDOWN($F154*60+1,0)/60)*2,(ROUNDDOWN(($E154+1)+ROUNDDOWN($F154*60+1,0)+ROUNDDOWN($G154/2*60+1,0)+ROUNDDOWN($H154*60+1,0)+1,0))/60+If(DPS_ATK_TYPE="挥砍",1/60)+If(DPS_ATK_TYPE="挥砍/刺击",1/120))+DPS_Weapon_Randomization/60 -> 0.28833333 | C154: =IF(DPS_Graph_True_Speed=TRUE,IF($A154<=DPS_Graph_Max,IF($A154>=DPS_Graph_Speed_Min,1/B154,),),) -> 3.4682081 | D154: =IF(DPS_Graph_True_Speed=TRUE,IF($E$8=$A154,DPS_Attacks_P_Sec,),) | E154: =ROUNDDOWN(MAX(2,IF(A154>=0, DPS_Base_Wpn_Spd/(1+A154),DPS_Base_Wpn_Spd*(1+ABS(A154)))),0) -> 7 | F154: =IF(A154>=0, DPS_Base_Recoil/(1+A154),DPS_Base_Recoil) -> 0.05 | G154: =MAX(0.01, 0.2 - ($A154 / 10)) + (J154 * 0.15) -> 1.1461429 | H154: =(0.2 / (1 + (Max(0,$A154) * 3))) -> 0.2 | J154: =MAX(0, Max(25,(DPS_Base_Range + ((DPS_Range_Stat) / 2))) / MIN(MAX(70, (70 * (1 + ($A154 / 3)))), 120)) -> 5.7142857 | K154: =IF(A154<=DPS_Graph_Max,IF(A154>=DPS_Graph_Speed_Min,A154,),) -> -0.89 | M154: =If(DPS_Weapon_Type="远程",$E154/60+$F154*2,$E154/60+$F154+$G154/2+$H154) -> 0.21666667 | N154: =IF(DPS_Graph_Tooltip_Speed=TRUE,IF($A154<=DPS_Graph_Max,IF($A154>=DPS_Graph_Speed_Min,1/M154,),),) -> 4.6153846 | R154: =IF(DPS_Graph_Tooltip_Speed=TRUE,IF($E$8=$A154,1/$N$6,),)
... A1243: 10 | B1243: =If(DPS_Weapon_Type="远程",($E1243+1)/60+(ROUNDDOWN($F1243*60+1,0)/60)*2,(ROUNDDOWN(($E1243+1)+ROUNDDOWN($F1243*60+1,0)+ROUNDDOWN($G1243/2*60+1,0)+ROUNDDOWN($H1243*60+1,0)+1,0))/60+If(DPS_ATK_TYPE="挥砍",1/60)+If(DPS_ATK_TYPE="挥砍/刺击",1/120))+DPS_Weapon_Randomization/60 -> 0.105 | C1243: =IF(DPS_Graph_True_Speed=TRUE,IF($A1243<=DPS_Graph_Max,IF($A1243>=DPS_Graph_Speed_Min,1/B1243,),),) | D1243: =IF(DPS_Graph_True_Speed=TRUE,IF($E$8=$A1243,DPS_Attacks_P_Sec,),) | E1243: =ROUNDDOWN(MAX(2,IF(A1243>=0, DPS_Base_Wpn_Spd/(1+A1243),DPS_Base_Wpn_Spd*(1+ABS(A1243)))),0) -> 2 | F1243: =IF(A1243>=0, DPS_Base_Recoil/(1+A1243),DPS_Base_Recoil) -> 0.0045454545 | G1243: =MAX(0.01, 0.2 - ($A1243 / 10)) + (J1243 * 0.15) -> 0.51 | H1243: =(0.2 / (1 + (Max(0,$A1243) * 3))) -> 0.0064516129 | J1243: =MAX(0, Max(25,(DPS_Base_Range + ((DPS_Range_Stat) / 2))) / MIN(MAX(70, (70 * (1 + ($A1243 / 3)))), 120)) -> 3.3333333 | K1243: =IF(A1243<=DPS_Graph_Max,IF(A1243>=DPS_Graph_Speed_Min,A1243,),) | M1243: =If(DPS_Weapon_Type="远程",$E1243/60+$F1243*2,$E1243/60+$F1243+$G1243/2+$H1243) -> 0.042424242 | N1243: =IF(DPS_Graph_Tooltip_Speed=TRUE,IF($A1243<=DPS_Graph_Max,IF($A1243>=DPS_Graph_Speed_Min,1/M1243,),),) | R1243: =IF(DPS_Graph_Tooltip_Speed=TRUE,IF($E$8=$A1243,1/$N$6,),)

Sheet 数值设定
A1: 属性 | B1: 每升级属性值 | C1: 每属性升级数 | D1: 设定 | G1: 升级效率
A2: 闪避 | B2: =(IF($D$2="一级、二、三级升级的平均值",3)+IF($D$2="一级升级",3)+IF($D$2="ArosRising 数值",3))*IF($D$4="疯子",0,1)*IF($D$4="胖墩",0,1) -> 3 | C2: =3/B2 -> 1 | D2: ArosRising 数值 | H2: 一级 | I2: 二级 | J2: 三级 | K2: 四级
A3: 元素伤害 | B3: =(IF($D$2="一级、二、三级升级的平均值",1)+IF($D$2="一级升级",1)+IF($D$2="ArosRising 数值",1))*IF($D$4="公牛",2,1)*IF($D$4="和平主义者",0,1)*IF($D$4="近战流派",0,1)*IF($D$4="远程流派",0,1)*IF($D$4="工程师",0,1) -> 1 | C3: =3/B3 -> 3 | G3: 闪避 | H3: =IFERROR(3/$B$2,0) -> 1 | I3: =IFERROR($B$2/3,0) -> 1 | J3: =IFERROR($B$2/3,0) -> 1 | K3: =IFERROR($B$2/3,0) -> 1
A4: 护甲 | B4: =(IF($D$2="一级、二、三级升级的平均值",1)+IF($D$2="一级升级",1)+IF($D$2="ArosRising 数值",1))*IF($D$4="幽灵",0,1) -> 1 | C4: =3/B4 -> 3 | D4: 默认 | G4: 元素伤害 | H4: =IFERROR(1/$B$3,0) -> 1 | I4: =IFERROR(1/$B$3,0) -> 1 | J4: =IFERROR(1/$B$3,0) -> 1 | K4: =IFERROR(1/$B$3,0) -> 1
A5: 射程 | B5: =(IF($D$2="一级、二、三级升级的平均值",15)+IF($D$2="一级升级",15)+IF($D$2="ArosRising 数值",20))*IF($D$4="公牛",0,1)*IF($D$4="疯子",3,1)*IF($D$4="工程师",0,1) -> 20 | C5: =3/B5 -> 0.15 | G5: 护甲 | H5: =IFERROR(1/$B$4,0) -> 1 | I5: =IFERROR(1/$B$4,0) -> 1 | J5: =IFERROR(1/$B$4,0) -> 1 | K5: =IFERROR(1/$B$4,0) -> 1
A6: 暴击率 | B6: =(IF($D$2="一级、二、三级升级的平均值",(3+5+7)/6)+IF($D$2="一级升级",3)+IF($D$2="ArosRising 数值",3))*IF($D$4="公牛",3,1)*IF($D$4="法师",0,1)*IF($D$4="和平主义者",0,1)*IF($D$4="工程师",0,1) -> 3 | C6: =3/B6 -> 1 | D6: 相比100%定价的效率 | G6: 射程 | H6: =IFERROR(15/$B$5,0) -> 0.75 | I6: =IF($B$5=0,0,(30/(2*$B$5))) -> 0.75 | J6: =IF($B$5=0,0,(45/(3*$B$5))) -> 0.75 | K6: =IF($B$5=0,0,(60/(4*$B$5))) -> 0.75
A7: 近战伤害 | B7: =(IF($D$2="一级、二、三级升级的平均值",2)+IF($D$2="一级升级",2)+IF($D$2="ArosRising 数值",2))*IF($D$4="和平主义者",0,1)*IF($D$4="法师",0,1)*IF($D$4="远程流派",0,1)*IF($D$4="工程师",0,1) -> 2 | C7: =3/B7 -> 1.5 | G7: 暴击率 | H7: =IFERROR(3/$B$6,0) -> 1 | I7: =IFERROR(5/(2*$B$6),0) -> 0.83333333 | J7: =IFERROR(7/(3*$B$6),0) -> 0.77777778 | K7: =IFERROR(9/(4*$B$6),0) -> 0.75
A8: 采集 | B8: =(IF($D$2="一级、二、三级升级的平均值",(5+8+10)/6)+IF($D$2="一级升级",5)+IF($D$2="ArosRising 数值",4))*IF($D$4="猎人",0,1) -> 4 | C8: =3/B8 -> 0.75 | D8: 波数 | F8: 价格修正 | G8: 近战伤害 | H8: =IFERROR(2/$B$7,0) -> 1 | I8: =IFERROR(2/$B$7,0) -> 1 | J8: =IFERROR(2/$B$7,0) -> 1 | K8: =IFERROR(2/$B$7,0) -> 1
A9: 最大生命值 | B9: =(IF($D$2="一级、二、三级升级的平均值",3)+IF($D$2="一级升级",3)+IF($D$2="ArosRising 数值",3))*IF($D$4="公牛",1/0.75,1) -> 3 | C9: =3/B9 -> 1 | D9: 10 | F9: 1 | G9: 采集 | H9: =IFERROR(5/(1*$B$8),0) -> 1.25 | I9: =IFERROR(8/(2*$B$8),0) -> 1 | J9: =IFERROR(10/(3*$B$8),0) -> 0.83333333 | K9: =IFERROR(12/(4*$B$8),0) -> 0.75
A10: 移动速度 | B10: =(IF($D$2="一级、二、三级升级的平均值",3)+IF($D$2="一级升级",3)+IF($D$2="ArosRising 数值",3))*IF($D$4="胖墩",0,1) -> 3 | C10: =3/B10 -> 1 | D10: 商店无尽系数 | F10: 武器/道具价格 | G10: 最大生命值 | H10: =IFERROR(3/$B$9,0) -> 1 | I10: =IFERROR(3/$B$9,0) -> 1 | J10: =IFERROR(3/$B$9,0) -> 1 | K10: =IFERROR(3/$B$9,0) -> 1
A11: 生命回复 | B11: =(IF($D$2="一级、二、三级升级的平均值",(2+3+4)/6)+IF($D$2="一级升级",2)+IF($D$2="ArosRising 数值",2))*IF($D$4="胖墩",2,1) -> 2 | C11: =3/B11 -> 1.5 | D11: =1+(Max(0,((max(D9-20,0)*((D9-20)+1))/2)/100)*(2+Max(0,(D9-35)*0.2)))/5 -> 1 | F11: 1 | G11: 移动速度 | H11: =IFERROR(3/$B$10,0) -> 1 | I11: =IFERROR(3/$B$10,0) -> 1 | J11: =IFERROR(3/$B$10,0) -> 1 | K11: =IFERROR(3/$B$10,0) -> 1
A12: 幸运 | B12: =(IF($D$2="一级、二、三级升级的平均值",5)+IF($D$2="一级升级",5)+IF($D$2="ArosRising 数值",7.5))*IF($D$4="Graverobber",0,1) -> 7.5 | C12: =3/B12 -> 0.4 | D12: 道具会按"性价比"评级：即该道具每100金币（含通胀）所提供的升级等效属性数量。例如某道具提供2点护甲、售价50金币，即相当于2个升级的属性量，其性价比为 2*100/50=4。在这里你可以控制用于计算道具性价比的各项设定。 你可以选择属性价值的计算体系：使用一级升级、一至三级升级的平均值，或使用我认为最贴合实际游戏的数值。你也可以自定义数值。 你可以修改"默认"以适配不同角色，例如幽灵不使用护甲，从而看出这对道具价值的影响。此功能有时会产生误导，请谨慎使用。 你还可以修改波数，以影响诸如"私刑者之戒"这类道具，并改变通胀带来的整体物价上涨。价格低廉的道具受通胀冲击更大，在高波数时性价比会略微下降。 | G12: 生命回复 | H12: =IFERROR(2/(1*$B$11),0) -> 1 | I12: =IFERROR(3/(2*$B$11),0) -> 0.75 | J12: =IFERROR(4/(3*$B$11),0) -> 0.66666667 | K12: =IFERROR(5/(4*$B$11),0) -> 0.625
A13: 攻击速度 | B13: =(IF($D$2="一级、二、三级升级的平均值",5)+IF($D$2="一级升级",5)+IF($D$2="ArosRising 数值",5))*IF($D$4="公牛",0,1)*IF($D$4="独臂",2.5,1)*IF($D$4="工程师",0,1) -> 5 | C13: =3/B13 -> 0.6 | G13: 幸运 | H13: =IFERROR(5/$B$12,0) -> 0.66666667 | I13: =IFERROR(5/$B$12,0) -> 0.66666667 | J13: =IFERROR(5/$B$12,0) -> 0.66666667 | K13: =IFERROR(5/$B$12,0) -> 0.66666667
A14: 远程伤害 | B14: =(IF($D$2="一级、二、三级升级的平均值",1)+IF($D$2="一级升级",1)+IF($D$2="ArosRising 数值",1))*IF($D$4="疯子",0,1)*IF($D$4="和平主义者",0,1)*IF($D$4="法师",0,1)*IF($D$4="公牛",2,1)*IF($D$4="近战流派",0,1)*IF($D$4="工程师",0,1) -> 1 | C14: =3/B14 -> 3 | G14: 攻击速度 | H14: =IFERROR(5/$B$13,0) -> 1 | I14: =IFERROR(5/$B$13,0) -> 1 | J14: =IFERROR(5/$B$13,0) -> 1 | K14: =IFERROR(5/$B$13,0) -> 1
A15: 工程学 | B15: =(IF($D$2="一级、二、三级升级的平均值",(2+3+4)/6)+IF($D$2="一级升级",2)+IF($D$2="ArosRising 数值",1.5))*IF($D$4="公牛",0,1)*IF($D$4="疯子",0,1)*IF($D$4="胖墩",0,1)*IF($D$4="和平主义者",0,1)*IF($D$4="独臂",0,1)*IF($D$4="法师",0,1)*IF($D$4="猎人",0,1)*IF($D$4="近战流派",0,1)*IF($D$4="远程流派",0,1) -> 1.5 | C15: =3/B15 -> 2 | G15: 远程伤害 | H15: =IFERROR(1/$B$14,0) -> 1 | I15: =IFERROR(1/$B$14,0) -> 1 | J15: =IFERROR(1/$B$14,0) -> 1 | K15: =IFERROR(1/$B$14,0) -> 1
A16: 生命偷取 | B16: =(IF($D$2="一级、二、三级升级的平均值",1)+IF($D$2="一级升级",1)+IF($D$2="ArosRising 数值",1.5))*IF($D$4="公牛",0,1)*IF($D$4="胖墩",0,1)*IF($D$4="工程师",2,1) -> 1.5 | C16: =3/B16 -> 2 | G16: 工程学 | H16: =IFERROR(2/(1*$B$15),0) -> 1.3333333 | I16: =IFERROR(3/(2*$B$15),0) -> 1 | J16: =IFERROR(4/(3*$B$15),0) -> 0.88888889 | K16: =IFERROR(5/(4*$B$15),0) -> 0.83333333
A17: 伤害% | B17: =(IF($D$2="一级、二、三级升级的平均值",(5+8+12)/6)+IF($D$2="一级升级",5)+IF($D$2="ArosRising 数值",4))*IF($D$4="和平主义者",0,1)*IF($D$4="工程师",0,1) -> 4 | C17: =3/B17 -> 0.75 | G17: 生命偷取 | H17: =IFERROR(1/$B$16,0) -> 0.66666667 | I17: =IFERROR(1/$B$16,0) -> 0.66666667 | J17: =IFERROR(1/$B$16,0) -> 0.66666667 | K17: =IFERROR(1/$B$16,0) -> 0.66666667
A18: 道具平均基础价格 | B18: =AVERAGE('道具性价比'!D2:D300) -> 54.376884 | G18: 伤害% | H18: =IFERROR(5/(1*$B$17),0) -> 1.25 | I18: =IFERROR(8/(2*$B$17),0) -> 1 | J18: =IFERROR(12/(3*$B$17),0) -> 1 | K18: =IFERROR(16/(4*$B$17),0) -> 1
A19: 通胀后价格 | B19: =IF(D6="相比100%定价的效率", AVERAGE('道具性价比'!E2:E300)/B18/F9,AVERAGE('道具性价比'!E2:E300)/B18) -> 2.1839017

Sheet 道具性价比
A1: 道具 | B1: 等级 | C1: 游戏 | D1: 基础价格 | E1: 通胀后价格 | F1: 性价比 | G1: 性价比计算 | H1: 强度榜 | I1: 属性1 | J1: 数值 | K1: 属性2 | L1: 数值2 | M1: 属性3 | N1: 数值3 | O1: 属性4 | P1: 数值4 | Q1: 其余属性 | R1: 数值5 | S1: 性价比·全部 | T1: 性价比·正面 | U1: 性价比·部分 | V1: 备注 | W1: 全部数值 | X1: 正面数值 | Y1: 部分数值
A2: 酸液 | B2: 2 | C2: 基础 | D2: 65 | E2: =ROUNDDOWN(Shop_Endless_Factor*Shop_Price_Modifier*(D2*Shop_Weapon_Price+(0.1*D2*Shop_Weapon_Price+1)*(Shop_Wave)),0) -> 140 | F2: =IF('数值设定'!$D$4="默认",S2,S2) -> 3.1198595 | G2: 未计入击退 | H2: C | I2: 生命值+8 | J2: =IFerror(8/Shop_Max_HP,0) -> 2.6666667 | K2: 闪避-2% | L2: =IFERROR(-2/Shop_Dodge,0) -> -0.66666667 | S2: =Shop_Inflated_Price*W2/$E2*100 -> 3.1198595 | T2: =Shop_Inflated_Price*X2/$E2*100 -> 4.1598127 | W2: =J2+L2+N2+P2 -> 2 | X2: =J2 -> 2.6666667
A3: 肾上腺素 | B3: 3 | C3: 基础 | D3: 60 | E3: =ROUNDDOWN(Shop_Endless_Factor*Shop_Price_Modifier*(D3*Shop_Weapon_Price+(0.1*D3*Shop_Weapon_Price+1)*(Shop_Wave)),0) -> 130 | F3: =IF('数值设定'!$D$4="默认",T3,S3) -> 2.7998739 | G3: 性价比：未计入治疗 | H3: A | I3: 闪避+5% | J3: =IFERROR(5/Shop_Dodge,0) -> 1.6666667 | S3: =Shop_Inflated_Price*W3/$E3*100 -> 2.7998739 | T3: =Shop_Inflated_Price*X3/$E3*100 -> 2.7998739 | W3: =J3+L3+N3+P3 -> 1.6666667 | X3: =J3+L3 -> 1.6666667
A4: 异形宝宝 | B4: 3 | C4: 基础 | D4: 80 | E4: =ROUNDDOWN(Shop_Endless_Factor*Shop_Price_Modifier*(D4*Shop_Weapon_Price+(0.1*D4*Shop_Weapon_Price+1)*(Shop_Wave)),0) -> 170 | F4: =IF('数值设定'!$D$4="默认",S4,S4) -> 6.4232402 | G4: 未计入敌人生命值 | H4: D | I4: 生命值+15 | J4: =IFerror(15/Shop_Max_HP,0) -> 5 | S4: =Shop_Inflated_Price*W4/$E4*100 -> 6.4232402 | T4: =Shop_Inflated_Price*X4/$E4*100 -> 6.4232402 | W4: =J4+L4+N4+P4 -> 5 | X4: =J4+L4+N4 -> 5
A5: 异形之眼 | B5: 2 | C5: 基础 | D5: 50 | E5: =ROUNDDOWN(Shop_Endless_Factor*Shop_Price_Modifier*(D5*Shop_Weapon_Price+(0.1*D5*Shop_Weapon_Price+1)*(Shop_Wave)),0) -> 110 | F5: =S5 | G5: 无法计算 | H5: 看情况
A6: 异形魔法 | B6: 3 | C6: 基础 | D6: 85 | E6: =ROUNDDOWN(Shop_Endless_Factor*Shop_Price_Modifier*(D6*Shop_Weapon_Price+(0.1*D6*Shop_Weapon_Price+1)*(Shop_Wave)),0) -> 180 | F6: =IF('数值设定'!$D$4="默认",S6,S6) -> 3.761164 | H6: B | I6: 生命值+8 | J6: =IFerror(8/Shop_Max_HP,0) -> 2.6666667 | K6: 生命回复+3 | L6: =IFERROR(3/Shop_HP_Regen,0) -> 1.5 | M6: 幸运-8 | N6: =IFERROR(-8/Shop_Luck,0) -> -1.0666667 | S6: =Shop_Inflated_Price*W6/$E6*100 -> 3.761164 | T6: =Shop_Inflated_Price*X6/$E6*100 -> 5.0553279 | W6: =J6+L6+N6+P6 -> 3.1 | X6: =J6+L6 -> 4.1666667
A7: 异形之舌 | B7: 1 | C7: 基础 | D7: 25 | E7: =ROUNDDOWN(Shop_Endless_Factor*Shop_Price_Modifier*(D7*Shop_Weapon_Price+(0.1*D7*Shop_Weapon_Price+1)*(Shop_Wave)),0) -> 60 | G7: 无法计算 | H7: 看情况
A8: 异形蠕虫 | B8: 1 | C8: 基础 | D8: 15 | E8: =ROUNDDOWN(Shop_Endless_Factor*Shop_Price_Modifier*(D8*Shop_Weapon_Price+(0.1*D8*Shop_Weapon_Price+1)*(Shop_Wave)),0) -> 40 | F8: =IF('数值设定'!$D$4="默认",T8,S8) -> 10.919508 | G8: 未计入消耗品带来的-1治疗。 | H8: D | I8: 生命值+3 | J8: =IFerror(3/Shop_Max_HP,0) -> 1 | K8: 生命回复+2 | L8: =IFERROR(2/Shop_HP_Regen,0) -> 1 | S8: =Shop_Inflated_Price*W8/$E8*100 -> 10.919508 | T8: =Shop_Inflated_Price*X8/$E8*100 -> 10.919508 | W8: =J8+L8+N8+P8 -> 2 | X8: =J8+L8 -> 2
A9: 合金 | B9: 3 | C9: 基础 | D9: 80 | E9: =ROUNDDOWN(Shop_Endless_Factor*Shop_Price_Modifier*(D9*Shop_Weapon_Price+(0.1*D9*Shop_Weapon_Price+1)*(Shop_Wave)),0) -> 170 | F9: =IF('数值设定'!$D$4="默认",U9,S9) -> 3.4257281 | G9: 性价比：随机伤害+暴击+闪避 | H9: B | I9: 近战伤害+3 | J9: =IFerror(3/Shop_Melee_Dmg,0) -> 1.5 | K9: 远程伤害+3 | L9: =IFERROR(3/Shop_Ranged_Dmg,0) -> 3 | M9: 闪避-6% | N9: =IFERROR(-6/Shop_Dodge,0) -> -2 | O9: 暴击+5% | P9: =IFERROR(5/Shop_Crit,0) -> 1.6666667 | Q9: 工程学+3、元素伤害+3 | R9: =IFERROR(3/Shop_Engineering+2/Shop_Elemental_DMG,0) -> 4 | S9: =Shop_Inflated_Price*W9/$E9*100 -> 10.491292 | T9: =Shop_Inflated_Price*X9/$E9*100 -> 13.060588 | U9: =Shop_Inflated_Price*Y9/$E9*100 -> 3.4257281 | V9: 部分计入：远程伤害+暴击+闪避 | W9: =J9+L9+N9+P9+R9 -> 8.1666667 | X9: =J9+L9+R9+P9 -> 10.166667 | Y9: =L9+P9+N9 -> 2.6666667
A10: 铁砧 | B10: 4 | C10: 基础 | D10: 120 | E10: =ROUNDDOWN(Shop_Endless_Factor*Shop_Price_Modifier*(D10*Shop_Weapon_Price+(0.1*D10*Shop_Weapon_Price+1)*(Shop_Wave)),0) -> 250 | F10: =IF('数值设定'!$D$4="默认",S10,S10) -> 17.471213 | G10: 仅护甲，按波数设定计算（默认10） | H10: S | I10: 护甲+2/波 | J10: =IFerror(2*(20-'数值设定'!$D$9)/Shop_Armor,0) -> 20 | S10: =Shop_Inflated_Price*W10/$E10*100 -> 17.471213 | T10: =Shop_Inflated_Price*X10/$E10*100 -> 17.471213 | W10: =J10+L10+N10+P10+R10 -> 20 | X10: =J10+L10+N10+P10 -> 20
A11: 小象 | B11: 1 | C11: 基础 | D11: 22 | E11: =ROUNDDOWN(Shop_Endless_Factor*Shop_Price_Modifier*(D11*Shop_Weapon_Price+(0.1*D11*Shop_Weapon_Price+1)*(Shop_Wave)),0) -> 54 | G11: 无法计算。 | H11: 看情况 | M11: 工程学+3 | N11: =IFERROR(3/Shop_Engineering,0) -> 2
A12: 小壁虎 | B12: 1 | C12: 基础 | D12: 18 | E12: =ROUNDDOWN(Shop_Endless_Factor*Shop_Price_Modifier*(D12*Shop_Weapon_Price+(0.1*D12*Shop_Weapon_Price+1)*(Shop_Wave)),0) -> 46 | G12: 无法计算。 | H12: 看情况
A13: 长胡子的宝宝 | B13: 3 | C13: 基础 | D13: 100 | E13: =ROUNDDOWN(Shop_Endless_Factor*Shop_Price_Modifier*(D13*Shop_Weapon_Price+(0.1*D13*Shop_Weapon_Price+1)*(Shop_Wave)),0) -> 210 | G13: 无法计算。 | H13: A
A14: 袋子 | B14: 1 | C14: 基础 | D14: 15 | E14: =ROUNDDOWN(Shop_Endless_Factor*Shop_Price_Modifier*(D14*Shop_Weapon_Price+(0.1*D14*Shop_Weapon_Price+1)*(Shop_Wave)),0) -> 40 | G14: 无法计算。 | H14: S
A15: 诱饵 | B15: 2 | C15: 基础 | D15: 25 | E15: =ROUNDDOWN(Shop_Endless_Factor*Shop_Price_Modifier*(D15*Shop_Weapon_Price+(0.1*D15*Shop_Weapon_Price+1)*(Shop_Wave)),0) -> 60 | F15: =IF('数值设定'!$D$4="默认",T15,S15) -> 7.2796722 | G15: 性价比：未计入额外敌人 | H15: B | I15: 伤害+8% | J15: =IFerror(8/Shop_Dmg,0) -> 2 | S15: =Shop_Inflated_Price*W15/$E15*100 -> 7.2796722 | T15: =Shop_Inflated_Price*X15/$E15*100 -> 7.2796722 | W15: =J15+L15+N15+P15 -> 2 | X15: =J15+L15 -> 2
A16: 头巾 | B16: 3 | C16: 基础 | D16: 75 | E16: =ROUNDDOWN(Shop_Endless_Factor*Shop_Price_Modifier*(D16*Shop_Weapon_Price+(0.1*D16*Shop_Weapon_Price+1)*(Shop_Wave)),0) -> 160 | G16: 无法计算。 | H16: A
A17: 旗帜 | B17: 2 | C17: 基础 | D17: 55 | E17: =ROUNDDOWN(Shop_Endless_Factor*Shop_Price_Modifier*(D17*Shop_Weapon_Price+(0.1*D17*Shop_Weapon_Price+1)*(Shop_Wave)),0) -> 120 | F17: =IF('数值设定'!$D$4="默认",T17,S17) -> 5.4597542 | G17: 无击退 | H17: B | I17: 射程+20 | J17: =IFerror(20/Shop_Range,0) -> 1 | K17: 攻速+10 | L17: =IFERROR(10/Shop_Atk_Spd,0) -> 2 | S17: =Shop_Inflated_Price*W17/$E17*100 -> 5.4597542 | T17: =Shop_Inflated_Price*X17/$E17*100 -> 5.4597542 | U17: =Shop_Inflated_Price*Y17/$E17*100 -> 3.6398361 | V17: 部分计入：仅攻速 | W17: =J17+L17+N17+P17 -> 3 | X17: =J17+L17 -> 3 | Y17: =L17 -> 2
A18: 路障 | B18: 3 | C18: 基础 | D18: 75 | E18: =ROUNDDOWN(Shop_Endless_Factor*Shop_Price_Modifier*(D18*Shop_Weapon_Price+(0.1*D18*Shop_Weapon_Price+1)*(Shop_Wave)),0) -> 160 | F18: =IF('数值设定'!$D$4="默认",S18,S18) -> 8.6446108 | G18: 未计入站立不动、击退 | H18: 看情况 | I18: 护甲+8 | J18: =IFerror(8/Shop_Armor,0) -> 8 | K18: 移动速度-5% | L18: =IFERROR(-5/Shop_Speed,0) -> -1.6666667 | S18: =Shop_Inflated_Price*W18/$E18*100 -> 8.6446108 | T18: =Shop_Inflated_Price*X18/$E18*100 -> 10.919508 | W18: =J18+L18+N18+P18 -> 6.3333333 | X18: =J18 -> 8
A19: 蝙蝠 | B19: 1 | C19: 基础 | D19: 20 | E19: =ROUNDDOWN(Shop_Endless_Factor*Shop_Price_Modifier*(D19*Shop_Weapon_Price+(0.1*D19*Shop_Weapon_Price+1)*(Shop_Wave)),0) -> 50 | F19: =IF('数值设定'!$D$4="默认",S19,S19) -> 3.6398361 | H19: B | I19: 生命偷取+2 | J19: =IFerror(2/Shop_Life_Steal,0) -> 1.3333333 | K19: 采集-2 | L19: =IFERROR(-2/Shop_Harvesting,0) -> -0.5 | S19: =Shop_Inflated_Price*W19/$E19*100 -> 3.6398361 | T19: =Shop_Inflated_Price*X19/$E19*100 -> 5.8237378 | W19: =J19+L19+N19+P19 -> 0.83333333 | X19: =J19 -> 1.3333333
A20: 豆豆老师 | B20: 3 | C20: 基础 | D20: 70 | E20: =ROUNDDOWN(Shop_Endless_Factor*Shop_Price_Modifier*(D20*Shop_Weapon_Price+(0.1*D20*Shop_Weapon_Price+1)*(Shop_Wave)),0) -> 150 | G20: 无法计算。 | H20: B
A21: 毛线帽 | B21: 1 | C21: 基础 | D21: 20 | E21: =ROUNDDOWN(Shop_Endless_Factor*Shop_Price_Modifier*(D21*Shop_Weapon_Price+(0.1*D21*Shop_Weapon_Price+1)*(Shop_Wave)),0) -> 50 | F21: =IF('数值设定'!$D$4="默认",S21,S21) -> 4.5133968 | H21: B | I21: 移动速度+4% | J21: =IFerror(4/Shop_Speed,0) -> 1.3333333 | K21: 射程-6 | L21: =IFERROR(-6/Shop_Range,0) -> -0.3 | S21: =Shop_Inflated_Price*W21/$E21*100 -> 4.5133968 | T21: =Shop_Inflated_Price*X21/$E21*100 -> 5.8237378 | W21: =J21+L21+N21+P21 -> 1.0333333 | X21: =J21 -> 1.3333333
A22: 粗壮手臂 | B22: 4 | C22: 基础 | D22: 105 | E22: =ROUNDDOWN(Shop_Endless_Factor*Shop_Price_Modifier*(D22*Shop_Weapon_Price+(0.1*D22*Shop_Weapon_Price+1)*(Shop_Wave)),0) -> 220 | F22: =IF('数值设定'!$D$4="默认",U22,S22) -> 4.3678033 | G22: 性价比：仅单一伤害类型。无击退 | H22: A | I22: 近战伤害+12 | J22: =IFerror(12/Shop_Melee_Dmg,0) -> 6 | K22: 远程伤害+6 | L22: =IFERROR(6/Shop_Ranged_Dmg,0) -> 6 | M22: 攻击速度-3% | N22: =IFERROR(-3/Shop_Atk_Spd,0) -> -0.6 | O22: 移动速度-3% | P22: =IFERROR(-3/Shop_Speed,0) -> -1 | S22: =Shop_Inflated_Price*W22/$E22*100 -> 10.323899 | T22: =Shop_Inflated_Price*X22/$E22*100 -> 11.912191 | U22: =Shop_Inflated_Price*Y22/$E22*100 -> 4.3678033 | V22: 部分计入：仅其中一种伤害类型受益。 | W22: =J22+L22+N22+P22 -> 10.4 | X22: =J22+L22 -> 12 | Y22: =J22+N22+P22 -> 4.4
A23: 黑带 | B23: 2 | C23: 基础 | D23: 50 | E23: =ROUNDDOWN(Shop_Endless_Factor*Shop_Price_Modifier*(D23*Shop_Weapon_Price+(0.1*D23*Shop_Weapon_Price+1)*(Shop_Wave)),0) -> 110 | F23: =IF('数值设定'!$D$4="默认",S23,S23) -> 0.8603249 | G23: 未计入经验值获取与击退。 | H23: D | I23: 近战伤害+3 | J23: =IFerror(3/Shop_Melee_Dmg,0) -> 1.5 | K23: 幸运-8 | L23: =IFERROR(-8/Shop_Luck,0) -> -1.0666667 | S23: =Shop_Inflated_Price*W23/$E23*100 -> 0.8603249 | T23: =Shop_Inflated_Price*X23/$E23*100 -> 2.9780477 | W23: =J23+L23+N23+P23 -> 0.43333333 | X23: =J23 -> 1.5
A24: 眼罩 | B24: 2 | C24: 基础 | D24: 45 | E24: =ROUNDDOWN(Shop_Endless_Factor*Shop_Price_Modifier*(D24*Shop_Weapon_Price+(0.1*D24*Shop_Weapon_Price+1)*(Shop_Wave)),0) -> 100 | F24: =IF('数值设定'!$D$4="默认",S24,S24) -> 5.641746 | H24: A | I24: 暴击+5 | J24: =IFerror(5/Shop_Crit,0) -> 1.6666667 | K24: 闪避+5 | L24: =IFERROR(5/Shop_Dodge,0) -> 1.6666667 | M24: 射程-15 | N24: =IFERROR(-15/Shop_Range,0) -> -0.75 | S24: =Shop_Inflated_Price*W24/$E24*100 -> 5.641746 | T24: =Shop_Inflated_Price*X24/$E24*100 -> 7.2796722 | W24: =J24+L24+N24+P24 -> 2.5833333 | X24: =J24+L24 -> 3.3333333
A25: 献血 | B25: 3 | C25: 基础 | D25: 50 | E25: =ROUNDDOWN(Shop_Endless_Factor*Shop_Price_Modifier*(D25*Shop_Weapon_Price+(0.1*D25*Shop_Weapon_Price+1)*(Shop_Wave)),0) -> 110 | F25: =IF('数值设定'!$D$4="默认",S25,S25) -> 8.6958994 | G25: 每秒伤害按生命回复计算。 | H25: 看情况 | I25: 采集+40 | J25: =IFerror(40/Shop_Harvesting,0) -> 10 | K25: 生命回复-11,24 | L25: =IFERROR(-11.24/Shop_HP_Regen,0) -> -5.62 | S25: =Shop_Inflated_Price*W25/$E25*100 -> 8.6958994 | T25: =Shop_Inflated_Price*X25/$E25*100 -> 19.853652 | W25: =J25+L25+N25+P25 -> 4.38 | X25: =J25 -> 10
A26: 吸血水蛭 | B26: 2 | C26: 基础 | D26: 45 | E26: =ROUNDDOWN(Shop_Endless_Factor*Shop_Price_Modifier*(D26*Shop_Weapon_Price+(0.1*D26*Shop_Weapon_Price+1)*(Shop_Wave)),0) -> 100 | F26: =IF('数值设定'!$D$4="默认",S26,S26) -> 3.4578443 | H26: C | I26: 生命偷取+2 | J26: =IFerror(2/Shop_Life_Steal,0) -> 1.3333333 | K26: 生命回复+2 | L26: =IFERROR(2/Shop_HP_Regen,0) -> 1 | M26: 采集-3 | N26: =IFERROR(-3/Shop_Harvesting,0) -> -0.75 | S26: =Shop_Inflated_Price*W26/$E26*100 -> 3.4578443 | T26: =Shop_Inflated_Price*X26/$E26*100 -> 5.0957706 | U26: =Shop_Inflated_Price*Y26/$E26*100 -> 2.9118689 | V26: 部分计入：仅生命偷取 | W26: =J26+L26+N26+P26 -> 1.5833333 | X26: =J26+L26 -> 2.3333333 | Y26: =J26 -> 1.3333333
A27: 血手 | B27: 4 | C27: 基础 | D27: 110 | E27: =ROUNDDOWN(Shop_Endless_Factor*Shop_Price_Modifier*(D27*Shop_Weapon_Price+(0.1*D27*Shop_Weapon_Price+1)*(Shop_Wave)),0) -> 230 | F27: =IF('数值设定'!$D$4="默认",S27,S27) -> 5.7414458 | G27: 性价比：伤害基于12%生命偷取 | H27: S | I27: 伤害+20% | J27: =IFerror(20/Shop_Dmg,0) -> 5 | K27: 生命偷取+10 | L27: =IFerror(10/Shop_Life_Steal,0) -> 6.6666667 | M27: 生命回复-11,24 | N27: =IFERROR(-11.24/Shop_HP_Regen,0) -> -5.62 | S27: =Shop_Inflated_Price*W27/$E27*100 -> 5.7414458 | T27: =Shop_Inflated_Price*X27/$E27*100 -> 11.077762 | W27: =J27+L27+N27+P27 -> 6.0466667 | X27: =J27+L27 -> 11.666667
A28: 沸水 | B28: 1 | C28: 基础 | D28: 30 | E28: =ROUNDDOWN(Shop_Endless_Factor*Shop_Price_Modifier*(D28*Shop_Weapon_Price+(0.1*D28*Shop_Weapon_Price+1)*(Shop_Wave)),0) -> 70 | F28: =IF('数值设定'!$D$4="默认",S28,S28) -> 5.1997659 | H28: B | I28: 元素伤害+2 | J28: =IFerror(2/Shop_Elemental_DMG,0) -> 2 | K28: 生命值-1 | L28: =IFERROR(-1/Shop_Max_HP,0) -> -0.33333333 | S28: =Shop_Inflated_Price*W28/$E28*100 -> 5.1997659 | T28: =Shop_Inflated_Price*X28/$E28*100 -> 6.2397191 | W28: =J28+L28+N28+P28 -> 1.6666667 | X28: =J28 -> 2
A29: 书 | B29: 1 | C29: 基础 | D29: 8 | E29: =ROUNDDOWN(Shop_Endless_Factor*Shop_Price_Modifier*(D29*Shop_Weapon_Price+(0.1*D29*Shop_Weapon_Price+1)*(Shop_Wave)),0) -> 26 | F29: =IF('数值设定'!$D$4="默认",S29,S29) -> 5.5997479 | H29: C | I29: 工程学+1 | J29: =IFerror(1/Shop_Engineering,0) -> 0.66666667 | S29: =Shop_Inflated_Price*W29/$E29*100 -> 5.5997479 | T29: =Shop_Inflated_Price*X29/$E29*100 -> 5.5997479 | W29: =J29+L29+N29+P29 -> 0.66666667 | X29: =$J29+L29+M29+O29 -> 0.66666667
A30: 圆顶礼帽 | B30: 3 | C30: 基础 | D30: 75 | E30: =ROUNDDOWN(Shop_Endless_Factor*Shop_Price_Modifier*(D30*Shop_Weapon_Price+(0.1*D30*Shop_Weapon_Price+1)*(Shop_Wave)),0) -> 160 | F30: =IF('数值设定'!$D$4="默认",S30,S30) -> 6.1422235 | H30: A | I30: 幸运+15 | J30: =IFerror(15/Shop_Luck,0) -> 2 | K30: 采集+18 | L30: =IFERROR(18/Shop_Harvesting,0) -> 4.5 | M30: 攻击速度-5% | N30: =IFERROR(-5/Shop_Atk_Spd,0) -> -1 | O30: 暴击-3% | P30: =IFERROR(-3/Shop_Crit,0) -> -1 | S30: =Shop_Inflated_Price*W30/$E30*100 -> 6.1422235 | T30: =Shop_Inflated_Price*X30/$E30*100 -> 8.8721005 | U30: =Shop_Inflated_Price*Y30/$E30*100 -> 0 | V30: 部分计入：无采集 | W30: =J30+L30+N30+P30 -> 4.5 | X30: =J30+L30 -> 6.5 | Y30: =J30+N30+P30 -> 0
A31: 拳击手套 | B31: 1 | C31: 基础 | D31: 18 | E31: =ROUNDDOWN(Shop_Endless_Factor*Shop_Price_Modifier*(D31*Shop_Weapon_Price+(0.1*D31*Shop_Weapon_Price+1)*(Shop_Wave)),0) -> 46 | F31: =IF('数值设定'!$D$4="默认",S31,S31) -> 2.3738062 | G31: 无击退 | H31: 看情况 | I31: 近战伤害+1 | J31: =IFerror(1/Shop_Melee_Dmg,0) -> 0.5 | S31: =Shop_Inflated_Price*W31/$E31*100 -> 2.3738062 | T31: =Shop_Inflated_Price*X31/$E31*100 -> 2.3738062 | W31: =J31+L31+N31+P31 -> 0.5 | X31: =J31+L31 -> 0.5
A32: 碎牙 | B32: 1 | C32: 基础 | D32: 25 | E32: =ROUNDDOWN(Shop_Endless_Factor*Shop_Price_Modifier*(D32*Shop_Weapon_Price+(0.1*D32*Shop_Weapon_Price+1)*(Shop_Wave)),0) -> 60 | F32: =IF('数值设定'!$D$4="默认",S32,S32) -> 4.2464755 | H32: A | I32: 生命值+5 | J32: =IFerror(5/Shop_Max_HP,0) -> 1.6666667 | K32: 生命回复-1 | L32: =IFERROR(-1/Shop_HP_Regen,0) -> -0.5 | S32: =Shop_Inflated_Price*W32/$E32*100 -> 4.2464755 | T32: =Shop_Inflated_Price*X32/$E32*100 -> 6.0663935 | W32: =J32+L32+N32+P32 -> 1.1666667 | X32: =J32 -> 1.6666667
A33: 蝴蝶 | B33: 1 | C33: 基础 | D33: 30 | E33: =ROUNDDOWN(Shop_Endless_Factor*Shop_Price_Modifier*(D33*Shop_Weapon_Price+(0.1*D33*Shop_Weapon_Price+1)*(Shop_Wave)),0) -> 70 | F33: =IF('数值设定'!$D$4="默认",T33,S33) -> 4.1598127 | G33: 性价比：无负面效果 | H33: B | I33: 生命偷取+2 | J33: =IFerror(2/Shop_Life_Steal,0) -> 1.3333333 | K33: 元素伤害-1 | L33: =IFERROR(-1/Shop_Elemental_DMG,0) -> -1 | S33: =Shop_Inflated_Price*W33/$E33*100 -> 1.0399532 | T33: =Shop_Inflated_Price*X33/$E33*100 -> 4.1598127 | W33: =J33+L33+N33+P33 -> 0.33333333 | X33: =J33 -> 1.3333333
A34: 蛋糕 | B34: 1 | C34: 基础 | D34: 15 | E34: =ROUNDDOWN(Shop_Endless_Factor*Shop_Price_Modifier*(D34*Shop_Weapon_Price+(0.1*D34*Shop_Weapon_Price+1)*(Shop_Wave)),0) -> 40 | F34: =IF('数值设定'!$D$4="默认",S34,S34) -> 4.0948156 | H34: B | I34: 生命值+3 | J34: =IFerror(3/Shop_Max_HP,0) -> 1 | K34: 伤害-1% | L34: =IFERROR(-1/Shop_Dmg,0) -> -0.25 | S34: =Shop_Inflated_Price*W34/$E34*100 -> 4.0948156 | T34: =Shop_Inflated_Price*X34/$E34*100 -> 5.4597542 | W34: =J34+L34+N34+P34 -> 0.75 | X34: =J34 -> 1
A35: 营火 | B35: 2 | C35: 基础 | D35: 40 | E35: =ROUNDDOWN(Shop_Endless_Factor*Shop_Price_Modifier*(D35*Shop_Weapon_Price+(0.1*D35*Shop_Weapon_Price+1)*(Shop_Wave)),0) -> 90 | F35: =IF('数值设定'!$D$4="默认",S35,S35) -> 5.6619673 | H35: C | I35: 元素伤害+2 | J35: =IFerror(2/Shop_Elemental_DMG,0) -> 2 | K35: 生命回复+2 | L35: =IFERROR(2/Shop_HP_Regen,0) -> 1 | M35: 移动速度-2% | N35: =IFERROR(-2/Shop_Speed,0) -> -0.66666667 | S35: =Shop_Inflated_Price*W35/$E35*100 -> 5.6619673 | T35: =Shop_Inflated_Price*X35/$E35*100 -> 7.2796722 | U35: =Shop_Inflated_Price*Y35/$E35*100 -> 3.2354099 | V35: 部分计入：无生命回复 | W35: =J35+L35+N35+P35 -> 2.3333333 | X35: =J35+L35 -> 3 | Y35: =J35+N35 -> 1.3333333
A36: 蜡烛 | B36: 3 | C36: 基础 | D36: 65 | E36: =ROUNDDOWN(Shop_Endless_Factor*Shop_Price_Modifier*(D36*Shop_Weapon_Price+(0.1*D36*Shop_Weapon_Price+1)*(Shop_Wave)),0) -> 140 | F36: =IF('数值设定'!$D$4="默认",S36,S36) -> 5.0697717 | G36: -10% 敌人未计入。 | H36: 看情况 | I36: 元素伤害+4 | J36: =IFerror(4/Shop_Elemental_DMG,0) -> 4 | K36: 生命回复+1 | L36: =IFERROR(1/Shop_HP_Regen,0) -> 0.5 | M36: 伤害-5% | N36: =IFERROR(-5/Shop_Dmg,0) -> -1.25 | S36: =Shop_Inflated_Price*W36/$E36*100 -> 5.0697717 | T36: =Shop_Inflated_Price*X36/$E36*100 -> 7.0196839 | U36: =Shop_Inflated_Price*Y36/$E36*100 -> 4.2898069 | V36: 部分计入：不含生命回复 | W36: =J36+L36+N36+P36 -> 3.25 | X36: =J36+L36 -> 4.5 | Y36: =J36+N36 -> 2.75
A37: 披风 | B37: 4 | C37: 基础 | D37: 110 | E37: =ROUNDDOWN(Shop_Endless_Factor*Shop_Price_Modifier*(D37*Shop_Weapon_Price+(0.1*D37*Shop_Weapon_Price+1)*(Shop_Wave)),0) -> 230 | F37: =IF('数值设定'!$D$4="默认",U37,S37) -> 7.5961797 | G37: 性价比：仅以远程伤害为负面效果。 | H37: S | I37: 闪避+20 | J37: =IFerror(20/Shop_Dodge,0) -> 6.6666667 | K37: 生命偷取+5 | L37: =IFERROR(5/Shop_Life_Steal,0) -> 3.3333333 | M37: 远程伤害-2 | N37: =IFERROR(-2/Shop_Ranged_Dmg,0) -> -2 | O37: 近战伤害-2 | P37: =IFERROR(-2/Shop_Melee_Dmg,0) -> -1 | Q37: 元素伤害-2 | R37: =IFERROR(-2/Shop_Elemental_DMG,0) -> -2 | S37: =Shop_Inflated_Price*W37/$E37*100 -> 4.7476123 | T37: =Shop_Inflated_Price*X37/$E37*100 -> 9.4952247 | U37: =Shop_Inflated_Price*Y37/$E37*100 -> 7.5961797 | V37: 部分计入：远程伤害+生命偷取+闪避。 | W37: =J37+L37+N37+P37+R37 -> 5 | X37: =J37+L37 -> 10 | Y37: =J37+L37+N37 -> 8
A38: 变色龙 | B38: 3 | C38: 基础 | D38: 70 | E38: =ROUNDDOWN(Shop_Endless_Factor*Shop_Price_Modifier*(D38*Shop_Weapon_Price+(0.1*D38*Shop_Weapon_Price+1)*(Shop_Wave)),0) -> 150 | F38: =IF('数值设定'!$D$4="默认",S38,S38) -> 9.7062297 | G38: 未计入站立不动 | H38: 看情况 | I38: 闪避+23 | J38: =IFerror(23/Shop_Dodge,0) -> 7.6666667 | K38: 伤害-4% | L38: =IFERROR(-4/Shop_Dmg,0) -> -1 | S38: =Shop_Inflated_Price*W38/$E38*100 -> 9.7062297 | T38: =Shop_Inflated_Price*X38/$E38*100 -> 11.162164 | W38: =J38+L38+N38+P38 -> 6.6666667 | X38: =J38 -> 7.6666667
A39: 木炭 | B39: 1 | C39: 基础 | D39: 20 | E39: =ROUNDDOWN(Shop_Endless_Factor*Shop_Price_Modifier*(D39*Shop_Weapon_Price+(0.1*D39*Shop_Weapon_Price+1)*(Shop_Wave)),0) -> 50 | F39: =IF('数值设定'!$D$4="默认",U39,S39) -> 2.1839017 | G39: 性价比：仅单一伤害类型。 | H39: D | I39: 元素伤害+1 | J39: =IFerror(1/Shop_Elemental_DMG,0) -> 1 | K39: 近战伤害+2 | L39: =IFERROR(2/Shop_Melee_Dmg,0) -> 1 | M39: 采集-2 | N39: =IFERROR(-2/Shop_Harvesting,0) -> -0.5 | S39: =Shop_Inflated_Price*W39/$E39*100 -> 6.551705 | T39: =Shop_Inflated_Price*X39/$E39*100 -> 8.7356067 | U39: =Shop_Inflated_Price*Y39/$E39*100 -> 2.1839017 | V39: 部分计入：仅其中一种伤害类型。 | W39: =J39+L39+N39+P39 -> 1.5 | X39: =J39+L39 -> 2 | Y39: =J39+N39 -> 0.5
A40: 爪树 | B40: 1 | C40: 基础 | D40: 20 | E40: =ROUNDDOWN(Shop_Endless_Factor*Shop_Price_Modifier*(D40*Shop_Weapon_Price+(0.1*D40*Shop_Weapon_Price+1)*(Shop_Wave)),0) -> 50 | F40: =IF('数值设定'!$D$4="默认",S40,S40) -> 5.0957706 | H40: C | I40: 近战伤害+1 | J40: =IFerror(1/Shop_Melee_Dmg,0) -> 0.5 | K40: 暴击+3 | L40: =IFERROR(3/Shop_Crit,0) -> 1 | M40: 生命值-1 | N40: =IFERROR(-1/Shop_Max_HP,0) -> -0.33333333 | S40: =Shop_Inflated_Price*W40/$E40*100 -> 5.0957706 | T40: =Shop_Inflated_Price*X40/$E40*100 -> 6.551705 | U40: =Shop_Inflated_Price*Y40/$E40*100 -> 0.72796722 | V40: 部分计入：仅暴击与生命值 | W40: =J40+L40+N40+P40 -> 1.1666667 | X40: =J40+L40 -> 1.5 | Y40: =J40+N40 -> 0.16666667
A41: 四叶草 | B41: 3 | C41: 基础 | D41: 65 | E41: =ROUNDDOWN(Shop_Endless_Factor*Shop_Price_Modifier*(D41*Shop_Weapon_Price+(0.1*D41*Shop_Weapon_Price+1)*(Shop_Wave)),0) -> 140 | F41: =IF('数值设定'!$D$4="默认",S41,S41) -> 5.1997659 | H41: A | I41: 闪避+6% | J41: =IFERROR(6/Shop_Dodge,0) -> 2 | K41: 幸运+20 | L41: =IFERROR(20/Shop_Luck,0) -> 2.6666667 | M41: 生命偷取-4 | N41: =IFerror(-2/Shop_Life_Steal,0) -> -1.3333333 | S41: =Shop_Inflated_Price*W41/$E41*100 -> 5.1997659 | T41: =Shop_Inflated_Price*X41/$E41*100 -> 7.2796722 | U41: =Shop_Inflated_Price*Y41/$E41*100 -> 2.0799064 | V41: 部分计入：无闪避 | W41: =J41+L41+N41+P41 -> 3.3333333 | X41: =J41+L41 -> 4.6666667 | Y41: =L41+N41 -> 1.3333333
A42: 咖啡 | B42: 1 | C42: 基础 | D42: 20 | E42: =ROUNDDOWN(Shop_Endless_Factor*Shop_Price_Modifier*(D42*Shop_Weapon_Price+(0.1*D42*Shop_Weapon_Price+1)*(Shop_Wave)),0) -> 50 | F42: =IF('数值设定'!$D$4="默认",S42,S42) -> 6.551705 | H42: S | I42: 攻速+10 | J42: =IFerror(10/Shop_Atk_Spd,0) -> 2 | K42: 伤害-2% | L42: =IFERROR(-2/Shop_Dmg,0) -> -0.5 | S42: =Shop_Inflated_Price*W42/$E42*100 -> 6.551705 | T42: =Shop_Inflated_Price*X42/$E42*100 -> 8.7356067 | W42: =J42+L42+N42+P42 -> 1.5 | X42: =J42 -> 2
A43: 齿轮 | B43: 2 | C43: 基础 | D43: 35 | E43: =ROUNDDOWN(Shop_Endless_Factor*Shop_Price_Modifier*(D43*Shop_Weapon_Price+(0.1*D43*Shop_Weapon_Price+1)*(Shop_Wave)),0) -> 80 | F43: =IF('数值设定'!$D$4="默认",T43,S43) -> 7.2796722 | G43: 性价比：无负面效果 | H43: A | I43: 工程学+4 | J43: =IFerror(4/Shop_Engineering,0) -> 2.6666667 | K43: 伤害-4% | L43: =IFERROR(-4/Shop_Dmg,0) -> -1 | S43: =Shop_Inflated_Price*W43/$E43*100 -> 4.5497952 | T43: =Shop_Inflated_Price*X43/$E43*100 -> 7.2796722 | W43: =J43+L43+N43+P43 -> 1.6666667 | X43: =J43 -> 2.6666667
A44: 社区支持 | B44: 3 | C44: 基础 | D44: 75 | E44: =ROUNDDOWN(Shop_Endless_Factor*Shop_Price_Modifier*(D44*Shop_Weapon_Price+(0.1*D44*Shop_Weapon_Price+1)*(Shop_Wave)),0) -> 160 | F44: =IF('数值设定'!$D$4="默认",S44,S44) -> 5.4597542 | G44: 性价比：假定平均30个敌人。 | H44: A | I44: 攻速+30% | J44: =IFerror(30/Shop_Atk_Spd,0) -> 6 | K44: 护甲-2 | L44: =IFERROR(-2/Shop_Armor,0) -> -2 | S44: =Shop_Inflated_Price*W44/$E44*100 -> 5.4597542 | T44: =Shop_Inflated_Price*X44/$E44*100 -> 8.1896313 | W44: =J44+L44+N44+P44 -> 4 | X44: =J44 -> 6
A45: 指南针 | B45: 2 | C45: 基础 | D45: 40 | E45: =ROUNDDOWN(Shop_Endless_Factor*Shop_Price_Modifier*(D45*Shop_Weapon_Price+(0.1*D45*Shop_Weapon_Price+1)*(Shop_Wave)),0) -> 90 | F45: =IF('数值设定'!$D$4="默认",T45,S45) -> 8.8973772 | G45: 性价比：无负面效果 | H45: A | I45: 移动速度+5% | J45: =IFerror(5/Shop_Speed,0) -> 1.6666667 | K45: 工程学+3 | L45: =IFERROR(3/Shop_Engineering,0) -> 2 | M45: 暴击-3 | N45: =IFERROR(-3/Shop_Crit,0) -> -1 | S45: =Shop_Inflated_Price*W45/$E45*100 -> 6.4708198 | T45: =Shop_Inflated_Price*X45/$E45*100 -> 8.8973772 | W45: =J45+L45+N45+P45 -> 2.6666667 | X45: =J45+L45 -> 3.6666667
A46: 优惠券 | B46: 1 | C46: 基础 | D46: 15 | E46: =ROUNDDOWN(Shop_Endless_Factor*Shop_Price_Modifier*(D46*Shop_Weapon_Price+(0.1*D46*Shop_Weapon_Price+1)*(Shop_Wave)),0) -> 40 | G46: 无法计算。 | H46: S
A47: 王冠 | B47: 3 | C47: 基础 | D47: 70 | E47: =ROUNDDOWN(Shop_Endless_Factor*Shop_Price_Modifier*(D47*Shop_Weapon_Price+(0.1*D47*Shop_Weapon_Price+1)*(Shop_Wave)),0) -> 150 | G47: 无法计算。 | H47: 看情况
A48: 可爱猴子 | B48: 1 | C48: 基础 | D48: 25 | E48: =ROUNDDOWN(Shop_Endless_Factor*Shop_Price_Modifier*(D48*Shop_Weapon_Price+(0.1*D48*Shop_Weapon_Price+1)*(Shop_Wave)),0) -> 60 | G48: 无法计算。 | H48: A
A49: 电子球 | B49: 2 | C49: 基础 | D49: 30 | E49: =ROUNDDOWN(Shop_Endless_Factor*Shop_Price_Modifier*(D49*Shop_Weapon_Price+(0.1*D49*Shop_Weapon_Price+1)*(Shop_Wave)),0) -> 70 | G49: 无法计算。 | H49: 看情况
A50: 独眼蠕虫 | B50: 2 | C50: 基础 | D50: 45 | E50: =ROUNDDOWN(Shop_Endless_Factor*Shop_Price_Modifier*(D50*Shop_Weapon_Price+(0.1*D50*Shop_Weapon_Price+1)*(Shop_Wave)),0) -> 100 | F50: =IF('数值设定'!$D$4="默认",S50,S50) -> 5.241364 | H50: A | I50: 伤害+12% | J50: =IFerror(12/Shop_Dmg,0) -> 3 | K50: 射程-12 | L50: =IFERROR(-12/Shop_Range,0) -> -0.6 | S50: =Shop_Inflated_Price*W50/$E50*100 -> 5.241364 | T50: =Shop_Inflated_Price*X50/$E50*100 -> 6.551705 | W50: =J50+L50+N50+P50 -> 2.4 | X50: =J50 -> 3
A51: 危险兔子 | B51: 2 | C51: 基础 | D51: 35 | E51: =ROUNDDOWN(Shop_Endless_Factor*Shop_Price_Modifier*(D51*Shop_Weapon_Price+(0.1*D51*Shop_Weapon_Price+1)*(Shop_Wave)),0) -> 80 | G51: 无法计算。 | H51: S
A52: 劣质类固醇 | B52: 1 | C52: 基础 | D52: 20 | E52: =ROUNDDOWN(Shop_Endless_Factor*Shop_Price_Modifier*(D52*Shop_Weapon_Price+(0.1*D52*Shop_Weapon_Price+1)*(Shop_Wave)),0) -> 50 | F52: =IF('数值设定'!$D$4="默认",S52,S52) -> 4.6589902 | H52: C | I52: 近战伤害+2 | J52: =IFerror(2/Shop_Melee_Dmg,0) -> 1 | K52: 攻击速度-3% | L52: =IFERROR(-3/Shop_Atk_Spd,0) -> -0.6 | M52: 生命值+2 | N52: =IFERROR(2/Shop_Max_HP,0) -> 0.66666667 | S52: =Shop_Inflated_Price*W52/$E52*100 -> 4.6589902 | T52: =Shop_Inflated_Price*X52/$E52*100 -> 7.2796722 | W52: =J52+L52+N52+P52 -> 1.0666667 | X52: =J52+N52 -> 1.6666667
A53: 文凭 | B53: 4 | C53: 基础 | D53: 90 | E53: =ROUNDDOWN(Shop_Endless_Factor*Shop_Price_Modifier*(D53*Shop_Weapon_Price+(0.1*D53*Shop_Weapon_Price+1)*(Shop_Wave)),0) -> 190 | F53: =IF('数值设定'!$D$4="默认",S53,S53) -> 6.513391 | G53: 未计入经验值获取。 | H53: A | I53: 工程学+10 | J53: =IFerror(10/Shop_Engineering,0) -> 6.6666667 | K53: 生命值-3 | L53: =IFERROR(-3/Shop_Max_HP,0) -> -1 | S53: =Shop_Inflated_Price*W53/$E53*100 -> 6.513391 | T53: =Shop_Inflated_Price*X53/$E53*100 -> 7.6628129 | W53: =J53+L53+N53+P53 -> 5.6666667 | X53: =J53 -> 6.6666667
A54: 胶带 | B54: 1 | C54: 基础 | D54: 20 | E54: =ROUNDDOWN(Shop_Endless_Factor*Shop_Price_Modifier*(D54*Shop_Weapon_Price+(0.1*D54*Shop_Weapon_Price+1)*(Shop_Wave)),0) -> 50 | F54: =IF('数值设定'!$D$4="默认",S54,S54) -> 4.3678033 | H54: B | I54: 护甲+1 | J54: =IFerror(1/Shop_Armor,0) -> 1 | K54: 工程学+1 | L54: =IFERROR(1/Shop_Engineering,0) -> 0.66666667 | M54: 生命值-2 | N54: =IFERROR(-2/Shop_Max_HP,0) -> -0.66666667 | S54: =Shop_Inflated_Price*W54/$E54*100 -> 4.3678033 | T54: =Shop_Inflated_Price*X54/$E54*100 -> 7.2796722 | U54: =Shop_Inflated_Price*Y54/$E54*100 -> 1.4559344 | V54: 部分计入：无工程学 | W54: =J54+L54+N54+P54 -> 1 | X54: =J54+L54 -> 1.6666667 | Y54: =J54+N54 -> 0.33333333
A55: 炸药 | B55: 1 | C55: 基础 | D55: 20 | E55: =ROUNDDOWN(Shop_Endless_Factor*Shop_Price_Modifier*(D55*Shop_Weapon_Price+(0.1*D55*Shop_Weapon_Price+1)*(Shop_Wave)),0) -> 50 | F55: =IF('数值设定'!$D$4="默认",S55,S55) -> 16.379263 | G55: 假定所有伤害均为爆炸伤害 | H55: S | I55: 伤害+15% | J55: =IFerror(15/Shop_Dmg,0) -> 3.75 | S55: =Shop_Inflated_Price*W55/$E55*100 -> 16.379263 | T55: =Shop_Inflated_Price*X55/$E55*100 -> 16.379263 | W55: =J55+L55+N55+P55 -> 3.75 | X55: =J55+L55 -> 3.75
A56: 能量手环 | B56: 2 | C56: 基础 | D56: 55 | E56: =ROUNDDOWN(Shop_Endless_Factor*Shop_Price_Modifier*(D56*Shop_Weapon_Price+(0.1*D56*Shop_Weapon_Price+1)*(Shop_Wave)),0) -> 120 | F56: =IF('数值设定'!$D$4="默认",T56,S56) -> 6.0663935 | G56: 性价比：无负面效果 | H56: C | I56: 暴击+4% | J56: =IFerror(4/Shop_Crit,0) -> 1.3333333 | K56: 元素伤害+2 | L56: =IFERROR(2/Shop_Elemental_DMG,0) -> 2 | M56: 远程伤害-2 | N56: =IFERROR(-2/Shop_Ranged_Dmg,0) -> -2 | S56: =Shop_Inflated_Price*W56/$E56*100 -> 2.4265574 | T56: =Shop_Inflated_Price*X56/$E56*100 -> 6.0663935 | U56: =Shop_Inflated_Price*Y56/$E56*100 -> 2.4265574 | V56: 部分计入：仅暴击 | W56: =J56+L56+N56+P56 -> 1.3333333 | X56: =J56+L56 -> 3.3333333 | Y56: =J56 -> 1.3333333
A57: Etsy的沙发 | B57: 4 | C57: 基础 | D57: 130 | E57: =ROUNDDOWN(Shop_Endless_Factor*Shop_Price_Modifier*(D57*Shop_Weapon_Price+(0.1*D57*Shop_Weapon_Price+1)*(Shop_Wave)),0) -> 270 | F57: =IF('数值设定'!$D$4="默认",T57,S57) -> 17.525137 | G57: 性价比：视为0速度 | H57: F | I57: 生命回复+40 | J57: =IFerror(40/Shop_HP_Regen,0) -> 20 | K57: 生命值+5 | L57: =IFERROR(5/Shop_Max_HP,0) -> 1.6666667 | M57: 移动速度-20% | N57: =IFERROR(-20/Shop_Speed,0) -> -6.6666667 | S57: =Shop_Inflated_Price*W57/$E57*100 -> 12.132787 | T57: =Shop_Inflated_Price*X57/$E57*100 -> 17.525137 | W57: =J57+L57+N57+P57 -> 15 | X57: =J57+L57 -> 21.666667
A58: 外骨骼 | B58: 4 | C58: 基础 | D58: 90 | E58: =ROUNDDOWN(Shop_Endless_Factor*Shop_Price_Modifier*(D58*Shop_Weapon_Price+(0.1*D58*Shop_Weapon_Price+1)*(Shop_Wave)),0) -> 190 | F58: =IF('数值设定'!$D$4="默认",U58,S58) -> 5.7471097 | G58: 性价比：无工程学、无生命回复。 | H58: S | I58: 护甲+3 | J58: =IFerror(3/Shop_Armor,0) -> 3 | K58: 工程学+5 | L58: =IFERROR(5/Shop_Engineering,0) -> 3.3333333 | M58: 生命回复-2 | N58: =IFERROR(-2/Shop_HP_Regen,0) -> -1 | O58: 生命偷取-2 | P58: =IFERROR(-2/Shop_Life_Steal,0) -> -1.3333333 | Q58: 暴击+5、移动速度+5% | R58: =IFERROR(5/Shop_Speed+5/Shop_Crit,0) -> 3.3333333 | S58: =Shop_Inflated_Price*W58/$E58*100 -> 8.4290942 | T58: =Shop_Inflated_Price*X58/$E58*100 -> 11.111079 | U58: =Shop_Inflated_Price*Y58/$E58*100 -> 5.7471097 | V58: 部分计入：无工程学、无生命回复。 | W58: =J58+L58+N58+P58+R58 -> 7.3333333 | X58: =J58+L58+R58 -> 9.6666667 | Y58: =J58+R58+P58 -> 5
A59: 爆炸弹壳 | B59: 4 | C59: 基础 | D59: 100 | E59: =ROUNDDOWN(Shop_Endless_Factor*Shop_Price_Modifier*(D59*Shop_Weapon_Price+(0.1*D59*Shop_Weapon_Price+1)*(Shop_Wave)),0) -> 210 | F59: =IF('数值设定'!$D$4="默认",S59,S59) -> 11.699473 | G59: 假定所有伤害均为爆炸伤害，未计入爆炸范围 | H59: S | I59: 伤害-15% | J59: =IFerror(-15/Shop_Dmg,0) -> -3.75 | K59: 伤害+60% | L59: =IFERROR(60/Shop_Dmg,0) -> 15 | S59: =Shop_Inflated_Price*W59/$E59*100 -> 11.699473 | T59: =Shop_Inflated_Price*X59/$E59*100 -> 15.599298 | W59: =J59+L59+N59+P59+R59 -> 11.25 | X59: =L59 -> 15
A60: 爆炸炮塔 | B60: 4 | C60: 基础 | D60: 80 | E60: =ROUNDDOWN(Shop_Endless_Factor*Shop_Price_Modifier*(D60*Shop_Weapon_Price+(0.1*D60*Shop_Weapon_Price+1)*(Shop_Wave)),0) -> 170 | G60: 无法计算。 | H60: S
A61: 额外胃袋 | B61: 4 | C61: 基础 | D61: 100 | E61: =ROUNDDOWN(Shop_Endless_Factor*Shop_Price_Modifier*(D61*Shop_Weapon_Price+(0.1*D61*Shop_Weapon_Price+1)*(Shop_Wave)),0) -> 210 | F61: =IF('数值设定'!$D$4="默认",T61,S61) -> 31.198595 | G61: 性价比：每波+10最大生命值，使用波数设定 | H61: A | I61: 最大生命值/波+10 | J61: =IFerror(10*Max(19-Shop_Wave,0)/Shop_Max_HP,0) -> 30 | S61: =Shop_Inflated_Price*W61/$E61*100 -> 31.198595 | T61: =Shop_Inflated_Price*X61/$E61*100 -> 31.198595 | W61: =J61+L61+N61+P61 -> 30 | X61: =J61+L61 -> 30
A62: 眼部手术 | B62: 2 | C62: 基础 | D62: 60 | E62: =ROUNDDOWN(Shop_Endless_Factor*Shop_Price_Modifier*(D62*Shop_Weapon_Price+(0.1*D62*Shop_Weapon_Price+1)*(Shop_Wave)),0) -> 130 | G62: 无法计算。 | H62: B
A63: 精灵 | B63: 3 | C63: 基础 | D63: 85 | E63: =ROUNDDOWN(Shop_Endless_Factor*Shop_Price_Modifier*(D63*Shop_Weapon_Price+(0.1*D63*Shop_Weapon_Price+1)*(Shop_Wave)),0) -> 180 | F63: =IF('数值设定'!$D$4="默认",T63,S63) -> 9.0995903 | G63: 按15点生命回复计算性价比 | H63: S | I63: 生命回复+15 | J63: =IFerror(15/Shop_HP_Regen,0) -> 7.5 | S63: =Shop_Inflated_Price*W63/$E63*100 -> 9.0995903 | T63: =Shop_Inflated_Price*X63/$E63*100 -> 9.0995903 | W63: =J63+L63+N63+P63 -> 7.5 | X63: =J63+L63 -> 7.5 | Y63: =L63
A64: 肥料 | B64: 1 | C64: 基础 | D64: 15 | E64: =ROUNDDOWN(Shop_Endless_Factor*Shop_Price_Modifier*(D64*Shop_Weapon_Price+(0.1*D64*Shop_Weapon_Price+1)*(Shop_Wave)),0) -> 40 | F64: =IF('数值设定'!$D$4="默认",T64,S64) -> 10.919508 | G64: 性价比：无负面效果 | H64: S | I64: 采集+8 | J64: =IFerror(8/Shop_Harvesting,0) -> 2 | K64: 近战伤害-1 | L64: =IFERROR(-1/Shop_Melee_Dmg,0) -> -0.5 | S64: =Shop_Inflated_Price*W64/$E64*100 -> 8.1896313 | T64: =Shop_Inflated_Price*X64/$E64*100 -> 10.919508 | W64: =J64+L64+N64+P64 -> 1.5 | X64: =J64 -> 2
A65: 鱼鳍 | B65: 3 | C65: 基础 | D65: 65 | E65: =ROUNDDOWN(Shop_Endless_Factor*Shop_Price_Modifier*(D65*Shop_Weapon_Price+(0.1*D65*Shop_Weapon_Price+1)*(Shop_Wave)),0) -> 140 | F65: =IF('数值设定'!$D$4="默认",S65,S65) -> 6.6557003 | H65: A | I65: 移动速度+10% | J65: =IFerror(10/Shop_Speed,0) -> 3.3333333 | K65: 生命偷取+3 | L65: =IFERROR(3/Shop_Life_Steal,0) -> 2 | M65: 幸运-8 | N65: =IFERROR(-8/Shop_Luck,0) -> -1.0666667 | S65: =Shop_Inflated_Price*W65/$E65*100 -> 6.6557003 | T65: =Shop_Inflated_Price*X65/$E65*100 -> 8.3196254 | U65: =Shop_Inflated_Price*Y65/$E65*100 -> 5.1997659 | V65: 部分计入：仅速度 | W65: =J65+L65+N65+P65 -> 4.2666667 | X65: =J65+L65 -> 5.3333333 | Y65: =J65 -> 3.3333333
A66: 专注（单一武器类型） | B66: 4 | C66: 基础 | D66: 110 | E66: =ROUNDDOWN(Shop_Endless_Factor*Shop_Price_Modifier*(D66*Shop_Weapon_Price+(0.1*D66*Shop_Weapon_Price+1)*(Shop_Wave)),0) -> 230 | F66: =IF('数值设定'!$D$4="默认",S66,S66) -> 6.551705 | H66: A | I66: 伤害+30% | J66: =IFerror(30/Shop_Dmg,0) -> 7.5 | K66: 攻速-3 | L66: =IFERROR(-3/Shop_Atk_Spd,0) -> -0.6 | S66: =Shop_Inflated_Price*W66/$E66*100 -> 6.551705 | T66: =Shop_Inflated_Price*X66/$E66*100 -> 7.1214185 | W66: =J66+L66+N66+P66 -> 6.9 | X66: =J66 -> 7.5
A67: 油箱 | B67: 2 | C67: 基础 | D67: 45 | E67: =ROUNDDOWN(Shop_Endless_Factor*Shop_Price_Modifier*(D67*Shop_Weapon_Price+(0.1*D67*Shop_Weapon_Price+1)*(Shop_Wave)),0) -> 100 | F67: =IF('数值设定'!$D$4="默认",T67,S67) -> 8.7356067 | G67: 性价比：无负面效果 | H67: A | I67: 元素伤害+4 | J67: =IFerror(4/Shop_Elemental_DMG,0) -> 4 | K67: 近战伤害-1 | L67: =IFERROR(-1/Shop_Melee_Dmg,0) -> -0.5 | M67: 远程伤害-1 | N67: =IFERROR(-1/Shop_Ranged_Dmg,0) -> -1 | S67: =Shop_Inflated_Price*W67/$E67*100 -> 5.4597542 | T67: =Shop_Inflated_Price*X67/$E67*100 -> 8.7356067 | W67: =J67+L67+N67+P67 -> 2.5 | X67: =J67 -> 4
A68: 赌场筹码 | B68: 2 | C68: 基础 | D68: 50 | E68: =ROUNDDOWN(Shop_Endless_Factor*Shop_Price_Modifier*(D68*Shop_Weapon_Price+(0.1*D68*Shop_Weapon_Price+1)*(Shop_Wave)),0) -> 110 | F68: =IF('数值设定'!$D$4="默认",S68,S68) -> 3.3089419 | H68: C | I68: 闪避+8 | J68: =IFerror(8/Shop_Dodge,0) -> 2.6666667 | K68: 护甲-1 | L68: =IFERROR(-1/Shop_Armor,0) -> -1 | S68: =Shop_Inflated_Price*W68/$E68*100 -> 3.3089419 | T68: =Shop_Inflated_Price*X68/$E68*100 -> 5.2943071 | W68: =J68+L68+N68+P68 -> 1.6666667 | X68: =J68 -> 2.6666667
A69: 花园 | B69: 2 | C69: 基础 | D69: 50 | E69: =ROUNDDOWN(Shop_Endless_Factor*Shop_Price_Modifier*(D69*Shop_Weapon_Price+(0.1*D69*Shop_Weapon_Price+1)*(Shop_Wave)),0) -> 110 | G69: 无法计算。 | H69: C
A70: 温和异形 | B70: 1 | C70: 基础 | D70: 30 | E70: =ROUNDDOWN(Shop_Endless_Factor*Shop_Price_Modifier*(D70*Shop_Weapon_Price+(0.1*D70*Shop_Weapon_Price+1)*(Shop_Wave)),0) -> 70 | F70: =IF('数值设定'!$D$4="默认",S70,S70) -> 5.9797308 | G70: +5% 敌人未计入 | H70: A | I70: 伤害+5% | J70: =IFerror(5/Shop_Dmg,0) -> 1.25 | K70: 生命值+2 | L70: =IFERROR(2/Shop_Max_HP,0) -> 0.66666667 | S70: =Shop_Inflated_Price*W70/$E70*100 -> 5.9797308 | T70: =Shop_Inflated_Price*X70/$E70*100 -> 5.9797308 | W70: =J70+L70+N70+P70 -> 1.9166667 | X70: =J70+L70+M70+O70 -> 1.9166667
A71: 巨人腰带 | B71: 4 | C71: 基础 | D71: 110 | E71: =ROUNDDOWN(Shop_Endless_Factor*Shop_Price_Modifier*(D71*Shop_Weapon_Price+(0.1*D71*Shop_Weapon_Price+1)*(Shop_Wave)),0) -> 230 | G71: 无法计算。 | H71: A
A72: 玻璃大炮 | B72: 3 | C72: 基础 | D72: 75 | E72: =ROUNDDOWN(Shop_Endless_Factor*Shop_Price_Modifier*(D72*Shop_Weapon_Price+(0.1*D72*Shop_Weapon_Price+1)*(Shop_Wave)),0) -> 160 | F72: =IF('数值设定'!$D$4="默认",S72,S72) -> 4.4360503 | H72: 看情况 | I72: 伤害+25% | J72: =IFerror(25/Shop_Dmg,0) -> 6.25 | K72: 护甲-3 | L72: =IFERROR(-3/Shop_Armor,0) -> -3 | S72: =Shop_Inflated_Price*W72/$E72*100 -> 4.4360503 | T72: =Shop_Inflated_Price*X72/$E72*100 -> 8.5308659 | U72: =Shop_Inflated_Price*Y72/$E72*100 -> 4.4360503 | W72: =J72+L72+N72+P72 -> 3.25 | X72: =J72 -> 6.25 | Y72: =J72+L72+M72+O72 -> 3.25
A73: 眼镜 | B73: 1 | C73: 基础 | D73: 20 | E73: =ROUNDDOWN(Shop_Endless_Factor*Shop_Price_Modifier*(D73*Shop_Weapon_Price+(0.1*D73*Shop_Weapon_Price+1)*(Shop_Wave)),0) -> 50 | F73: =IF('数值设定'!$D$4="默认",S73,S73) -> 4.3678033 | H73: C | I73: 射程+20 | J73: =IFerror(20/Shop_Range,0) -> 1 | S73: =Shop_Inflated_Price*W73/$E73*100 -> 4.3678033 | T73: =Shop_Inflated_Price*X73/$E73*100 -> 4.3678033 | W73: =J73+L73+N73+P73 -> 1 | X73: =J73+L73+M73+O73 -> 1
A74: 地精 | B74: 4 | C74: 基础 | D74: 100 | E74: =ROUNDDOWN(Shop_Endless_Factor*Shop_Price_Modifier*(D74*Shop_Weapon_Price+(0.1*D74*Shop_Weapon_Price+1)*(Shop_Wave)),0) -> 210 | F74: =IF('数值设定'!$D$4="默认",U74,S74) -> 9.3595786 | G74: 未计入拾取范围。性价比：仅元素伤害 | H74: B | I74: 近战伤害+10 | J74: =IFerror(10/Shop_Melee_Dmg,0) -> 5 | K74: 元素伤害+10 | L74: =IFERROR(10/Shop_Elemental_DMG,0) -> 10 | M74: 射程-20 | N74: =IFERROR(-20/Shop_Range,0) -> -1 | S74: =Shop_Inflated_Price*W74/$E74*100 -> 14.559344 | T74: =Shop_Inflated_Price*X74/$E74*100 -> 15.599298 | U74: =Shop_Inflated_Price*Y74/$E74*100 -> 9.3595786 | V74: 部分计入：仅一种伤害类型受益。 | W74: =J74+L74+N74+P74 -> 14 | X74: =J74+L74 -> 15 | Y74: =L74+N74 -> 9
A75: 山羊头骨 | B75: 1 | C75: 基础 | D75: 25 | E75: =ROUNDDOWN(Shop_Endless_Factor*Shop_Price_Modifier*(D75*Shop_Weapon_Price+(0.1*D75*Shop_Weapon_Price+1)*(Shop_Wave)),0) -> 60 | F75: =IF('数值设定'!$D$4="默认",S75,S75) -> 3.0331968 | H75: C | I75: 近战伤害+3 | J75: =IFerror(3/Shop_Melee_Dmg,0) -> 1.5 | K75: 暴击-2% | L75: =IFERROR(-2/Shop_Crit,0) -> -0.66666667 | S75: =Shop_Inflated_Price*W75/$E75*100 -> 3.0331968 | T75: =Shop_Inflated_Price*X75/$E75*100 -> 5.4597542 | W75: =J75+L75+N75+P75 -> 0.83333333 | X75: =J75 -> 1.5
A76: Grind的魔法叶 | B76: 4 | C76: 基础 | D76: 110 | E76: =ROUNDDOWN(Shop_Endless_Factor*Shop_Price_Modifier*(D76*Shop_Weapon_Price+(0.1*D76*Shop_Weapon_Price+1)*(Shop_Wave)),0) -> 230 | F76: =IF('数值设定'!$D$4="默认",T76,S76) -> 18.515688 | G76: 各属性按波数设定计算（默认10） | H76: S | I76: 生命值/波+3 | J76: =IFerror(3*Max(19-Shop_Wave,0)/Shop_Max_HP,0) -> 9 | K76: 生命回复+1/波 | L76: =IFERROR(1*Max(19-Shop_Wave,0)/Shop_HP_Regen,0) -> 4.5 | M76: 生命偷取+1/波 | N76: =IFERROR(1*Max(19-Shop_Wave,0)/Shop_Life_Steal,0) -> 6 | S76: =Shop_Inflated_Price*W76/$E76*100 -> 18.515688 | T76: =Shop_Inflated_Price*X76/$E76*100 -> 18.515688 | U76: =Shop_Inflated_Price*Y76/$E76*100 -> 14.242837 | V76: 部分计入：仅生命偷取 | W76: =J76+L76+N76+P76 -> 19.5 | X76: =J76+L76+N76 -> 19.5 | Y76: =J76+N76 -> 15
A77: 软糖狂战士 | B77: 1 | C77: 基础 | D77: 25 | E77: =ROUNDDOWN(Shop_Endless_Factor*Shop_Price_Modifier*(D77*Shop_Weapon_Price+(0.1*D77*Shop_Weapon_Price+1)*(Shop_Wave)),0) -> 60 | F77: =IF('数值设定'!$D$4="默认",S77,S77) -> 4.5497952 | H77: D | I77: 攻速+5% | J77: =IFerror(5/Shop_Atk_Spd,0) -> 1 | K77: 射程+25 | L77: =IFERROR(25/Shop_Range,0) -> 1.25 | M77: 护甲-1 | N77: =IFERROR(-1/Shop_Armor,0) -> -1 | S77: =Shop_Inflated_Price*W77/$E77*100 -> 4.5497952 | T77: =Shop_Inflated_Price*X77/$E77*100 -> 8.1896313 | V77: 部分计入：不计射程 | W77: =J77+L77+N77+P77 -> 1.25 | X77: =J77+L77 -> 2.25 | Y77: =J77+N77 -> 0
A78: 手铐 | B78: 3 | C78: 基础 | D78: 80 | E78: =ROUNDDOWN(Shop_Endless_Factor*Shop_Price_Modifier*(D78*Shop_Weapon_Price+(0.1*D78*Shop_Weapon_Price+1)*(Shop_Wave)),0) -> 170 | F78: =IF('数值设定'!$D$4="默认",U78,S78) -> 10.277184 | G78: 未计入生命上限：仅远程伤害。 | H78: A | I78: 近战伤害+8 | J78: =IFerror(8/Shop_Melee_Dmg,0) -> 4 | K78: 远程伤害+8 | L78: =IFERROR(8/Shop_Ranged_Dmg,0) -> 8 | M78: 元素伤害+8 | N78: =IFERROR(8/Shop_Elemental_DMG,0) -> 8 | S78: =Shop_Inflated_Price*W78/$E78*100 -> 25.692961 | T78: =Shop_Inflated_Price*X78/$E78*100 -> 25.692961 | U78: =Shop_Inflated_Price*Y78/$E78*100 -> 10.277184 | V78: 部分计入：仅远程伤害。 | W78: =J78+L78+N78+P78 -> 20 | X78: =J78+L78+N78 -> 20 | Y78: =L78 -> 8
A79: 头部创伤 | B79: 1 | C79: 基础 | D79: 25 | E79: =ROUNDDOWN(Shop_Endless_Factor*Shop_Price_Modifier*(D79*Shop_Weapon_Price+(0.1*D79*Shop_Weapon_Price+1)*(Shop_Wave)),0) -> 60 | F79: =IF('数值设定'!$D$4="默认",S79,S79) -> 4.0038197 | H79: B | I79: 伤害+6% | J79: =IFerror(6/Shop_Dmg,0) -> 1.5 | K79: 射程-8 | L79: =IFERROR(-8/Shop_Range,0) -> -0.4 | S79: =Shop_Inflated_Price*W79/$E79*100 -> 4.0038197 | T79: =Shop_Inflated_Price*X79/$E79*100 -> 5.4597542 | W79: =J79+L79+N79+P79 -> 1.1 | X79: =J79 -> 1.5
A80: 重型子弹 | B80: 4 | C80: 基础 | D80: 100 | E80: =ROUNDDOWN(Shop_Endless_Factor*Shop_Price_Modifier*(D80*Shop_Weapon_Price+(0.1*D80*Shop_Weapon_Price+1)*(Shop_Wave)),0) -> 210 | F80: =IF('数值设定'!$D$4="默认",S80,S80) -> 5.5464169 | H80: B | I80: 远程伤害+5 | J80: =IFerror(5/Shop_Ranged_Dmg,0) -> 5 | K80: 伤害+10% | L80: =IFERROR(10/Shop_Dmg,0) -> 2.5 | M80: 射程+10 | N80: =IFERROR(10/Shop_Range,0) -> 0.5 | O80: 攻击速度-5% | P80: =IFERROR(-5/Shop_Atk_Spd,0) -> -1 | Q80: 暴击-5% | R80: =IFERROR(-5/Shop_Crit,0) -> -1.6666667 | S80: =Shop_Inflated_Price*W80/$E80*100 -> 5.5464169 | T80: =Shop_Inflated_Price*X80/$E80*100 -> 8.3196254 | U80: =Shop_Inflated_Price*Y80/$E80*100 -> 6.7596957 | V80: 部分计入：无射程、无暴击。 | W80: =J80+L80+N80+P80+R80 -> 5.3333333 | X80: =J80+L80+N80 -> 8 | Y80: =J80+L80+P80 -> 6.5
A81: 刺猬 | B81: 1 | C81: 基础 | D81: 30 | E81: =ROUNDDOWN(Shop_Endless_Factor*Shop_Price_Modifier*(D81*Shop_Weapon_Price+(0.1*D81*Shop_Weapon_Price+1)*(Shop_Wave)),0) -> 70 | F81: =IF('数值设定'!$D$4="默认",U81,S81) -> 3.1198595 | G81: 性价比：仅单一伤害类型。无生命回复 | H81: C | I81: 近战伤害+2 | J81: =IFerror(2/Shop_Melee_Dmg,0) -> 1 | K81: 远程伤害+1 | L81: =IFERROR(1/Shop_Ranged_Dmg,0) -> 1 | M81: 生命回复-1 | N81: =IFERROR(-1/Shop_HP_Regen,0) -> -0.5 | S81: =Shop_Inflated_Price*W81/$E81*100 -> 4.6797893 | T81: =Shop_Inflated_Price*X81/$E81*100 -> 6.2397191 | U81: =Shop_Inflated_Price*Y81/$E81*100 -> 3.1198595 | V81: 部分计入：仅其中一种伤害类型。未计入回复。 | W81: =J81+L81+N81+P81 -> 1.5 | X81: =J81+L81 -> 2 | Y81: =J81 -> 1
A82: 头盔 | B82: 1 | C82: 基础 | D82: 15 | E82: =ROUNDDOWN(Shop_Endless_Factor*Shop_Price_Modifier*(D82*Shop_Weapon_Price+(0.1*D82*Shop_Weapon_Price+1)*(Shop_Wave)),0) -> 40 | F82: =IF('数值设定'!$D$4="默认",S82,S82) -> 1.8199181 | H82: F | I82: 护甲+1 | J82: =IFerror(1/Shop_Armor,0) -> 1 | K82: 移动速度-2% | L82: =IFERROR(-2/Shop_Speed,0) -> -0.66666667 | S82: =Shop_Inflated_Price*W82/$E82*100 -> 1.8199181 | T82: =Shop_Inflated_Price*X82/$E82*100 -> 5.4597542 | W82: =J82+L82+N82+P82 -> 0.33333333 | X82: =J82 -> 1
A83: 猎人战利品 | B83: 3 | C83: 基础 | D83: 55 | E83: =ROUNDDOWN(Shop_Endless_Factor*Shop_Price_Modifier*(D83*Shop_Weapon_Price+(0.1*D83*Shop_Weapon_Price+1)*(Shop_Wave)),0) -> 120 | G83: 无法计算。 | H83: S
A84: 改良工具 | B84: 3 | C84: 基础 | D84: 70 | E84: =ROUNDDOWN(Shop_Endless_Factor*Shop_Price_Modifier*(D84*Shop_Weapon_Price+(0.1*D84*Shop_Weapon_Price+1)*(Shop_Wave)),0) -> 150 | F84: =IF('数值设定'!$D$4="默认",T84,S84) -> 2.9118689 | G84: 性价比：未计入特殊能力。 | H84: A | I84: 攻速+10% | J84: =IFERROR(10/Shop_Atk_Spd,0) -> 2 | S84: =Shop_Inflated_Price*W84/$E84*100 -> 2.9118689 | T84: =Shop_Inflated_Price*X84/$E84*100 -> 2.9118689 | W84: =J84+L84+N84+P84 -> 2 | X84: =J84+L84 -> 2
A85: 燃烧炮塔 | B85: 2 | C85: 基础 | D85: 40 | E85: =ROUNDDOWN(Shop_Endless_Factor*Shop_Price_Modifier*(D85*Shop_Weapon_Price+(0.1*D85*Shop_Weapon_Price+1)*(Shop_Wave)),0) -> 90 | G85: 无法计算。 | H85: B
A86: 注射剂 | B86: 1 | C86: 基础 | D86: 20 | E86: =ROUNDDOWN(Shop_Endless_Factor*Shop_Price_Modifier*(D86*Shop_Weapon_Price+(0.1*D86*Shop_Weapon_Price+1)*(Shop_Wave)),0) -> 50 | F86: =IF('数值设定'!$D$4="默认",S86,S86) -> 4.731787 | H86: D | I86: 伤害+7% | J86: =IFerror(7/Shop_Dmg,0) -> 1.75 | K86: 生命值-2 | L86: =IFERROR(-2/Shop_Max_HP,0) -> -0.66666667 | S86: =Shop_Inflated_Price*W86/$E86*100 -> 4.731787 | T86: =Shop_Inflated_Price*X86/$E86*100 -> 7.6436559 | W86: =J86+L86+N86+P86 -> 1.0833333 | X86: =J86 -> 1.75
A87: 疯狂 | B87: 1 | C87: 基础 | D87: 20 | E87: =ROUNDDOWN(Shop_Endless_Factor*Shop_Price_Modifier*(D87*Shop_Weapon_Price+(0.1*D87*Shop_Weapon_Price+1)*(Shop_Wave)),0) -> 50 | F87: =IF('数值设定'!$D$4="默认",S87,S87) -> 5.4597542 | H87: B | I87: 暴击+6 | J87: =IFerror(6/Shop_Crit,0) -> 2 | K87: 伤害-3% | L87: =IFERROR(-3/Shop_Dmg,0) -> -0.75 | S87: =Shop_Inflated_Price*W87/$E87*100 -> 5.4597542 | T87: =Shop_Inflated_Price*X87/$E87*100 -> 8.7356067 | W87: =J87+L87+N87+P87 -> 1.25 | X87: =J87 -> 2
A88: 喷气背包 | B88: 4 | C88: 基础 | D88: 100 | E88: =ROUNDDOWN(Shop_Endless_Factor*Shop_Price_Modifier*(D88*Shop_Weapon_Price+(0.1*D88*Shop_Weapon_Price+1)*(Shop_Wave)),0) -> 210 | F88: =IF('数值设定'!$D$4="默认",S88,S88) -> 5.893068 | H88: B | I88: 移动速度+15% | J88: =IFerror(15/Shop_Speed,0) -> 5 | K88: 闪避+10 | L88: =IFERROR(10/Shop_Dodge,0) -> 3.3333333 | M88: 生命值-5 | N88: =IFERROR(-5/Shop_Max_HP,0) -> -1.6666667 | O88: 护甲-1 | P88: =IFERROR(-1/Shop_Armor,0) -> -1 | S88: =Shop_Inflated_Price*W88/$E88*100 -> 5.893068 | T88: =Shop_Inflated_Price*X88/$E88*100 -> 8.6662765 | W88: =J88+L88+N88+P88 -> 5.6666667 | X88: =J88+L88 -> 8.3333333
A89: 地雷 | B89: 1 | C89: 基础 | D89: 15 | E89: =ROUNDDOWN(Shop_Endless_Factor*Shop_Price_Modifier*(D89*Shop_Weapon_Price+(0.1*D89*Shop_Weapon_Price+1)*(Shop_Wave)),0) -> 40 | G89: 无法计算。 | H89: 看情况
A90: 激光炮塔 | B90: 3 | C90: 基础 | D90: 65 | E90: =ROUNDDOWN(Shop_Endless_Factor*Shop_Price_Modifier*(D90*Shop_Weapon_Price+(0.1*D90*Shop_Weapon_Price+1)*(Shop_Wave)),0) -> 140 | G90: 无法计算。 | H90: B
A91: 皮背心 | B91: 2 | C91: 基础 | D91: 45 | E91: =ROUNDDOWN(Shop_Endless_Factor*Shop_Price_Modifier*(D91*Shop_Weapon_Price+(0.1*D91*Shop_Weapon_Price+1)*(Shop_Wave)),0) -> 100 | F91: =IF('数值设定'!$D$4="默认",S91,S91) -> 6.551705 | H91: A | I91: 护甲+2 | J91: =IFerror(2/Shop_Armor,0) -> 2 | K91: 闪避+6 | L91: =IFERROR(6/Shop_Dodge,0) -> 2 | M91: 生命值-3 | N91: =IFERROR(-3/Shop_Max_HP,0) -> -1 | S91: =Shop_Inflated_Price*W91/$E91*100 -> 6.551705 | T91: =Shop_Inflated_Price*X91/$E91*100 -> 8.7356067 | U91: =Shop_Inflated_Price*Y91/$E91*100 -> 2.1839017 | V91: 部分计入：无闪避。 | W91: =J91+L91+N91+P91 -> 3 | X91: =J91+L91 -> 4 | Y91: =J91+N91 -> 1
A92: 柠檬水 | B92: 1 | C92: 基础 | D92: 15 | E92: =ROUNDDOWN(Shop_Endless_Factor*Shop_Price_Modifier*(D92*Shop_Weapon_Price+(0.1*D92*Shop_Weapon_Price+1)*(Shop_Wave)),0) -> 40 | G92: 无法计算。 | H92: A
A93: 镜片 | B93: 1 | C93: 基础 | D93: 20 | E93: =ROUNDDOWN(Shop_Endless_Factor*Shop_Price_Modifier*(D93*Shop_Weapon_Price+(0.1*D93*Shop_Weapon_Price+1)*(Shop_Wave)),0) -> 50 | F93: =IF('数值设定'!$D$4="默认",S93,S93) -> 3.2758525 | H93: B | I93: 远程伤害+1 | J93: =IFerror(1/Shop_Ranged_Dmg,0) -> 1 | K93: 射程-5 | L93: =IFERROR(-5/Shop_Range,0) -> -0.25 | S93: =Shop_Inflated_Price*W93/$E93*100 -> 3.2758525 | T93: =Shop_Inflated_Price*X93/$E93*100 -> 4.3678033 | W93: =J93+L93+N93+P93 -> 0.75 | X93: =J93 -> 1
A94: 小青蛙 | B94: 2 | C94: 基础 | D94: 45 | E94: =ROUNDDOWN(Shop_Endless_Factor*Shop_Price_Modifier*(D94*Shop_Weapon_Price+(0.1*D94*Shop_Weapon_Price+1)*(Shop_Wave)),0) -> 100 | F94: =IF('数值设定'!$D$4="默认",S94,S94) -> 3.2758525 | G94: 未计入拾取范围。 | H94: C | I94: 采集+10 | J94: =IFerror(10/Shop_Harvesting,0) -> 2.5 | K94: 闪避-3% | L94: =IFERROR(-3/Shop_Dodge,0) -> -1 | S94: =Shop_Inflated_Price*W94/$E94*100 -> 3.2758525 | T94: =Shop_Inflated_Price*X94/$E94*100 -> 5.4597542 | W94: =J94+L94+N94+P94 -> 1.5 | X94: =J94 -> 2.5
A95: 小肌肉男 | B95: 2 | C95: 基础 | D95: 50 | E95: =ROUNDDOWN(Shop_Endless_Factor*Shop_Price_Modifier*(D95*Shop_Weapon_Price+(0.1*D95*Shop_Weapon_Price+1)*(Shop_Wave)),0) -> 110 | F95: =IF('数值设定'!$D$4="默认",S95,S95) -> 4.7979658 | H95: B | I95: 近战伤害+3 | J95: =IFerror(3/Shop_Melee_Dmg,0) -> 1.5 | K95: 生命值+5 | L95: =IFERROR(5/Shop_Max_HP,0) -> 1.6666667 | M95: 射程-15 | N95: =IFERROR(-15/Shop_Range,0) -> -0.75 | S95: =Shop_Inflated_Price*W95/$E95*100 -> 4.7979658 | T95: =Shop_Inflated_Price*X95/$E95*100 -> 6.2869897 | W95: =J95+L95+N95+P95 -> 2.4166667 | X95: =J95+L95 -> 3.1666667
A96: 迷路小鸭 | B96: 1 | C96: 基础 | D96: 25 | E96: =ROUNDDOWN(Shop_Endless_Factor*Shop_Price_Modifier*(D96*Shop_Weapon_Price+(0.1*D96*Shop_Weapon_Price+1)*(Shop_Wave)),0) -> 60 | F96: =IF('数值设定'!$D$4="默认",T96,S96) -> 3.8824919 | G96: 性价比：无负面效果 | H96: B | I96: 幸运+8 | J96: =IFerror(8/Shop_Luck,0) -> 1.0666667 | K96: 元素伤害-1 | L96: =IFERROR(-1/Shop_Elemental_DMG,0) -> -1 | S96: =Shop_Inflated_Price*W96/$E96*100 -> 0.24265574 | T96: =Shop_Inflated_Price*X96/$E96*100 -> 3.8824919 | W96: =J96+L96+N96+P96 -> 0.066666667 | X96: =J96 -> 1.0666667
A97: 幸运符 | B97: 3 | C97: 基础 | D97: 75 | E97: =ROUNDDOWN(Shop_Endless_Factor*Shop_Price_Modifier*(D97*Shop_Weapon_Price+(0.1*D97*Shop_Weapon_Price+1)*(Shop_Wave)),0) -> 160 | F97: =IF('数值设定'!$D$4="默认",U97,S97) -> 4.0948156 | G97: 性价比：仅一种伤害类型作为负面效果 | H97: A | I97: 幸运+30 | J97: =IFerror(30/Shop_Luck,0) -> 4 | K97: 近战伤害-2 | L97: =IFERROR(-2/Shop_Melee_Dmg,0) -> -1 | M97: 远程伤害-1 | N97: =IFERROR(-1/Shop_Ranged_Dmg,0) -> -1 | S97: =Shop_Inflated_Price*W97/$E97*100 -> 2.7298771 | T97: =Shop_Inflated_Price*X97/$E97*100 -> 5.4597542 | U97: =Shop_Inflated_Price*Y97/$E97*100 -> 4.0948156 | V97: 部分计入：仅幸运和其中一种伤害类型。 | W97: =J97+L97+N97+P97 -> 2 | X97: =J97 -> 4 | Y97: =J97+L97 -> 3
A98: 伐木工衬衫 | B98: 1 | C98: 基础 | D98: 15 | E98: =ROUNDDOWN(Shop_Endless_Factor*Shop_Price_Modifier*(D98*Shop_Weapon_Price+(0.1*D98*Shop_Weapon_Price+1)*(Shop_Wave)),0) -> 40 | G98: 无法计算。 | H98: 看情况
A99: 鱼饵 | B99: 2 | C99: 基础 | D99: 34 | E99: =ROUNDDOWN(Shop_Endless_Factor*Shop_Price_Modifier*(D99*Shop_Weapon_Price+(0.1*D99*Shop_Weapon_Price+1)*(Shop_Wave)),0) -> 78 | F99: =IF('数值设定'!$D$4="默认",T99,S99) -> 2.7998739 | G99: 未计入生成的战利品 | H99: S | I99: 生命回复+2 | J99: =IFerror(2/Shop_HP_Regen,0) -> 1 | S99: =Shop_Inflated_Price*W99/$E99*100 -> 2.7998739 | T99: =Shop_Inflated_Price*X99/$E99*100 -> 2.7998739 | W99: =J99+L99+N99+P99 -> 1 | X99: =J99+L99 -> 1 | Y99: =L99
A100: 猛犸象 | B100: 4 | C100: 基础 | D100: 110 | E100: =ROUNDDOWN(Shop_Endless_Factor*Shop_Price_Modifier*(D100*Shop_Weapon_Price+(0.1*D100*Shop_Weapon_Price+1)*(Shop_Wave)),0) -> 230 | F100: =IF('数值设定'!$D$4="默认",U100,S100) -> 6.6466573 | G100: 性价比：无生命回复 | H100: B | I100: 近战伤害+20 | J100: =IFerror(20/Shop_Melee_Dmg,0) -> 10 | K100: 生命回复+5 | L100: =IFERROR(5/Shop_HP_Regen,0) -> 2.5 | M100: 伤害-8% | N100: =IFERROR(-8/Shop_Dmg,0) -> -2 | O100: 移动速度-3% | P100: =IFERROR(-3/Shop_Speed,0) -> -1 | S100: =Shop_Inflated_Price*W100/$E100*100 -> 9.0204634 | T100: =Shop_Inflated_Price*X100/$E100*100 -> 11.869031 | U100: =Shop_Inflated_Price*Y100/$E100*100 -> 6.6466573 | V100: 部分计入：无生命回复 | W100: =J100+L100+N100+P100 -> 9.5 | X100: =J100+L100 -> 12.5 | Y100: =J100+P100+N100 -> 7
...

Sheet 计算器
A1: 有效生命值计算器 | E1: 道具价格计算器 | K1: 采集计算器
E3: 基础价格 | F3: 波数 | G3: 价格% | H3: 回收% | I3: 军火商价格 | J3: 难度 - 通胀 | K3: 起始波数 | L3: 默认 | N3: 默认+王冠 | P3: 农夫 | R3: 农夫+王冠 | T3: 企业家 | V3: 企业家+王冠
E4: 15 | F4: 1 | G4: 1 | H4: 1 | I4: 0.05 | J4: 噩梦 | L4: 起始采集 | M4: 利息率 | N4: 起始采集 | O4: 利息率 | P4: 起始采集 | Q4: 利息率 | R4: 起始采集 | S4: 利息率 | T4: 起始采集 | U4: 利息率 | V4: 起始采集 | W4: 利息率
A5: 护甲 | B5: 伤害减免 | C5: 护甲有效生命系数 | D5: 提示框% | J5: 通胀 | K5: 1 | L5: 5 | M5: 0.05 | N5: 5 | O5: 0.13 | P5: 5 | Q5: 0.08 | R5: 5 | S5: 0.16 | T5: 7.5 | U5: 0.05 | V5: 7.5 | W5: 0.13
A6: 5 | B6: =If(A6>-0.5, 1-1/(1+ 2/30*A6),-(1-1/(1+ 2/30*(-A6)))) -> 0.25 | C6: =1/(1-B6) -> 1.3333333 | D6: =Round(B6,2) -> 0.25 | J6: =IF(J4="噩梦",0.11,0.1) -> 0.11 | K6: 波数 | L6: 当前采集 | M6: 累计获得 | N6: 当前采集 | O6: 累计获得 | P6: 当前采集 | Q6: 累计获得 | R6: 当前采集 | S6: 累计获得 | T6: 当前采集 | U6: 累计获得 | V6: 当前采集 | W6: 累计获得
A7: 闪避% | C7: 闪避有效生命系数 | E7: 结果 | K7: =K5 -> 1 | L7: =L5 -> 5 | M7: 0 | N7: =N5 -> 5 | O7: 0 | P7: =P5 -> 5 | Q7: 0 | R7: =R5 -> 5 | S7: 0 | T7: =T5 -> 7.5 | U7: 0 | V7: =V5 -> 7.5 | W7: 0
A8: 50 | C8: =If(A8>0, 1/(1-A8/100),1) -> 2 | E8: 商店价格 | F8: 回收价值 | G8: 军火商价格 | H8: 军火商回收 | I8: 恶魔价格 | J8: 无尽系数 /5 | K8: =K7+1 -> 2 | L8: =If(L7>0,If($K8>20 ,L7-ROUNDUP(L7*0.2,0) , L7+ROUNDUP(L7*M$5,0)),L7) -> 6 | M8: =M7+L7 -> 5 | N8: =If(N7>0,If($K8>20 ,N7-ROUNDUP(N7*0.2,0) , N7+ROUNDUP(N7*O$5,0)),N7) -> 6 | O8: =O7+N7 -> 5 | P8: =If(P7>0,If($K8>20 ,P7-ROUNDUP(P7*0.2,0) , P7+ROUNDUP(P7*Q$5,0)),P7) -> 6 | Q8: =Q7+P7 -> 5 | R8: =If(R7>0,If($K8>20 ,R7-ROUNDUP(R7*0.2,0) , R7+ROUNDUP(R7*S$5,0)),R7) -> 6 | S8: =S7+R7 -> 5 | T8: =If(T7>0,If($K8>20 ,T7-ROUNDUP(T7*0.2,0)*1.5 , T7+ROUNDUP(T7*U$5,0)*1.5),T7) -> 9 | U8: =U7+T7 -> 7.5 | V8: =If(V7>0,If($K8>20 ,V7-ROUNDUP(V7*0.2,0)*1.5 , V7+ROUNDUP(V7*W$5,0)*1.5),V7) -> 9 | W8: =W7+V7 -> 7.5
C9: 有效生命系数 | E9: =MAX(1,ROUNDDOWN(G4*(1+J9)*(E4+(J6*E4+1)*(F4)),0)) -> 17 | F9: =MAX(1,ROUNDDOWN(MIN(1,H4)*ROUNDDOWN(G4*(E4+(J6*E4+1)*(F4)),0),0)) -> 17 | G9: =MAX(1,ROUNDDOWN(G4*(1+J9)*(I4*E4+(J6*I4*E4+1)*(F4)),0)) -> 1 | H9: =MAX(1,ROUNDDOWN(MIN(1,H4)*ROUNDDOWN(G4*(I4*E4+(J6*I4*E4+1)*(F4)),0),0)) -> 1 | I9: =ROUNDUP(E9/20,0) & "生命值" -> 1点生命 | J9: =Max(0,((max(F4-20,0)*((F4-20)+1))/2)/100)*(2+Max(0,(F4-35)*0.2))/5 -> 0 | K9: =K8+1 -> 3 | L9: =If(L8>0,If($K9>20 ,L8-ROUNDUP(L8*0.2,0) , L8+ROUNDUP(L8*M$5,0)),L8) -> 7 | M9: =M8+L8 -> 11 | N9: =If(N8>0,If($K9>20 ,N8-ROUNDUP(N8*0.2,0) , N8+ROUNDUP(N8*O$5,0)),N8) -> 7 | O9: =O8+N8 -> 11 | P9: =If(P8>0,If($K9>20 ,P8-ROUNDUP(P8*0.2,0) , P8+ROUNDUP(P8*Q$5,0)),P8) -> 7 | Q9: =Q8+P8 -> 11 | R9: =If(R8>0,If($K9>20 ,R8-ROUNDUP(R8*0.2,0) , R8+ROUNDUP(R8*S$5,0)),R8) -> 7 | S9: =S8+R8 -> 11 | T9: =If(T8>0,If($K9>20 ,T8-ROUNDUP(T8*0.2,0)*1.5 , T8+ROUNDUP(T8*U$5,0)*1.5),T8) -> 10.5 | U9: =U8+T8 -> 16.5 | V9: =If(V8>0,If($K9>20 ,V8-ROUNDUP(V8*0.2,0)*1.5 , V8+ROUNDUP(V8*W$5,0)*1.5),V8) -> 12 | W9: =W8+V8 -> 16.5
C10: =C6*C8 -> 2.6666667 | K10: =K9+1 -> 4 | L10: =If(L9>0,If($K10>20 ,L9-ROUNDUP(L9*0.2,0) , L9+ROUNDUP(L9*M$5,0)),L9) -> 8 | M10: =M9+L9 -> 18 | N10: =If(N9>0,If($K10>20 ,N9-ROUNDUP(N9*0.2,0) , N9+ROUNDUP(N9*O$5,0)),N9) -> 8 | O10: =O9+N9 -> 18 | P10: =If(P9>0,If($K10>20 ,P9-ROUNDUP(P9*0.2,0) , P9+ROUNDUP(P9*Q$5,0)),P9) -> 8 | Q10: =Q9+P9 -> 18 | R10: =If(R9>0,If($K10>20 ,R9-ROUNDUP(R9*0.2,0) , R9+ROUNDUP(R9*S$5,0)),R9) -> 9 | S10: =S9+R9 -> 18 | T10: =If(T9>0,If($K10>20 ,T9-ROUNDUP(T9*0.2,0)*1.5 , T9+ROUNDUP(T9*U$5,0)*1.5),T9) -> 12 | U10: =U9+T9 -> 27 | V10: =If(V9>0,If($K10>20 ,V9-ROUNDUP(V9*0.2,0)*1.5 , V9+ROUNDUP(V9*W$5,0)*1.5),V9) -> 15 | W10: =W9+V9 -> 28.5
A11: 最大生命值 | C11: 有效最大生命 | E11: 波数=1代表第一家商店、第一次刷新，以及第1波掉落箱开出的道具。 基础价格是你在 Wiki 或道具性价比表中看到的价格。 价格100%即你的商店价格，参见你的次要属性。例如配合"储蓄者"设为150%，配合"优惠券"设为95%、90%…75%，或配合"企业家"设为75%。 | K11: =K10+1 -> 5 | L11: =If(L10>0,If($K11>20 ,L10-ROUNDUP(L10*0.2,0) , L10+ROUNDUP(L10*M$5,0)),L10) -> 9 | M11: =M10+L10 -> 26 | N11: =If(N10>0,If($K11>20 ,N10-ROUNDUP(N10*0.2,0) , N10+ROUNDUP(N10*O$5,0)),N10) -> 10 | O11: =O10+N10 -> 26 | P11: =If(P10>0,If($K11>20 ,P10-ROUNDUP(P10*0.2,0) , P10+ROUNDUP(P10*Q$5,0)),P10) -> 9 | Q11: =Q10+P10 -> 26 | R11: =If(R10>0,If($K11>20 ,R10-ROUNDUP(R10*0.2,0) , R10+ROUNDUP(R10*S$5,0)),R10) -> 11 | S11: =S10+R10 -> 27 | T11: =If(T10>0,If($K11>20 ,T10-ROUNDUP(T10*0.2,0)*1.5 , T10+ROUNDUP(T10*U$5,0)*1.5),T10) -> 13.5 | U11: =U10+T10 -> 39 | V11: =If(V10>0,If($K11>20 ,V10-ROUNDUP(V10*0.2,0)*1.5 , V10+ROUNDUP(V10*W$5,0)*1.5),V10) -> 18 | W11: =W10+V10 -> 43.5
A12: 100 | C12: =C10*A12 -> 266.66667 | K12: =K11+1 -> 6 | L12: =If(L11>0,If($K12>20 ,L11-ROUNDUP(L11*0.2,0) , L11+ROUNDUP(L11*M$5,0)),L11) -> 10 | M12: =M11+L11 -> 35 | N12: =If(N11>0,If($K12>20 ,N11-ROUNDUP(N11*0.2,0) , N11+ROUNDUP(N11*O$5,0)),N11) -> 12 | O12: =O11+N11 -> 36 | P12: =If(P11>0,If($K12>20 ,P11-ROUNDUP(P11*0.2,0) , P11+ROUNDUP(P11*Q$5,0)),P11) -> 10 | Q12: =Q11+P11 -> 35 | R12: =If(R11>0,If($K12>20 ,R11-ROUNDUP(R11*0.2,0) , R11+ROUNDUP(R11*S$5,0)),R11) -> 13 | S12: =S11+R11 -> 38 | T12: =If(T11>0,If($K12>20 ,T11-ROUNDUP(T11*0.2,0)*1.5 , T11+ROUNDUP(T11*U$5,0)*1.5),T11) -> 15 | U12: =U11+T11 -> 52.5 | V12: =If(V11>0,If($K12>20 ,V11-ROUNDUP(V11*0.2,0)*1.5 , V11+ROUNDUP(V11*W$5,0)*1.5),V11) -> 22.5 | W12: =W11+V11 -> 61.5
A13: 生命回复 | B13: 每秒生命 | C13: 每秒有效生命 | K13: =K12+1 -> 7 | L13: =If(L12>0,If($K13>20 ,L12-ROUNDUP(L12*0.2,0) , L12+ROUNDUP(L12*M$5,0)),L12) -> 11 | M13: =M12+L12 -> 45 | N13: =If(N12>0,If($K13>20 ,N12-ROUNDUP(N12*0.2,0) , N12+ROUNDUP(N12*O$5,0)),N12) -> 14 | O13: =O12+N12 -> 48 | P13: =If(P12>0,If($K13>20 ,P12-ROUNDUP(P12*0.2,0) , P12+ROUNDUP(P12*Q$5,0)),P12) -> 11 | Q13: =Q12+P12 -> 45 | R13: =If(R12>0,If($K13>20 ,R12-ROUNDUP(R12*0.2,0) , R12+ROUNDUP(R12*S$5,0)),R12) -> 16 | S13: =S12+R12 -> 51 | T13: =If(T12>0,If($K13>20 ,T12-ROUNDUP(T12*0.2,0)*1.5 , T12+ROUNDUP(T12*U$5,0)*1.5),T12) -> 16.5 | U13: =U12+T12 -> 67.5 | V13: =If(V12>0,If($K13>20 ,V12-ROUNDUP(V12*0.2,0)*1.5 , V12+ROUNDUP(V12*W$5,0)*1.5),V12) -> 27 | W13: =W12+V12 -> 84
A14: 10 | B14: =1/(5 / (1 + (abs(A14 - 1) / 2.25))) -> 1 | C14: =B14*C10 -> 2.6666667 | K14: =K13+1 -> 8 | L14: =If(L13>0,If($K14>20 ,L13-ROUNDUP(L13*0.2,0) , L13+ROUNDUP(L13*M$5,0)),L13) -> 12 | M14: =M13+L13 -> 56 | N14: =If(N13>0,If($K14>20 ,N13-ROUNDUP(N13*0.2,0) , N13+ROUNDUP(N13*O$5,0)),N13) -> 16 | O14: =O13+N13 -> 62 | P14: =If(P13>0,If($K14>20 ,P13-ROUNDUP(P13*0.2,0) , P13+ROUNDUP(P13*Q$5,0)),P13) -> 12 | Q14: =Q13+P13 -> 56 | R14: =If(R13>0,If($K14>20 ,R13-ROUNDUP(R13*0.2,0) , R13+ROUNDUP(R13*S$5,0)),R13) -> 19 | S14: =S13+R13 -> 67 | T14: =If(T13>0,If($K14>20 ,T13-ROUNDUP(T13*0.2,0)*1.5 , T13+ROUNDUP(T13*U$5,0)*1.5),T13) -> 18 | U14: =U13+T13 -> 84 | V14: =If(V13>0,If($K14>20 ,V13-ROUNDUP(V13*0.2,0)*1.5 , V13+ROUNDUP(V13*W$5,0)*1.5),V13) -> 33 | W14: =W13+V13 -> 111
K15: =K14+1 -> 9 | L15: =If(L14>0,If($K15>20 ,L14-ROUNDUP(L14*0.2,0) , L14+ROUNDUP(L14*M$5,0)),L14) -> 13 | M15: =M14+L14 -> 68 | N15: =If(N14>0,If($K15>20 ,N14-ROUNDUP(N14*0.2,0) , N14+ROUNDUP(N14*O$5,0)),N14) -> 19 | O15: =O14+N14 -> 78 | P15: =If(P14>0,If($K15>20 ,P14-ROUNDUP(P14*0.2,0) , P14+ROUNDUP(P14*Q$5,0)),P14) -> 13 | Q15: =Q14+P14 -> 68 | R15: =If(R14>0,If($K15>20 ,R14-ROUNDUP(R14*0.2,0) , R14+ROUNDUP(R14*S$5,0)),R14) -> 23 | S15: =S14+R14 -> 86 | T15: =If(T14>0,If($K15>20 ,T14-ROUNDUP(T14*0.2,0)*1.5 , T14+ROUNDUP(T14*U$5,0)*1.5),T14) -> 19.5 | U15: =U14+T14 -> 102 | V15: =If(V14>0,If($K15>20 ,V14-ROUNDUP(V14*0.2,0)*1.5 , V14+ROUNDUP(V14*W$5,0)*1.5),V14) -> 40.5 | W15: =W14+V14 -> 144
A16: 百分比通关计算器 | K16: =K15+1 -> 10 | L16: =If(L15>0,If($K16>20 ,L15-ROUNDUP(L15*0.2,0) , L15+ROUNDUP(L15*M$5,0)),L15) -> 14 | M16: =M15+L15 -> 81 | N16: =If(N15>0,If($K16>20 ,N15-ROUNDUP(N15*0.2,0) , N15+ROUNDUP(N15*O$5,0)),N15) -> 22 | O16: =O15+N15 -> 97 | P16: =If(P15>0,If($K16>20 ,P15-ROUNDUP(P15*0.2,0) , P15+ROUNDUP(P15*Q$5,0)),P15) -> 15 | Q16: =Q15+P15 -> 81 | R16: =If(R15>0,If($K16>20 ,R15-ROUNDUP(R15*0.2,0) , R15+ROUNDUP(R15*S$5,0)),R15) -> 27 | S16: =S15+R15 -> 109 | T16: =If(T15>0,If($K16>20 ,T15-ROUNDUP(T15*0.2,0)*1.5 , T15+ROUNDUP(T15*U$5,0)*1.5),T15) -> 21 | U16: =U15+T15 -> 121.5 | V16: =If(V15>0,If($K16>20 ,V15-ROUNDUP(V15*0.2,0)*1.5 , V15+ROUNDUP(V15*W$5,0)*1.5),V15) -> 49.5 | W16: =W15+V15 -> 184.5
A17: 本项计算百分比通关的难度百分比（各数值的几何平均数）。数值可设在25%到200%之间，速度的上限为150%。 | E17: 刷新 | K17: =K16+1 -> 11 | L17: =If(L16>0,If($K17>20 ,L16-ROUNDUP(L16*0.2,0) , L16+ROUNDUP(L16*M$5,0)),L16) -> 15 | M17: =M16+L16 -> 95 | N17: =If(N16>0,If($K17>20 ,N16-ROUNDUP(N16*0.2,0) , N16+ROUNDUP(N16*O$5,0)),N16) -> 25 | O17: =O16+N16 -> 119 | P17: =If(P16>0,If($K17>20 ,P16-ROUNDUP(P16*0.2,0) , P16+ROUNDUP(P16*Q$5,0)),P16) -> 17 | Q17: =Q16+P16 -> 96 | R17: =If(R16>0,If($K17>20 ,R16-ROUNDUP(R16*0.2,0) , R16+ROUNDUP(R16*S$5,0)),R16) -> 32 | S17: =S16+R16 -> 136 | T17: =If(T16>0,If($K17>20 ,T16-ROUNDUP(T16*0.2,0)*1.5 , T16+ROUNDUP(T16*U$5,0)*1.5),T16) -> 24 | U17: =U16+T16 -> 142.5 | V17: =If(V16>0,If($K17>20 ,V16-ROUNDUP(V16*0.2,0)*1.5 , V16+ROUNDUP(V16*W$5,0)*1.5),V16) -> 60 | W17: =W16+V16 -> 234
K18: =K17+1 -> 12 | L18: =If(L17>0,If($K18>20 ,L17-ROUNDUP(L17*0.2,0) , L17+ROUNDUP(L17*M$5,0)),L17) -> 16 | M18: =M17+L17 -> 110 | N18: =If(N17>0,If($K18>20 ,N17-ROUNDUP(N17*0.2,0) , N17+ROUNDUP(N17*O$5,0)),N17) -> 29 | O18: =O17+N17 -> 144 | P18: =If(P17>0,If($K18>20 ,P17-ROUNDUP(P17*0.2,0) , P17+ROUNDUP(P17*Q$5,0)),P17) -> 19 | Q18: =Q17+P17 -> 113 | R18: =If(R17>0,If($K18>20 ,R17-ROUNDUP(R17*0.2,0) , R17+ROUNDUP(R17*S$5,0)),R17) -> 38 | S18: =S17+R17 -> 168 | T18: =If(T17>0,If($K18>20 ,T17-ROUNDUP(T17*0.2,0)*1.5 , T17+ROUNDUP(T17*U$5,0)*1.5),T17) -> 27 | U18: =U17+T17 -> 166.5 | V18: =If(V17>0,If($K18>20 ,V17-ROUNDUP(V17*0.2,0)*1.5 , V17+ROUNDUP(V17*W$5,0)*1.5),V17) -> 72 | W18: =W17+V17 -> 294
E19: 波数 | F19: 刷新价格减免 | H19: 第N次刷新 | J19: 无尽系数 | K19: =K18+1 -> 13 | L19: =If(L18>0,If($K19>20 ,L18-ROUNDUP(L18*0.2,0) , L18+ROUNDUP(L18*M$5,0)),L18) -> 17 | M19: =M18+L18 -> 126 | N19: =If(N18>0,If($K19>20 ,N18-ROUNDUP(N18*0.2,0) , N18+ROUNDUP(N18*O$5,0)),N18) -> 33 | O19: =O18+N18 -> 173 | P19: =If(P18>0,If($K19>20 ,P18-ROUNDUP(P18*0.2,0) , P18+ROUNDUP(P18*Q$5,0)),P18) -> 21 | Q19: =Q18+P18 -> 132 | R19: =If(R18>0,If($K19>20 ,R18-ROUNDUP(R18*0.2,0) , R18+ROUNDUP(R18*S$5,0)),R18) -> 45 | S19: =S18+R18 -> 206 | T19: =If(T18>0,If($K19>20 ,T18-ROUNDUP(T18*0.2,0)*1.5 , T18+ROUNDUP(T18*U$5,0)*1.5),T18) -> 30 | U19: =U18+T18 -> 193.5 | V19: =If(V18>0,If($K19>20 ,V18-ROUNDUP(V18*0.2,0)*1.5 , V18+ROUNDUP(V18*W$5,0)*1.5),V18) -> 87 | W19: =W18+V18 -> 366
E20: 1 | F20: 0 | H20: 1 | J20: =Max(0,((max(E20-20,0)*((E20-20)+1))/2)/100)*(2+Max(0,(E20-35)*0.2)) -> 0 | K20: =K19+1 -> 14 | L20: =If(L19>0,If($K20>20 ,L19-ROUNDUP(L19*0.2,0) , L19+ROUNDUP(L19*M$5,0)),L19) -> 18 | M20: =M19+L19 -> 143 | N20: =If(N19>0,If($K20>20 ,N19-ROUNDUP(N19*0.2,0) , N19+ROUNDUP(N19*O$5,0)),N19) -> 38 | O20: =O19+N19 -> 206 | P20: =If(P19>0,If($K20>20 ,P19-ROUNDUP(P19*0.2,0) , P19+ROUNDUP(P19*Q$5,0)),P19) -> 23 | Q20: =Q19+P19 -> 153 | R20: =If(R19>0,If($K20>20 ,R19-ROUNDUP(R19*0.2,0) , R19+ROUNDUP(R19*S$5,0)),R19) -> 53 | S20: =S19+R19 -> 251 | T20: =If(T19>0,If($K20>20 ,T19-ROUNDUP(T19*0.2,0)*1.5 , T19+ROUNDUP(T19*U$5,0)*1.5),T19) -> 33 | U20: =U19+T19 -> 223.5 | V20: =If(V19>0,If($K20>20 ,V19-ROUNDUP(V19*0.2,0)*1.5 , V19+ROUNDUP(V19*W$5,0)*1.5),V19) -> 105 | W20: =W19+V19 -> 453
A21: 敌人生命值 | B21: 敌人伤害 | C21: 敌人速度 | E21: 首次刷新 | F21: 刷新费用增幅 | H21: 第N次刷新价格 | K21: =K20+1 -> 15 | L21: =If(L20>0,If($K21>20 ,L20-ROUNDUP(L20*0.2,0) , L20+ROUNDUP(L20*M$5,0)),L20) -> 19 | M21: =M20+L20 -> 161 | N21: =If(N20>0,If($K21>20 ,N20-ROUNDUP(N20*0.2,0) , N20+ROUNDUP(N20*O$5,0)),N20) -> 43 | O21: =O20+N20 -> 244 | P21: =If(P20>0,If($K21>20 ,P20-ROUNDUP(P20*0.2,0) , P20+ROUNDUP(P20*Q$5,0)),P20) -> 25 | Q21: =Q20+P20 -> 176 | R21: =If(R20>0,If($K21>20 ,R20-ROUNDUP(R20*0.2,0) , R20+ROUNDUP(R20*S$5,0)),R20) -> 62 | S21: =S20+R20 -> 304 | T21: =If(T20>0,If($K21>20 ,T20-ROUNDUP(T20*0.2,0)*1.5 , T20+ROUNDUP(T20*U$5,0)*1.5),T20) -> 36 | U21: =U20+T20 -> 256.5 | V21: =If(V20>0,If($K21>20 ,V20-ROUNDUP(V20*0.2,0)*1.5 , V20+ROUNDUP(V20*W$5,0)*1.5),V20) -> 126 | W21: =W20+V20 -> 558
A22: 2 | B22: 2 | C22: 1.5 | E22: =ROUNDUP(MAX(0.1,1-F20)*(F22+Rounddown(E20*0.75,0)),0) -> 1 | F22: =Rounddown(max(1,0.4*E20*(1+J20)^0.5),0) -> 1 | H22: =E22+F22*(H20-1) -> 1 | K22: =K21+1 -> 16 | L22: =If(L21>0,If($K22>20 ,L21-ROUNDUP(L21*0.2,0) , L21+ROUNDUP(L21*M$5,0)),L21) -> 20 | M22: =M21+L21 -> 180 | N22: =If(N21>0,If($K22>20 ,N21-ROUNDUP(N21*0.2,0) , N21+ROUNDUP(N21*O$5,0)),N21) -> 49 | O22: =O21+N21 -> 287 | P22: =If(P21>0,If($K22>20 ,P21-ROUNDUP(P21*0.2,0) , P21+ROUNDUP(P21*Q$5,0)),P21) -> 27 | Q22: =Q21+P21 -> 201 | R22: =If(R21>0,If($K22>20 ,R21-ROUNDUP(R21*0.2,0) , R21+ROUNDUP(R21*S$5,0)),R21) -> 72 | S22: =S21+R21 -> 366 | T22: =If(T21>0,If($K22>20 ,T21-ROUNDUP(T21*0.2,0)*1.5 , T21+ROUNDUP(T21*U$5,0)*1.5),T21) -> 39 | U22: =U21+T21 -> 292.5 | V22: =If(V21>0,If($K22>20 ,V21-ROUNDUP(V21*0.2,0)*1.5 , V21+ROUNDUP(V21*W$5,0)*1.5),V21) -> 151.5 | W22: =W21+V21 -> 684
A23: 难度 | K23: =K22+1 -> 17 | L23: =If(L22>0,If($K23>20 ,L22-ROUNDUP(L22*0.2,0) , L22+ROUNDUP(L22*M$5,0)),L22) -> 21 | M23: =M22+L22 -> 200 | N23: =If(N22>0,If($K23>20 ,N22-ROUNDUP(N22*0.2,0) , N22+ROUNDUP(N22*O$5,0)),N22) -> 56 | O23: =O22+N22 -> 336 | P23: =If(P22>0,If($K23>20 ,P22-ROUNDUP(P22*0.2,0) , P22+ROUNDUP(P22*Q$5,0)),P22) -> 30 | Q23: =Q22+P22 -> 228 | R23: =If(R22>0,If($K23>20 ,R22-ROUNDUP(R22*0.2,0) , R22+ROUNDUP(R22*S$5,0)),R22) -> 84 | S23: =S22+R22 -> 438 | T23: =If(T22>0,If($K23>20 ,T22-ROUNDUP(T22*0.2,0)*1.5 , T22+ROUNDUP(T22*U$5,0)*1.5),T22) -> 42 | U23: =U22+T22 -> 331.5 | V23: =If(V22>0,If($K23>20 ,V22-ROUNDUP(V22*0.2,0)*1.5 , V22+ROUNDUP(V22*W$5,0)*1.5),V22) -> 181.5 | W23: =W22+V22 -> 835.5
B24: =ROUND((A22*B22*C22)^(1/3),2) -> 1.82 | K24: =K23+1 -> 18 | L24: =If(L23>0,If($K24>20 ,L23-ROUNDUP(L23*0.2,0) , L23+ROUNDUP(L23*M$5,0)),L23) -> 23 | M24: =M23+L23 -> 221 | N24: =If(N23>0,If($K24>20 ,N23-ROUNDUP(N23*0.2,0) , N23+ROUNDUP(N23*O$5,0)),N23) -> 64 | O24: =O23+N23 -> 392 | P24: =If(P23>0,If($K24>20 ,P23-ROUNDUP(P23*0.2,0) , P23+ROUNDUP(P23*Q$5,0)),P23) -> 33 | Q24: =Q23+P23 -> 258 | R24: =If(R23>0,If($K24>20 ,R23-ROUNDUP(R23*0.2,0) , R23+ROUNDUP(R23*S$5,0)),R23) -> 98 | S24: =S23+R23 -> 522 | T24: =If(T23>0,If($K24>20 ,T23-ROUNDUP(T23*0.2,0)*1.5 , T23+ROUNDUP(T23*U$5,0)*1.5),T23) -> 46.5 | U24: =U23+T23 -> 373.5 | V24: =If(V23>0,If($K24>20 ,V23-ROUNDUP(V23*0.2,0)*1.5 , V23+ROUNDUP(V23*W$5,0)*1.5),V23) -> 217.5 | W24: =W23+V23 -> 1017
K25: =K24+1 -> 19 | L25: =If(L24>0,If($K25>20 ,L24-ROUNDUP(L24*0.2,0) , L24+ROUNDUP(L24*M$5,0)),L24) -> 25 | M25: =M24+L24 -> 244 | N25: =If(N24>0,If($K25>20 ,N24-ROUNDUP(N24*0.2,0) , N24+ROUNDUP(N24*O$5,0)),N24) -> 73 | O25: =O24+N24 -> 456 | P25: =If(P24>0,If($K25>20 ,P24-ROUNDUP(P24*0.2,0) , P24+ROUNDUP(P24*Q$5,0)),P24) -> 36 | Q25: =Q24+P24 -> 291 | R25: =If(R24>0,If($K25>20 ,R24-ROUNDUP(R24*0.2,0) , R24+ROUNDUP(R24*S$5,0)),R24) -> 114 | S25: =S24+R24 -> 620 | T25: =If(T24>0,If($K25>20 ,T24-ROUNDUP(T24*0.2,0)*1.5 , T24+ROUNDUP(T24*U$5,0)*1.5),T24) -> 51 | U25: =U24+T24 -> 420 | V25: =If(V24>0,If($K25>20 ,V24-ROUNDUP(V24*0.2,0)*1.5 , V24+ROUNDUP(V24*W$5,0)*1.5),V24) -> 261 | W25: =W24+V24 -> 1234.5
A26: 黑帮被抓几率 | K26: =K25+1 -> 20 | L26: =If(L25>0,If($K26>20 ,L25-ROUNDUP(L25*0.2,0) , L25+ROUNDUP(L25*M$5,0)),L25) -> 27 | M26: =M25+L25 -> 269 | N26: =If(N25>0,If($K26>20 ,N25-ROUNDUP(N25*0.2,0) , N25+ROUNDUP(N25*O$5,0)),N25) -> 83 | O26: =O25+N25 -> 529 | P26: =If(P25>0,If($K26>20 ,P25-ROUNDUP(P25*0.2,0) , P25+ROUNDUP(P25*Q$5,0)),P25) -> 39 | Q26: =Q25+P25 -> 327 | R26: =If(R25>0,If($K26>20 ,R25-ROUNDUP(R25*0.2,0) , R25+ROUNDUP(R25*S$5,0)),R25) -> 133 | S26: =S25+R25 -> 734 | T26: =If(T25>0,If($K26>20 ,T25-ROUNDUP(T25*0.2,0)*1.5 , T25+ROUNDUP(T25*U$5,0)*1.5),T25) -> 55.5 | U26: =U25+T25 -> 471 | V26: =If(V25>0,If($K26>20 ,V25-ROUNDUP(V25*0.2,0)*1.5 , V25+ROUNDUP(V25*W$5,0)*1.5),V25) -> 312 | W26: =W25+V25 -> 1495.5
A27: 本项计算从偷窃道具中获得精英怪的概率 | K27: =K26+1 -> 21 | L27: =If(L26>0,If($K27>20 ,L26-ROUNDUP(L26*0.2,0) , L26+ROUNDUP(L26*M$5,0)),L26) -> 21 | M27: =M26+L26 -> 296 | N27: =If(N26>0,If($K27>20 ,N26-ROUNDUP(N26*0.2,0) , N26+ROUNDUP(N26*O$5,0)),N26) -> 66 | O27: =O26+N26 -> 612 | P27: =If(P26>0,If($K27>20 ,P26-ROUNDUP(P26*0.2,0) , P26+ROUNDUP(P26*Q$5,0)),P26) -> 31 | Q27: =Q26+P26 -> 366 | R27: =If(R26>0,If($K27>20 ,R26-ROUNDUP(R26*0.2,0) , R26+ROUNDUP(R26*S$5,0)),R26) -> 106 | S27: =S26+R26 -> 867 | T27: =If(T26>0,If($K27>20 ,T26-ROUNDUP(T26*0.2,0)*1.5 , T26+ROUNDUP(T26*U$5,0)*1.5),T26) -> 37.5 | U27: =U26+T26 -> 526.5 | V27: =If(V26>0,If($K27>20 ,V26-ROUNDUP(V26*0.2,0)*1.5 , V26+ROUNDUP(V26*W$5,0)*1.5),V26) -> 217.5 | W27: =W26+V26 -> 1807.5
K28: =K27+1 -> 22 | L28: =If(L27>0,If($K28>20 ,L27-ROUNDUP(L27*0.2,0) , L27+ROUNDUP(L27*M$5,0)),L27) -> 16 | M28: =M27+L27 -> 317 | N28: =If(N27>0,If($K28>20 ,N27-ROUNDUP(N27*0.2,0) , N27+ROUNDUP(N27*O$5,0)),N27) -> 52 | O28: =O27+N27 -> 678 | P28: =If(P27>0,If($K28>20 ,P27-ROUNDUP(P27*0.2,0) , P27+ROUNDUP(P27*Q$5,0)),P27) -> 24 | Q28: =Q27+P27 -> 397 | R28: =If(R27>0,If($K28>20 ,R27-ROUNDUP(R27*0.2,0) , R27+ROUNDUP(R27*S$5,0)),R27) -> 84 | S28: =S27+R27 -> 973 | T28: =If(T27>0,If($K28>20 ,T27-ROUNDUP(T27*0.2,0)*1.5 , T27+ROUNDUP(T27*U$5,0)*1.5),T27) -> 25.5 | U28: =U27+T27 -> 564 | V28: =If(V27>0,If($K28>20 ,V27-ROUNDUP(V27*0.2,0)*1.5 , V27+ROUNDUP(V27*W$5,0)*1.5),V27) -> 151.5 | W28: =W27+V27 -> 2025
K29: =K28+1 -> 23 | L29: =If(L28>0,If($K29>20 ,L28-ROUNDUP(L28*0.2,0) , L28+ROUNDUP(L28*M$5,0)),L28) -> 12 | M29: =M28+L28 -> 333 | N29: =If(N28>0,If($K29>20 ,N28-ROUNDUP(N28*0.2,0) , N28+ROUNDUP(N28*O$5,0)),N28) -> 41 | O29: =O28+N28 -> 730 | P29: =If(P28>0,If($K29>20 ,P28-ROUNDUP(P28*0.2,0) , P28+ROUNDUP(P28*Q$5,0)),P28) -> 19 | Q29: =Q28+P28 -> 421 | R29: =If(R28>0,If($K29>20 ,R28-ROUNDUP(R28*0.2,0) , R28+ROUNDUP(R28*S$5,0)),R28) -> 67 | S29: =S28+R28 -> 1057 | T29: =If(T28>0,If($K29>20 ,T28-ROUNDUP(T28*0.2,0)*1.5 , T28+ROUNDUP(T28*U$5,0)*1.5),T28) -> 16.5 | U29: =U28+T28 -> 589.5 | V29: =If(V28>0,If($K29>20 ,V28-ROUNDUP(V28*0.2,0)*1.5 , V28+ROUNDUP(V28*W$5,0)*1.5),V28) -> 105 | W29: =W28+V28 -> 2176.5
K30: =K29+1 -> 24 | L30: =If(L29>0,If($K30>20 ,L29-ROUNDUP(L29*0.2,0) , L29+ROUNDUP(L29*M$5,0)),L29) -> 9 | M30: =M29+L29 -> 345 | N30: =If(N29>0,If($K30>20 ,N29-ROUNDUP(N29*0.2,0) , N29+ROUNDUP(N29*O$5,0)),N29) -> 32 | O30: =O29+N29 -> 771 | P30: =If(P29>0,If($K30>20 ,P29-ROUNDUP(P29*0.2,0) , P29+ROUNDUP(P29*Q$5,0)),P29) -> 15 | Q30: =Q29+P29 -> 440 | R30: =If(R29>0,If($K30>20 ,R29-ROUNDUP(R29*0.2,0) , R29+ROUNDUP(R29*S$5,0)),R29) -> 53 | S30: =S29+R29 -> 1124 | T30: =If(T29>0,If($K30>20 ,T29-ROUNDUP(T29*0.2,0)*1.5 , T29+ROUNDUP(T29*U$5,0)*1.5),T29) -> 10.5 | U30: =U29+T29 -> 606 | V30: =If(V29>0,If($K30>20 ,V29-ROUNDUP(V29*0.2,0)*1.5 , V29+ROUNDUP(V29*W$5,0)*1.5),V29) -> 73.5 | W30: =W29+V29 -> 2281.5
A31: 当前波数 | B31: 道具等级 | C31: 道具价格 | K31: =K30+1 -> 25 | L31: =If(L30>0,If($K31>20 ,L30-ROUNDUP(L30*0.2,0) , L30+ROUNDUP(L30*M$5,0)),L30) -> 7 | M31: =M30+L30 -> 354 | N31: =If(N30>0,If($K31>20 ,N30-ROUNDUP(N30*0.2,0) , N30+ROUNDUP(N30*O$5,0)),N30) -> 25 | O31: =O30+N30 -> 803 | P31: =If(P30>0,If($K31>20 ,P30-ROUNDUP(P30*0.2,0) , P30+ROUNDUP(P30*Q$5,0)),P30) -> 12 | Q31: =Q30+P30 -> 455 | R31: =If(R30>0,If($K31>20 ,R30-ROUNDUP(R30*0.2,0) , R30+ROUNDUP(R30*S$5,0)),R30) -> 42 | S31: =S30+R30 -> 1177 | T31: =If(T30>0,If($K31>20 ,T30-ROUNDUP(T30*0.2,0)*1.5 , T30+ROUNDUP(T30*U$5,0)*1.5),T30) -> 6 | U31: =U30+T30 -> 616.5 | V31: =If(V30>0,If($K31>20 ,V30-ROUNDUP(V30*0.2,0)*1.5 , V30+ROUNDUP(V30*W$5,0)*1.5),V30) -> 51 | W31: =W30+V30 -> 2355
A32: 11 | B32: 3 | C32: 227 | K32: =K31+1 -> 26 | L32: =If(L31>0,If($K32>20 ,L31-ROUNDUP(L31*0.2,0) , L31+ROUNDUP(L31*M$5,0)),L31) -> 5 | M32: =M31+L31 -> 361 | N32: =If(N31>0,If($K32>20 ,N31-ROUNDUP(N31*0.2,0) , N31+ROUNDUP(N31*O$5,0)),N31) -> 20 | O32: =O31+N31 -> 828 | P32: =If(P31>0,If($K32>20 ,P31-ROUNDUP(P31*0.2,0) , P31+ROUNDUP(P31*Q$5,0)),P31) -> 9 | Q32: =Q31+P31 -> 467 | R32: =If(R31>0,If($K32>20 ,R31-ROUNDUP(R31*0.2,0) , R31+ROUNDUP(R31*S$5,0)),R31) -> 33 | S32: =S31+R31 -> 1219 | T32: =If(T31>0,If($K32>20 ,T31-ROUNDUP(T31*0.2,0)*1.5 , T31+ROUNDUP(T31*U$5,0)*1.5),T31) -> 3 | U32: =U31+T31 -> 622.5 | V32: =If(V31>0,If($K32>20 ,V31-ROUNDUP(V31*0.2,0)*1.5 , V31+ROUNDUP(V31*W$5,0)*1.5),V31) -> 34.5 | W32: =W31+V31 -> 2406
A33: 最终偷窃几率 | K33: =K32+1 -> 27 | L33: =If(L32>0,If($K33>20 ,L32-ROUNDUP(L32*0.2,0) , L32+ROUNDUP(L32*M$5,0)),L32) -> 4 | M33: =M32+L32 -> 366 | N33: =If(N32>0,If($K33>20 ,N32-ROUNDUP(N32*0.2,0) , N32+ROUNDUP(N32*O$5,0)),N32) -> 16 | O33: =O32+N32 -> 848 | P33: =If(P32>0,If($K33>20 ,P32-ROUNDUP(P32*0.2,0) , P32+ROUNDUP(P32*Q$5,0)),P32) -> 7 | Q33: =Q32+P32 -> 476 | R33: =If(R32>0,If($K33>20 ,R32-ROUNDUP(R32*0.2,0) , R32+ROUNDUP(R32*S$5,0)),R32) -> 26 | S33: =S32+R32 -> 1252 | T33: =If(T32>0,If($K33>20 ,T32-ROUNDUP(T32*0.2,0)*1.5 , T32+ROUNDUP(T32*U$5,0)*1.5),T32) -> 1.5 | U33: =U32+T32 -> 625.5 | V33: =If(V32>0,If($K33>20 ,V32-ROUNDUP(V32*0.2,0)*1.5 , V32+ROUNDUP(V32*W$5,0)*1.5),V32) -> 24 | W33: =W32+V32 -> 2440.5
B34: =min(95%,(A32/10)*((0+B32)/4)*(C32/300)) -> 0.62425 | K34: =K33+1 -> 28 | L34: =If(L33>0,If($K34>20 ,L33-ROUNDUP(L33*0.2,0) , L33+ROUNDUP(L33*M$5,0)),L33) -> 3 | M34: =M33+L33 -> 370 | N34: =If(N33>0,If($K34>20 ,N33-ROUNDUP(N33*0.2,0) , N33+ROUNDUP(N33*O$5,0)),N33) -> 12 | O34: =O33+N33 -> 864 | P34: =If(P33>0,If($K34>20 ,P33-ROUNDUP(P33*0.2,0) , P33+ROUNDUP(P33*Q$5,0)),P33) -> 5 | Q34: =Q33+P33 -> 483 | R34: =If(R33>0,If($K34>20 ,R33-ROUNDUP(R33*0.2,0) , R33+ROUNDUP(R33*S$5,0)),R33) -> 20 | S34: =S33+R33 -> 1278 | T34: =If(T33>0,If($K34>20 ,T33-ROUNDUP(T33*0.2,0)*1.5 , T33+ROUNDUP(T33*U$5,0)*1.5),T33) -> 0 | U34: =U33+T33 -> 627 | V34: =If(V33>0,If($K34>20 ,V33-ROUNDUP(V33*0.2,0)*1.5 , V33+ROUNDUP(V33*W$5,0)*1.5),V33) -> 16.5 | W34: =W33+V33 -> 2464.5
K35: =K34+1 -> 29 | L35: =If(L34>0,If($K35>20 ,L34-ROUNDUP(L34*0.2,0) , L34+ROUNDUP(L34*M$5,0)),L34) -> 2 | M35: =M34+L34 -> 373 | N35: =If(N34>0,If($K35>20 ,N34-ROUNDUP(N34*0.2,0) , N34+ROUNDUP(N34*O$5,0)),N34) -> 9 | O35: =O34+N34 -> 876 | P35: =If(P34>0,If($K35>20 ,P34-ROUNDUP(P34*0.2,0) , P34+ROUNDUP(P34*Q$5,0)),P34) -> 4 | Q35: =Q34+P34 -> 488 | R35: =If(R34>0,If($K35>20 ,R34-ROUNDUP(R34*0.2,0) , R34+ROUNDUP(R34*S$5,0)),R34) -> 16 | S35: =S34+R34 -> 1298 | T35: =If(T34>0,If($K35>20 ,T34-ROUNDUP(T34*0.2,0)*1.5 , T34+ROUNDUP(T34*U$5,0)*1.5),T34) -> 0 | U35: =U34+T34 -> 627 | V35: =If(V34>0,If($K35>20 ,V34-ROUNDUP(V34*0.2,0)*1.5 , V34+ROUNDUP(V34*W$5,0)*1.5),V34) -> 10.5 | W35: =W34+V34 -> 2481
K36: =K35+1 -> 30 | L36: =If(L35>0,If($K36>20 ,L35-ROUNDUP(L35*0.2,0) , L35+ROUNDUP(L35*M$5,0)),L35) -> 1 | M36: =M35+L35 -> 375 | N36: =If(N35>0,If($K36>20 ,N35-ROUNDUP(N35*0.2,0) , N35+ROUNDUP(N35*O$5,0)),N35) -> 7 | O36: =O35+N35 -> 885 | P36: =If(P35>0,If($K36>20 ,P35-ROUNDUP(P35*0.2,0) , P35+ROUNDUP(P35*Q$5,0)),P35) -> 3 | Q36: =Q35+P35 -> 492 | R36: =If(R35>0,If($K36>20 ,R35-ROUNDUP(R35*0.2,0) , R35+ROUNDUP(R35*S$5,0)),R35) -> 12 | S36: =S35+R35 -> 1314 | T36: =If(T35>0,If($K36>20 ,T35-ROUNDUP(T35*0.2,0)*1.5 , T35+ROUNDUP(T35*U$5,0)*1.5),T35) -> 0 | U36: =U35+T35 -> 627 | V36: =If(V35>0,If($K36>20 ,V35-ROUNDUP(V35*0.2,0)*1.5 , V35+ROUNDUP(V35*W$5,0)*1.5),V35) -> 6 | W36: =W35+V35 -> 2491.5
K37: =K36+1 -> 31 | L37: =If(L36>0,If($K37>20 ,L36-ROUNDUP(L36*0.2,0) , L36+ROUNDUP(L36*M$5,0)),L36) -> 0 | M37: =M36+L36 -> 376 | N37: =If(N36>0,If($K37>20 ,N36-ROUNDUP(N36*0.2,0) , N36+ROUNDUP(N36*O$5,0)),N36) -> 5 | O37: =O36+N36 -> 892 | P37: =If(P36>0,If($K37>20 ,P36-ROUNDUP(P36*0.2,0) , P36+ROUNDUP(P36*Q$5,0)),P36) -> 2 | Q37: =Q36+P36 -> 495 | R37: =If(R36>0,If($K37>20 ,R36-ROUNDUP(R36*0.2,0) , R36+ROUNDUP(R36*S$5,0)),R36) -> 9 | S37: =S36+R36 -> 1326 | T37: =If(T36>0,If($K37>20 ,T36-ROUNDUP(T36*0.2,0)*1.5 , T36+ROUNDUP(T36*U$5,0)*1.5),T36) -> 0 | U37: =U36+T36 -> 627 | V37: =If(V36>0,If($K37>20 ,V36-ROUNDUP(V36*0.2,0)*1.5 , V36+ROUNDUP(V36*W$5,0)*1.5),V36) -> 3 | W37: =W36+V36 -> 2497.5

Sheet 敌人计算器
A1: 玩家人数（联机） | B1: 危险等级 | C1: 你的护甲 | D1: 生命滑块 | E1: 伤害滑块 | F1: 速度滑块 | G1: 无尽波数 | H1: 茶 / 异形宝宝 | I1: 孔雀 | J1: Jack？ | K1: 强化版 | L1: 护甲（受到的%伤害） | M1: 危险等级生命 | N1: 危险等级伤害 | O1: Jack伤害系数 | P1: Jack生命系数
A2: 1 | B2: 5 | C2: 0 | D2: 1 | E2: 1 | F2: 1 | G2: 400 | H2: 0 | I2: 0 | J2: FALSE | K2: FALSE | L2: =(If(C2>-0.5, 1/(1+ 2/30*C2),1+(1-1/(1+ 2/30*(-C2))))) -> 1 | M2: =1+IF($B$2=3,0.12,0)+IF($B$2=4,0.26,0)+IF($B$2=5,0.4,0) -> 1.4 | N2: =1+IF($B$2=3,0.12,0)+IF($B$2=4,0.26,0)+IF($B$2=5,0.4,0) -> 1.4 | O2: =If(J2=True,1.5,1) -> 1 | P2: =If(J2=True,3.5,1) -> 1
A3: 移动速度 | B3: 速度（相对你基础速度的百分比）
A4: 敌人 | B4: 树 | C4: 异形幼体 | D4: 追猎者 | E4: 喷射者 | F4: 冲锋者 | G4: 追击者 | H4: 蛮兵 | I4: 增益者 | J4: 苍蝇 | K4: 治疗者 | L4: 掠夺者 | M4: 头盔异形 | N4: 鳍异形 | O4: 孵化者 | P4: 瘾君子 | Q4: 重甲蛮兵 | R4: 尖角冲锋者 | S4: 切割者之卵 | T4: 切割者 | U4: 触手 | V4: 犀牛 | W4: 屠夫 | X4: 武僧 | Y4: 掠食者 | Z4: 祈求者 | AA4: 七鳃鳗
A5: 移动速度 | B5: 0 | C5: =Round(C$87*$F$2*IF(EnemyBuffed=TRUE,1.5,1),0) & " (" & Round(Round(C$87*$F$2*IF(EnemyBuffed=TRUE,1.5,1),0)/4.5,0) & "%" & ")" -> 250 (56%) | D5: =Round(D$87*$F$2*IF(EnemyBuffed=TRUE,1.5,1),0) & " (" & Round(Round(D$87*$F$2*IF(EnemyBuffed=TRUE,1.5,1),0)/4.5,0) & "%" & ")" -> 380 (84%) | E5: =Round(E$87*$F$2*IF(EnemyBuffed=TRUE,1.5,1),0) & " (" & Round(Round(E$87*$F$2*IF(EnemyBuffed=TRUE,1.5,1),0)/4.5,0) & "%" & ")" -> 200 (44%) | F5: =Round(F$87*$F$2*IF(EnemyBuffed=TRUE,1.5,1),0) & " (" & Round(Round(F$87*$F$2*IF(EnemyBuffed=TRUE,1.5,1),0)/4.5,0) & "%" & ")" -> 400 (89%) | G5: =Round(G$87*$F$2*IF(EnemyBuffed=TRUE,1.5,1),0) & " (" & Round(Round(G$87*$F$2*IF(EnemyBuffed=TRUE,1.5,1),0)/4.5,0) & "%" & ")" -> 600 (133%) | H5: =Round(H$87*$F$2*IF(EnemyBuffed=TRUE,1.5,1),0) & " (" & Round(Round(H$87*$F$2*IF(EnemyBuffed=TRUE,1.5,1),0)/4.5,0) & "%" & ")" -> 300 (67%) | I5: =Round(I$87*$F$2*IF(EnemyBuffed=TRUE,1.5,1),0) & " (" & Round(Round(I$87*$F$2*IF(EnemyBuffed=TRUE,1.5,1),0)/4.5,0) & "%" & ")" -> 150 (33%) | J5: =Round(J$87*$F$2*IF(EnemyBuffed=TRUE,1.5,1),0) & " (" & Round(Round(J$87*$F$2*IF(EnemyBuffed=TRUE,1.5,1),0)/4.5,0) & "%" & ")" -> 350 (78%) | ... AA5: =Round(AA$87*$F$2*IF(EnemyBuffed=TRUE,1.5,1),0) & " (" & Round(Round(AA$87*$F$2*IF(EnemyBuffed=TRUE,1.5,1),0)/4.5,0) & "%" & ")" -> 350 (78%)
A6: ="无尽 " & $G$2 -> Endless 400 | B6: 0 | C6: =Round(C$87*$F$2*IF(EnemyBuffed=TRUE,1.5,1)*(1+Min(1.75,IF($G$2>20,(Max(0,((($G$2-20)*(($G$2-20)+1))/2)/100)*(2+Max(0,($G$2-35)*0.2))/(1000/75)),0))),0) & " (" & Round(Round(C$87*$F$2*IF(EnemyBuffed=TRUE,1.5,1)*(1+Min(1.75,IF($G$2>20,(Max(0,((($G$2-20)*(($G$2-20)+1))/2)/100)*(2+Max(0,($G$2-35)*0.2))/(1000/75)),0))),0)/4.5,0) & "%" & ")" -> 688 (153%) | D6: =Round(D$87*$F$2*IF(EnemyBuffed=TRUE,1.5,1)*(1+Min(1.75,IF($G$2>20,(Max(0,((($G$2-20)*(($G$2-20)+1))/2)/100)*(2+Max(0,($G$2-35)*0.2))/(1000/75)),0))),0) & " (" & Round(Round(D$87*$F$2*IF(EnemyBuffed=TRUE,1.5,1)*(1+Min(1.75,IF($G$2>20,(Max(0,((($G$2-20)*(($G$2-20)+1))/2)/100)*(2+Max(0,($G$2-35)*0.2))/(1000/75)),0))),0)/4.5,0) & "%" & ")" -> 1045 (232%) | E6: =Round(E$87*$F$2*IF(EnemyBuffed=TRUE,1.5,1)*(1+Min(1.75,IF($G$2>20,(Max(0,((($G$2-20)*(($G$2-20)+1))/2)/100)*(2+Max(0,($G$2-35)*0.2))/(1000/75)),0))),0) & " (" & Round(Round(E$87*$F$2*IF(EnemyBuffed=TRUE,1.5,1)*(1+Min(1.75,IF($G$2>20,(Max(0,((($G$2-20)*(($G$2-20)+1))/2)/100)*(2+Max(0,($G$2-35)*0.2))/(1000/75)),0))),0)/4.5,0) & "%" & ")" -> 550 (122%) | F6: =Round(F$87*$F$2*IF(EnemyBuffed=TRUE,1.5,1)*(1+Min(1.75,IF($G$2>20,(Max(0,((($G$2-20)*(($G$2-20)+1))/2)/100)*(2+Max(0,($G$2-35)*0.2))/(1000/75)),0))),0) & " (" & Round(Round(F$87*$F$2*IF(EnemyBuffed=TRUE,1.5,1)*(1+Min(1.75,IF($G$2>20,(Max(0,((($G$2-20)*(($G$2-20)+1))/2)/100)*(2+Max(0,($G$2-35)*0.2))/(1000/75)),0))),0)/4.5,0) & "%" & ")" -> 1100 (244%) | G6: =Round(G$87*$F$2*IF(EnemyBuffed=TRUE,1.5,1)*(1+Min(1.75,IF($G$2>20,(Max(0,((($G$2-20)*(($G$2-20)+1))/2)/100)*(2+Max(0,($G$2-35)*0.2))/(1000/75)),0))),0) & " (" & Round(Round(G$87*$F$2*IF(EnemyBuffed=TRUE,1.5,1)*(1+Min(1.75,IF($G$2>20,(Max(0,((($G$2-20)*(($G$2-20)+1))/2)/100)*(2+Max(0,($G$2-35)*0.2))/(1000/75)),0))),0)/4.5,0) & "%" & ")" -> 1650 (367%) | H6: =Round(H$87*$F$2*IF(EnemyBuffed=TRUE,1.5,1)*(1+Min(1.75,IF($G$2>20,(Max(0,((($G$2-20)*(($G$2-20)+1))/2)/100)*(2+Max(0,($G$2-35)*0.2))/(1000/75)),0))),0) & " (" & Round(Round(H$87*$F$2*IF(EnemyBuffed=TRUE,1.5,1)*(1+Min(1.75,IF($G$2>20,(Max(0,((($G$2-20)*(($G$2-20)+1))/2)/100)*(2+Max(0,($G$2-35)*0.2))/(1000/75)),0))),0)/4.5,0) & "%" & ")" -> 825 (183%) | I6: =Round(I$87*$F$2*IF(EnemyBuffed=TRUE,1.5,1)*(1+Min(1.75,IF($G$2>20,(Max(0,((($G$2-20)*(($G$2-20)+1))/2)/100)*(2+Max(0,($G$2-35)*0.2))/(1000/75)),0))),0) & " (" & Round(Round(I$87*$F$2*IF(EnemyBuffed=TRUE,1.5,1)*(1+Min(1.75,IF($G$2>20,(Max(0,((($G$2-20)*(($G$2-20)+1))/2)/100)*(2+Max(0,($G$2-35)*0.2))/(1000/75)),0))),0)/4.5,0) & "%" & ")" -> 413 (92%) | J6: =Round(J$87*$F$2*IF(EnemyBuffed=TRUE,1.5,1)*(1+Min(1.75,IF($G$2>20,(Max(0,((($G$2-20)*(($G$2-20)+1))/2)/100)*(2+Max(0,($G$2-35)*0.2))/(1000/75)),0))),0) & " (" & Round(Round(J$87*$F$2*IF(EnemyBuffed=TRUE,1.5,1)*(1+Min(1.75,IF($G$2>20,(Max(0,((($G$2-20)*(($G$2-20)+1))/2)/100)*(2+Max(0,($G$2-35)*0.2))/(1000/75)),0))),0)/4.5,0) & "%" & ")" -> 963 (214%) | ... AA6: =Round(AA$87*$F$2*IF(EnemyBuffed=TRUE,1.5,1)*(1+Min(1.75,IF($G$2>20,(Max(0,((($G$2-20)*(($G$2-20)+1))/2)/100)*(2+Max(0,($G$2-35)*0.2))/(1000/75)),0))),0) & " (" & Round(Round(AA$87*$F$2*IF(EnemyBuffed=TRUE,1.5,1)*(1+Min(1.75,IF($G$2>20,(Max(0,((($G$2-20)*(($G$2-20)+1))/2)/100)*(2+Max(0,($G$2-35)*0.2))/(1000/75)),0))),0)/4.5,0) & "%" & ")" -> 963 (214%)
A7: 生命值
A8: 波数 | B8: 树 | C8: 异形幼体 | D8: 追猎者 | E8: 喷射者 | F8: 冲锋者 | G8: 追击者 | H8: 蛮兵 | I8: 增益者 | J8: 苍蝇 | K8: 治疗者 | L8: 掠夺者 | M8: 头盔异形 | N8: 鳍异形 | O8: 孵化者 | P8: 瘾君子 | Q8: 重甲蛮兵 | R8: 尖角冲锋者 | S8: 切割者之卵 | T8: 切割者 | U8: 触手 | V8: 犀牛 | W8: 屠夫 | X8: 武僧 | Y8: 掠食者 | Z8: 祈求者 | AA8: 七鳃鳗
A9: 基础生命值 | B9: 10 | C9: 3 | D9: 1 | E9: 8 | F9: 4 | G9: 10 | H9: 20 | I9: 20 | J9: 15 | K9: 10 | L9: 50 | M9: 8 | N9: 12 | O9: 10 | P9: 5 | Q9: 30 | R9: 12 | S9: 5 | T9: 50 | U9: 100 | V9: 1 | W9: 1 | X9: 1 | Y9: 15000 | Z9: 15000 | AA9: 30
A10: 生命/波 | B10: 5 | C10: 2 | D10: 1 | E10: 1 | F10: 2.5 | G10: 24 | H10: 11 | I10: 3 | J10: 4 | K10: 8 | L10: 25 | M10: 3 | N10: 2 | O10: 1 | P10: 5 | Q10: 22 | R10: 5 | S10: 3 | T10: 25 | U10: 20 | V10: 750 | W10: 750 | X10: 700 | Y10: 750 | Z10: 750 | AA10: 15
A11: 1 | B11: =Rounddown(Round(Round((B$9+B$10*($A11-1))*(1+(EnemyHPSlider-1)+(EnemyHPDanger-1)+(EnemyJackHP-1)),0)*IF($A11>20,(1+Max(0,((($A11-20)*(($A11-20)+1))/2)/100)*(2+Max(0,($A11-35)*0.2))*2),1),0)*IF(EnemyBuffed=TRUE,2.5,1),0) -> 14 | C11: =Rounddown(Round(Round((C$9+C$10*($A11-1))*(1+(EnemyHPSlider-1)+(EnemyHPDanger-1)+(EnemyJackHP-1)),0)*IF($A11>20,(1+Max(0,((($A11-20)*(($A11-20)+1))/2)/100)*(2+Max(0,($A11-35)*0.2))*2),1),0)*IF(EnemyBuffed=TRUE,2.5,1),0) -> 4 | D11: =Rounddown(Round(Round((D$9+D$10*($A11-1))*(1+(EnemyHPSlider-1)+(EnemyHPDanger-1)+(EnemyJackHP-1)),0)*IF($A11>20,(1+Max(0,((($A11-20)*(($A11-20)+1))/2)/100)*(2+Max(0,($A11-35)*0.2))*2),1),0)*IF(EnemyBuffed=TRUE,2.5,1),0) -> 1 | E11: =Rounddown(Round(Round((E$9+E$10*($A11-1))*(1+(EnemyHPSlider-1)+(EnemyHPDanger-1)+(EnemyJackHP-1)),0)*IF($A11>20,(1+Max(0,((($A11-20)*(($A11-20)+1))/2)/100)*(2+Max(0,($A11-35)*0.2))*2),1),0)*IF(EnemyBuffed=TRUE,2.5,1),0) -> 11 | F11: =Rounddown(Round(Round((F$9+F$10*($A11-1))*(1+(EnemyHPSlider-1)+(EnemyHPDanger-1)+(EnemyJackHP-1)),0)*IF($A11>20,(1+Max(0,((($A11-20)*(($A11-20)+1))/2)/100)*(2+Max(0,($A11-35)*0.2))*2),1),0)*IF(EnemyBuffed=TRUE,2.5,1),0) -> 6 | G11: =Rounddown(Round(Round((G$9+G$10*($A11-1))*(1+(EnemyHPSlider-1)+(EnemyHPDanger-1)+(EnemyJackHP-1)),0)*IF($A11>20,(1+Max(0,((($A11-20)*(($A11-20)+1))/2)/100)*(2+Max(0,($A11-35)*0.2))*2),1),0)*IF(EnemyBuffed=TRUE,2.5,1),0) -> 14 | H11: =Rounddown(Round(Round((H$9+H$10*($A11-1))*(1+(EnemyHPSlider-1)+(EnemyHPDanger-1)+(EnemyJackHP-1)),0)*IF($A11>20,(1+Max(0,((($A11-20)*(($A11-20)+1))/2)/100)*(2+Max(0,($A11-35)*0.2))*2),1),0)*IF(EnemyBuffed=TRUE,2.5,1),0) -> 28 | I11: =Rounddown(Round(Round((I$9+I$10*($A11-1))*(1+(EnemyHPSlider-1)+(EnemyHPDanger-1)+(EnemyJackHP-1)),0)*IF($A11>20,(1+Max(0,((($A11-20)*(($A11-20)+1))/2)/100)*(2+Max(0,($A11-35)*0.2))*2),1),0)*IF(EnemyBuffed=TRUE,2.5,1),0) -> 28 | ... X11: =Rounddown(Round(Round((X$9+X$10*($A11-1))*(1+(EnemyHPSlider-1)+(EnemyHPDanger-1)+(EnemyJackHP-1)),0)*IF($A11>20,(1+Max(0,((($A11-20)*(($A11-20)+1))/2)/100)*(2+Max(0,($A11-35)*0.2))*2),1),0)*IF(EnemyBuffed=TRUE,2.5,1),0) -> 1 | Y11: =Rounddown(Round(Round((Y$9+Y$10*($A11-1))*(1+(EnemyHPSlider-1)+(EnemyHPDanger-1)+(EnemyJackHP-1)),0)*IF($A11>20,(1+Max(0,((($A11-20)*(($A11-20)+1))/2)/100)*(2+Max(0,($A11-35)*0.2))*2),1),0)*IF(EnemyBuffed=TRUE,2.5,1)*IF(AND($B$2=5,$A11<=20),0.75,1),0) -> 15750 | Z11: =Rounddown(Round(Round((Z$9+Z$10*($A11-1))*(1+(EnemyHPSlider-1)+(EnemyHPDanger-1)+(EnemyJackHP-1)),0)*IF($A11>20,(1+Max(0,((($A11-20)*(($A11-20)+1))/2)/100)*(2+Max(0,($A11-35)*0.2))*2),1),0)*IF(EnemyBuffed=TRUE,2.5,1)*IF(AND($B$2=5,$A11<=20),0.75,1),0) -> 15750 | AA11: =Rounddown(Round(Round((AA$9+AA$10*($A11-1))*(1+(EnemyHPSlider-1)+(EnemyHPDanger-1)+(EnemyJackHP-1)),0)*IF($A11>20,(1+Max(0,((($A11-20)*(($A11-20)+1))/2)/100)*(2+Max(0,($A11-35)*0.2))*2),1),0)*IF(EnemyBuffed=TRUE,2.5,1),0) -> 42
A12: 2 | B12: =Rounddown(Round(Round((B$9+B$10*($A12-1))*(1+(EnemyHPSlider-1)+(EnemyHPDanger-1)+(EnemyJackHP-1)),0)*IF($A12>20,(1+Max(0,((($A12-20)*(($A12-20)+1))/2)/100)*(2+Max(0,($A12-35)*0.2))*2),1),0)*IF(EnemyBuffed=TRUE,2.5,1),0) -> 21 | C12: =Rounddown(Round(Round((C$9+C$10*($A12-1))*(1+(EnemyHPSlider-1)+(EnemyHPDanger-1)+(EnemyJackHP-1)),0)*IF($A12>20,(1+Max(0,((($A12-20)*(($A12-20)+1))/2)/100)*(2+Max(0,($A12-35)*0.2))*2),1),0)*IF(EnemyBuffed=TRUE,2.5,1),0) -> 7 | D12: =Rounddown(Round(Round((D$9+D$10*($A12-1))*(1+(EnemyHPSlider-1)+(EnemyHPDanger-1)+(EnemyJackHP-1)),0)*IF($A12>20,(1+Max(0,((($A12-20)*(($A12-20)+1))/2)/100)*(2+Max(0,($A12-35)*0.2))*2),1),0)*IF(EnemyBuffed=TRUE,2.5,1),0) -> 3 | E12: =Rounddown(Round(Round((E$9+E$10*($A12-1))*(1+(EnemyHPSlider-1)+(EnemyHPDanger-1)+(EnemyJackHP-1)),0)*IF($A12>20,(1+Max(0,((($A12-20)*(($A12-20)+1))/2)/100)*(2+Max(0,($A12-35)*0.2))*2),1),0)*IF(EnemyBuffed=TRUE,2.5,1),0) -> 13 | F12: =Rounddown(Round(Round((F$9+F$10*($A12-1))*(1+(EnemyHPSlider-1)+(EnemyHPDanger-1)+(EnemyJackHP-1)),0)*IF($A12>20,(1+Max(0,((($A12-20)*(($A12-20)+1))/2)/100)*(2+Max(0,($A12-35)*0.2))*2),1),0)*IF(EnemyBuffed=TRUE,2.5,1),0) -> 9 | G12: =Rounddown(Round(Round((G$9+G$10*($A12-1))*(1+(EnemyHPSlider-1)+(EnemyHPDanger-1)+(EnemyJackHP-1)),0)*IF($A12>20,(1+Max(0,((($A12-20)*(($A12-20)+1))/2)/100)*(2+Max(0,($A12-35)*0.2))*2),1),0)*IF(EnemyBuffed=TRUE,2.5,1),0) -> 48 | H12: =Rounddown(Round(Round((H$9+H$10*($A12-1))*(1+(EnemyHPSlider-1)+(EnemyHPDanger-1)+(EnemyJackHP-1)),0)*IF($A12>20,(1+Max(0,((($A12-20)*(($A12-20)+1))/2)/100)*(2+Max(0,($A12-35)*0.2))*2),1),0)*IF(EnemyBuffed=TRUE,2.5,1),0) -> 43 | I12: =Rounddown(Round(Round((I$9+I$10*($A12-1))*(1+(EnemyHPSlider-1)+(EnemyHPDanger-1)+(EnemyJackHP-1)),0)*IF($A12>20,(1+Max(0,((($A12-20)*(($A12-20)+1))/2)/100)*(2+Max(0,($A12-35)*0.2))*2),1),0)*IF(EnemyBuffed=TRUE,2.5,1),0) -> 32 | ... X12: =Rounddown(Round(Round((X$9+X$10*($A12-1))*(1+(EnemyHPSlider-1)+(EnemyHPDanger-1)+(EnemyJackHP-1)),0)*IF($A12>20,(1+Max(0,((($A12-20)*(($A12-20)+1))/2)/100)*(2+Max(0,($A12-35)*0.2))*2),1),0)*IF(EnemyBuffed=TRUE,2.5,1),0) -> 981 | Y12: =Rounddown(Round(Round((Y$9+Y$10*($A12-1))*(1+(EnemyHPSlider-1)+(EnemyHPDanger-1)+(EnemyJackHP-1)),0)*IF($A12>20,(1+Max(0,((($A12-20)*(($A12-20)+1))/2)/100)*(2+Max(0,($A12-35)*0.2))*2),1),0)*IF(EnemyBuffed=TRUE,2.5,1)*IF(AND($B$2=5,$A12<=20),0.75,1),0) -> 16537 | Z12: =Rounddown(Round(Round((Z$9+Z$10*($A12-1))*(1+(EnemyHPSlider-1)+(EnemyHPDanger-1)+(EnemyJackHP-1)),0)*IF($A12>20,(1+Max(0,((($A12-20)*(($A12-20)+1))/2)/100)*(2+Max(0,($A12-35)*0.2))*2),1),0)*IF(EnemyBuffed=TRUE,2.5,1)*IF(AND($B$2=5,$A12<=20),0.75,1),0) -> 16537 | AA12: =Rounddown(Round(Round((AA$9+AA$10*($A12-1))*(1+(EnemyHPSlider-1)+(EnemyHPDanger-1)+(EnemyJackHP-1)),0)*IF($A12>20,(1+Max(0,((($A12-20)*(($A12-20)+1))/2)/100)*(2+Max(0,($A12-35)*0.2))*2),1),0)*IF(EnemyBuffed=TRUE,2.5,1),0) -> 63
A13: 3 | B13: =Rounddown(Round(Round((B$9+B$10*($A13-1))*(1+(EnemyHPSlider-1)+(EnemyHPDanger-1)+(EnemyJackHP-1)),0)*IF($A13>20,(1+Max(0,((($A13-20)*(($A13-20)+1))/2)/100)*(2+Max(0,($A13-35)*0.2))*2),1),0)*IF(EnemyBuffed=TRUE,2.5,1),0) -> 28 | C13: =Rounddown(Round(Round((C$9+C$10*($A13-1))*(1+(EnemyHPSlider-1)+(EnemyHPDanger-1)+(EnemyJackHP-1)),0)*IF($A13>20,(1+Max(0,((($A13-20)*(($A13-20)+1))/2)/100)*(2+Max(0,($A13-35)*0.2))*2),1),0)*IF(EnemyBuffed=TRUE,2.5,1),0) -> 10 | D13: =Rounddown(Round(Round((D$9+D$10*($A13-1))*(1+(EnemyHPSlider-1)+(EnemyHPDanger-1)+(EnemyJackHP-1)),0)*IF($A13>20,(1+Max(0,((($A13-20)*(($A13-20)+1))/2)/100)*(2+Max(0,($A13-35)*0.2))*2),1),0)*IF(EnemyBuffed=TRUE,2.5,1),0) -> 4 | E13: =Rounddown(Round(Round((E$9+E$10*($A13-1))*(1+(EnemyHPSlider-1)+(EnemyHPDanger-1)+(EnemyJackHP-1)),0)*IF($A13>20,(1+Max(0,((($A13-20)*(($A13-20)+1))/2)/100)*(2+Max(0,($A13-35)*0.2))*2),1),0)*IF(EnemyBuffed=TRUE,2.5,1),0) -> 14 | F13: =Rounddown(Round(Round((F$9+F$10*($A13-1))*(1+(EnemyHPSlider-1)+(EnemyHPDanger-1)+(EnemyJackHP-1)),0)*IF($A13>20,(1+Max(0,((($A13-20)*(($A13-20)+1))/2)/100)*(2+Max(0,($A13-35)*0.2))*2),1),0)*IF(EnemyBuffed=TRUE,2.5,1),0) -> 13 | G13: =Rounddown(Round(Round((G$9+G$10*($A13-1))*(1+(EnemyHPSlider-1)+(EnemyHPDanger-1)+(EnemyJackHP-1)),0)*IF($A13>20,(1+Max(0,((($A13-20)*(($A13-20)+1))/2)/100)*(2+Max(0,($A13-35)*0.2))*2),1),0)*IF(EnemyBuffed=TRUE,2.5,1),0) -> 81 | H13: =Rounddown(Round(Round((H$9+H$10*($A13-1))*(1+(EnemyHPSlider-1)+(EnemyHPDanger-1)+(EnemyJackHP-1)),0)*IF($A13>20,(1+Max(0,((($A13-20)*(($A13-20)+1))/2)/100)*(2+Max(0,($A13-35)*0.2))*2),1),0)*IF(EnemyBuffed=TRUE,2.5,1),0) -> 59 | I13: =Rounddown(Round(Round((I$9+I$10*($A13-1))*(1+(EnemyHPSlider-1)+(EnemyHPDanger-1)+(EnemyJackHP-1)),0)*IF($A13>20,(1+Max(0,((($A13-20)*(($A13-20)+1))/2)/100)*(2+Max(0,($A13-35)*0.2))*2),1),0)*IF(EnemyBuffed=TRUE,2.5,1),0) -> 36 | ... X13: =Rounddown(Round(Round((X$9+X$10*($A13-1))*(1+(EnemyHPSlider-1)+(EnemyHPDanger-1)+(EnemyJackHP-1)),0)*IF($A13>20,(1+Max(0,((($A13-20)*(($A13-20)+1))/2)/100)*(2+Max(0,($A13-35)*0.2))*2),1),0)*IF(EnemyBuffed=TRUE,2.5,1),0) -> 1961 | Y13: =Rounddown(Round(Round((Y$9+Y$10*($A13-1))*(1+(EnemyHPSlider-1)+(EnemyHPDanger-1)+(EnemyJackHP-1)),0)*IF($A13>20,(1+Max(0,((($A13-20)*(($A13-20)+1))/2)/100)*(2+Max(0,($A13-35)*0.2))*2),1),0)*IF(EnemyBuffed=TRUE,2.5,1)*IF(AND($B$2=5,$A13<=20),0.75,1),0) -> 17325 | Z13: =Rounddown(Round(Round((Z$9+Z$10*($A13-1))*(1+(EnemyHPSlider-1)+(EnemyHPDanger-1)+(EnemyJackHP-1)),0)*IF($A13>20,(1+Max(0,((($A13-20)*(($A13-20)+1))/2)/100)*(2+Max(0,($A13-35)*0.2))*2),1),0)*IF(EnemyBuffed=TRUE,2.5,1)*IF(AND($B$2=5,$A13<=20),0.75,1),0) -> 17325 | AA13: =Rounddown(Round(Round((AA$9+AA$10*($A13-1))*(1+(EnemyHPSlider-1)+(EnemyHPDanger-1)+(EnemyJackHP-1)),0)*IF($A13>20,(1+Max(0,((($A13-20)*(($A13-20)+1))/2)/100)*(2+Max(0,($A13-35)*0.2))*2),1),0)*IF(EnemyBuffed=TRUE,2.5,1),0) -> 84
A14: 4 | B14: =Rounddown(Round(Round((B$9+B$10*($A14-1))*(1+(EnemyHPSlider-1)+(EnemyHPDanger-1)+(EnemyJackHP-1)),0)*IF($A14>20,(1+Max(0,((($A14-20)*(($A14-20)+1))/2)/100)*(2+Max(0,($A14-35)*0.2))*2),1),0)*IF(EnemyBuffed=TRUE,2.5,1),0) -> 35 | C14: =Rounddown(Round(Round((C$9+C$10*($A14-1))*(1+(EnemyHPSlider-1)+(EnemyHPDanger-1)+(EnemyJackHP-1)),0)*IF($A14>20,(1+Max(0,((($A14-20)*(($A14-20)+1))/2)/100)*(2+Max(0,($A14-35)*0.2))*2),1),0)*IF(EnemyBuffed=TRUE,2.5,1),0) -> 13 | D14: =Rounddown(Round(Round((D$9+D$10*($A14-1))*(1+(EnemyHPSlider-1)+(EnemyHPDanger-1)+(EnemyJackHP-1)),0)*IF($A14>20,(1+Max(0,((($A14-20)*(($A14-20)+1))/2)/100)*(2+Max(0,($A14-35)*0.2))*2),1),0)*IF(EnemyBuffed=TRUE,2.5,1),0) -> 6 | E14: =Rounddown(Round(Round((E$9+E$10*($A14-1))*(1+(EnemyHPSlider-1)+(EnemyHPDanger-1)+(EnemyJackHP-1)),0)*IF($A14>20,(1+Max(0,((($A14-20)*(($A14-20)+1))/2)/100)*(2+Max(0,($A14-35)*0.2))*2),1),0)*IF(EnemyBuffed=TRUE,2.5,1),0) -> 15 | F14: =Rounddown(Round(Round((F$9+F$10*($A14-1))*(1+(EnemyHPSlider-1)+(EnemyHPDanger-1)+(EnemyJackHP-1)),0)*IF($A14>20,(1+Max(0,((($A14-20)*(($A14-20)+1))/2)/100)*(2+Max(0,($A14-35)*0.2))*2),1),0)*IF(EnemyBuffed=TRUE,2.5,1),0) -> 16 | G14: =Rounddown(Round(Round((G$9+G$10*($A14-1))*(1+(EnemyHPSlider-1)+(EnemyHPDanger-1)+(EnemyJackHP-1)),0)*IF($A14>20,(1+Max(0,((($A14-20)*(($A14-20)+1))/2)/100)*(2+Max(0,($A14-35)*0.2))*2),1),0)*IF(EnemyBuffed=TRUE,2.5,1),0) -> 115 | H14: =Rounddown(Round(Round((H$9+H$10*($A14-1))*(1+(EnemyHPSlider-1)+(EnemyHPDanger-1)+(EnemyJackHP-1)),0)*IF($A14>20,(1+Max(0,((($A14-20)*(($A14-20)+1))/2)/100)*(2+Max(0,($A14-35)*0.2))*2),1),0)*IF(EnemyBuffed=TRUE,2.5,1),0) -> 74 | I14: =Rounddown(Round(Round((I$9+I$10*($A14-1))*(1+(EnemyHPSlider-1)+(EnemyHPDanger-1)+(EnemyJackHP-1)),0)*IF($A14>20,(1+Max(0,((($A14-20)*(($A14-20)+1))/2)/100)*(2+Max(0,($A14-35)*0.2))*2),1),0)*IF(EnemyBuffed=TRUE,2.5,1),0) -> 41 | ... X14: =Rounddown(Round(Round((X$9+X$10*($A14-1))*(1+(EnemyHPSlider-1)+(EnemyHPDanger-1)+(EnemyJackHP-1)),0)*IF($A14>20,(1+Max(0,((($A14-20)*(($A14-20)+1))/2)/100)*(2+Max(0,($A14-35)*0.2))*2),1),0)*IF(EnemyBuffed=TRUE,2.5,1),0) -> 2941 | Y14: =Rounddown(Round(Round((Y$9+Y$10*($A14-1))*(1+(EnemyHPSlider-1)+(EnemyHPDanger-1)+(EnemyJackHP-1)),0)*IF($A14>20,(1+Max(0,((($A14-20)*(($A14-20)+1))/2)/100)*(2+Max(0,($A14-35)*0.2))*2),1),0)*IF(EnemyBuffed=TRUE,2.5,1)*IF(AND($B$2=5,$A14<=20),0.75,1),0) -> 18112 | Z14: =Rounddown(Round(Round((Z$9+Z$10*($A14-1))*(1+(EnemyHPSlider-1)+(EnemyHPDanger-1)+(EnemyJackHP-1)),0)*IF($A14>20,(1+Max(0,((($A14-20)*(($A14-20)+1))/2)/100)*(2+Max(0,($A14-35)*0.2))*2),1),0)*IF(EnemyBuffed=TRUE,2.5,1)*IF(AND($B$2=5,$A14<=20),0.75,1),0) -> 18112 | AA14: =Rounddown(Round(Round((AA$9+AA$10*($A14-1))*(1+(EnemyHPSlider-1)+(EnemyHPDanger-1)+(EnemyJackHP-1)),0)*IF($A14>20,(1+Max(0,((($A14-20)*(($A14-20)+1))/2)/100)*(2+Max(0,($A14-35)*0.2))*2),1),0)*IF(EnemyBuffed=TRUE,2.5,1),0) -> 105
A15: 5 | B15: =Rounddown(Round(Round((B$9+B$10*($A15-1))*(1+(EnemyHPSlider-1)+(EnemyHPDanger-1)+(EnemyJackHP-1)),0)*IF($A15>20,(1+Max(0,((($A15-20)*(($A15-20)+1))/2)/100)*(2+Max(0,($A15-35)*0.2))*2),1),0)*IF(EnemyBuffed=TRUE,2.5,1),0) -> 42 | C15: =Rounddown(Round(Round((C$9+C$10*($A15-1))*(1+(EnemyHPSlider-1)+(EnemyHPDanger-1)+(EnemyJackHP-1)),0)*IF($A15>20,(1+Max(0,((($A15-20)*(($A15-20)+1))/2)/100)*(2+Max(0,($A15-35)*0.2))*2),1),0)*IF(EnemyBuffed=TRUE,2.5,1),0) -> 15 | D15: =Rounddown(Round(Round((D$9+D$10*($A15-1))*(1+(EnemyHPSlider-1)+(EnemyHPDanger-1)+(EnemyJackHP-1)),0)*IF($A15>20,(1+Max(0,((($A15-20)*(($A15-20)+1))/2)/100)*(2+Max(0,($A15-35)*0.2))*2),1),0)*IF(EnemyBuffed=TRUE,2.5,1),0) -> 7 | E15: =Rounddown(Round(Round((E$9+E$10*($A15-1))*(1+(EnemyHPSlider-1)+(EnemyHPDanger-1)+(EnemyJackHP-1)),0)*IF($A15>20,(1+Max(0,((($A15-20)*(($A15-20)+1))/2)/100)*(2+Max(0,($A15-35)*0.2))*2),1),0)*IF(EnemyBuffed=TRUE,2.5,1),0) -> 17 | F15: =Rounddown(Round(Round((F$9+F$10*($A15-1))*(1+(EnemyHPSlider-1)+(EnemyHPDanger-1)+(EnemyJackHP-1)),0)*IF($A15>20,(1+Max(0,((($A15-20)*(($A15-20)+1))/2)/100)*(2+Max(0,($A15-35)*0.2))*2),1),0)*IF(EnemyBuffed=TRUE,2.5,1),0) -> 20 | G15: =Rounddown(Round(Round((G$9+G$10*($A15-1))*(1+(EnemyHPSlider-1)+(EnemyHPDanger-1)+(EnemyJackHP-1)),0)*IF($A15>20,(1+Max(0,((($A15-20)*(($A15-20)+1))/2)/100)*(2+Max(0,($A15-35)*0.2))*2),1),0)*IF(EnemyBuffed=TRUE,2.5,1),0) -> 148 | H15: =Rounddown(Round(Round((H$9+H$10*($A15-1))*(1+(EnemyHPSlider-1)+(EnemyHPDanger-1)+(EnemyJackHP-1)),0)*IF($A15>20,(1+Max(0,((($A15-20)*(($A15-20)+1))/2)/100)*(2+Max(0,($A15-35)*0.2))*2),1),0)*IF(EnemyBuffed=TRUE,2.5,1),0) -> 90 | I15: =Rounddown(Round(Round((I$9+I$10*($A15-1))*(1+(EnemyHPSlider-1)+(EnemyHPDanger-1)+(EnemyJackHP-1)),0)*IF($A15>20,(1+Max(0,((($A15-20)*(($A15-20)+1))/2)/100)*(2+Max(0,($A15-35)*0.2))*2),1),0)*IF(EnemyBuffed=TRUE,2.5,1),0) -> 45 | ... X15: =Rounddown(Round(Round((X$9+X$10*($A15-1))*(1+(EnemyHPSlider-1)+(EnemyHPDanger-1)+(EnemyJackHP-1)),0)*IF($A15>20,(1+Max(0,((($A15-20)*(($A15-20)+1))/2)/100)*(2+Max(0,($A15-35)*0.2))*2),1),0)*IF(EnemyBuffed=TRUE,2.5,1),0) -> 3921 | Y15: =Rounddown(Round(Round((Y$9+Y$10*($A15-1))*(1+(EnemyHPSlider-1)+(EnemyHPDanger-1)+(EnemyJackHP-1)),0)*IF($A15>20,(1+Max(0,((($A15-20)*(($A15-20)+1))/2)/100)*(2+Max(0,($A15-35)*0.2))*2),1),0)*IF(EnemyBuffed=TRUE,2.5,1)*IF(AND($B$2=5,$A15<=20),0.75,1),0) -> 18900 | Z15: =Rounddown(Round(Round((Z$9+Z$10*($A15-1))*(1+(EnemyHPSlider-1)+(EnemyHPDanger-1)+(EnemyJackHP-1)),0)*IF($A15>20,(1+Max(0,((($A15-20)*(($A15-20)+1))/2)/100)*(2+Max(0,($A15-35)*0.2))*2),1),0)*IF(EnemyBuffed=TRUE,2.5,1)*IF(AND($B$2=5,$A15<=20),0.75,1),0) -> 18900 | AA15: =Rounddown(Round(Round((AA$9+AA$10*($A15-1))*(1+(EnemyHPSlider-1)+(EnemyHPDanger-1)+(EnemyJackHP-1)),0)*IF($A15>20,(1+Max(0,((($A15-20)*(($A15-20)+1))/2)/100)*(2+Max(0,($A15-35)*0.2))*2),1),0)*IF(EnemyBuffed=TRUE,2.5,1),0) -> 126
A16: 6 | B16: =Rounddown(Round(Round((B$9+B$10*($A16-1))*(1+(EnemyHPSlider-1)+(EnemyHPDanger-1)+(EnemyJackHP-1)),0)*IF($A16>20,(1+Max(0,((($A16-20)*(($A16-20)+1))/2)/100)*(2+Max(0,($A16-35)*0.2))*2),1),0)*IF(EnemyBuffed=TRUE,2.5,1),0) -> 49 | C16: =Rounddown(Round(Round((C$9+C$10*($A16-1))*(1+(EnemyHPSlider-1)+(EnemyHPDanger-1)+(EnemyJackHP-1)),0)*IF($A16>20,(1+Max(0,((($A16-20)*(($A16-20)+1))/2)/100)*(2+Max(0,($A16-35)*0.2))*2),1),0)*IF(EnemyBuffed=TRUE,2.5,1),0) -> 18 | D16: =Rounddown(Round(Round((D$9+D$10*($A16-1))*(1+(EnemyHPSlider-1)+(EnemyHPDanger-1)+(EnemyJackHP-1)),0)*IF($A16>20,(1+Max(0,((($A16-20)*(($A16-20)+1))/2)/100)*(2+Max(0,($A16-35)*0.2))*2),1),0)*IF(EnemyBuffed=TRUE,2.5,1),0) -> 8 | E16: =Rounddown(Round(Round((E$9+E$10*($A16-1))*(1+(EnemyHPSlider-1)+(EnemyHPDanger-1)+(EnemyJackHP-1)),0)*IF($A16>20,(1+Max(0,((($A16-20)*(($A16-20)+1))/2)/100)*(2+Max(0,($A16-35)*0.2))*2),1),0)*IF(EnemyBuffed=TRUE,2.5,1),0) -> 18 | F16: =Rounddown(Round(Round((F$9+F$10*($A16-1))*(1+(EnemyHPSlider-1)+(EnemyHPDanger-1)+(EnemyJackHP-1)),0)*IF($A16>20,(1+Max(0,((($A16-20)*(($A16-20)+1))/2)/100)*(2+Max(0,($A16-35)*0.2))*2),1),0)*IF(EnemyBuffed=TRUE,2.5,1),0) -> 23 | G16: =Rounddown(Round(Round((G$9+G$10*($A16-1))*(1+(EnemyHPSlider-1)+(EnemyHPDanger-1)+(EnemyJackHP-1)),0)*IF($A16>20,(1+Max(0,((($A16-20)*(($A16-20)+1))/2)/100)*(2+Max(0,($A16-35)*0.2))*2),1),0)*IF(EnemyBuffed=TRUE,2.5,1),0) -> 182 | H16: =Rounddown(Round(Round((H$9+H$10*($A16-1))*(1+(EnemyHPSlider-1)+(EnemyHPDanger-1)+(EnemyJackHP-1)),0)*IF($A16>20,(1+Max(0,((($A16-20)*(($A16-20)+1))/2)/100)*(2+Max(0,($A16-35)*0.2))*2),1),0)*IF(EnemyBuffed=TRUE,2.5,1),0) -> 105 | I16: =Rounddown(Round(Round((I$9+I$10*($A16-1))*(1+(EnemyHPSlider-1)+(EnemyHPDanger-1)+(EnemyJackHP-1)),0)*IF($A16>20,(1+Max(0,((($A16-20)*(($A16-20)+1))/2)/100)*(2+Max(0,($A16-35)*0.2))*2),1),0)*IF(EnemyBuffed=TRUE,2.5,1),0) -> 49 | ... X16: =Rounddown(Round(Round((X$9+X$10*($A16-1))*(1+(EnemyHPSlider-1)+(EnemyHPDanger-1)+(EnemyJackHP-1)),0)*IF($A16>20,(1+Max(0,((($A16-20)*(($A16-20)+1))/2)/100)*(2+Max(0,($A16-35)*0.2))*2),1),0)*IF(EnemyBuffed=TRUE,2.5,1),0) -> 4901 | Y16: =Rounddown(Round(Round((Y$9+Y$10*($A16-1))*(1+(EnemyHPSlider-1)+(EnemyHPDanger-1)+(EnemyJackHP-1)),0)*IF($A16>20,(1+Max(0,((($A16-20)*(($A16-20)+1))/2)/100)*(2+Max(0,($A16-35)*0.2))*2),1),0)*IF(EnemyBuffed=TRUE,2.5,1)*IF(AND($B$2=5,$A16<=20),0.75,1),0) -> 19687 | Z16: =Rounddown(Round(Round((Z$9+Z$10*($A16-1))*(1+(EnemyHPSlider-1)+(EnemyHPDanger-1)+(EnemyJackHP-1)),0)*IF($A16>20,(1+Max(0,((($A16-20)*(($A16-20)+1))/2)/100)*(2+Max(0,($A16-35)*0.2))*2),1),0)*IF(EnemyBuffed=TRUE,2.5,1)*IF(AND($B$2=5,$A16<=20),0.75,1),0) -> 19687 | AA16: =Rounddown(Round(Round((AA$9+AA$10*($A16-1))*(1+(EnemyHPSlider-1)+(EnemyHPDanger-1)+(EnemyJackHP-1)),0)*IF($A16>20,(1+Max(0,((($A16-20)*(($A16-20)+1))/2)/100)*(2+Max(0,($A16-35)*0.2))*2),1),0)*IF(EnemyBuffed=TRUE,2.5,1),0) -> 147
A17: 7 | B17: =Rounddown(Round(Round((B$9+B$10*($A17-1))*(1+(EnemyHPSlider-1)+(EnemyHPDanger-1)+(EnemyJackHP-1)),0)*IF($A17>20,(1+Max(0,((($A17-20)*(($A17-20)+1))/2)/100)*(2+Max(0,($A17-35)*0.2))*2),1),0)*IF(EnemyBuffed=TRUE,2.5,1),0) -> 56 | C17: =Rounddown(Round(Round((C$9+C$10*($A17-1))*(1+(EnemyHPSlider-1)+(EnemyHPDanger-1)+(EnemyJackHP-1)),0)*IF($A17>20,(1+Max(0,((($A17-20)*(($A17-20)+1))/2)/100)*(2+Max(0,($A17-35)*0.2))*2),1),0)*IF(EnemyBuffed=TRUE,2.5,1),0) -> 21 | D17: =Rounddown(Round(Round((D$9+D$10*($A17-1))*(1+(EnemyHPSlider-1)+(EnemyHPDanger-1)+(EnemyJackHP-1)),0)*IF($A17>20,(1+Max(0,((($A17-20)*(($A17-20)+1))/2)/100)*(2+Max(0,($A17-35)*0.2))*2),1),0)*IF(EnemyBuffed=TRUE,2.5,1),0) -> 10 | E17: =Rounddown(Round(Round((E$9+E$10*($A17-1))*(1+(EnemyHPSlider-1)+(EnemyHPDanger-1)+(EnemyJackHP-1)),0)*IF($A17>20,(1+Max(0,((($A17-20)*(($A17-20)+1))/2)/100)*(2+Max(0,($A17-35)*0.2))*2),1),0)*IF(EnemyBuffed=TRUE,2.5,1),0) -> 20 | F17: =Rounddown(Round(Round((F$9+F$10*($A17-1))*(1+(EnemyHPSlider-1)+(EnemyHPDanger-1)+(EnemyJackHP-1)),0)*IF($A17>20,(1+Max(0,((($A17-20)*(($A17-20)+1))/2)/100)*(2+Max(0,($A17-35)*0.2))*2),1),0)*IF(EnemyBuffed=TRUE,2.5,1),0) -> 27 | G17: =Rounddown(Round(Round((G$9+G$10*($A17-1))*(1+(EnemyHPSlider-1)+(EnemyHPDanger-1)+(EnemyJackHP-1)),0)*IF($A17>20,(1+Max(0,((($A17-20)*(($A17-20)+1))/2)/100)*(2+Max(0,($A17-35)*0.2))*2),1),0)*IF(EnemyBuffed=TRUE,2.5,1),0) -> 216 | H17: =Rounddown(Round(Round((H$9+H$10*($A17-1))*(1+(EnemyHPSlider-1)+(EnemyHPDanger-1)+(EnemyJackHP-1)),0)*IF($A17>20,(1+Max(0,((($A17-20)*(($A17-20)+1))/2)/100)*(2+Max(0,($A17-35)*0.2))*2),1),0)*IF(EnemyBuffed=TRUE,2.5,1),0) -> 120 | I17: =Rounddown(Round(Round((I$9+I$10*($A17-1))*(1+(EnemyHPSlider-1)+(EnemyHPDanger-1)+(EnemyJackHP-1)),0)*IF($A17>20,(1+Max(0,((($A17-20)*(($A17-20)+1))/2)/100)*(2+Max(0,($A17-35)*0.2))*2),1),0)*IF(EnemyBuffed=TRUE,2.5,1),0) -> 53 | ... X17: =Rounddown(Round(Round((X$9+X$10*($A17-1))*(1+(EnemyHPSlider-1)+(EnemyHPDanger-1)+(EnemyJackHP-1)),0)*IF($A17>20,(1+Max(0,((($A17-20)*(($A17-20)+1))/2)/100)*(2+Max(0,($A17-35)*0.2))*2),1),0)*IF(EnemyBuffed=TRUE,2.5,1),0) -> 5881 | Y17: =Rounddown(Round(Round((Y$9+Y$10*($A17-1))*(1+(EnemyHPSlider-1)+(EnemyHPDanger-1)+(EnemyJackHP-1)),0)*IF($A17>20,(1+Max(0,((($A17-20)*(($A17-20)+1))/2)/100)*(2+Max(0,($A17-35)*0.2))*2),1),0)*IF(EnemyBuffed=TRUE,2.5,1)*IF(AND($B$2=5,$A17<=20),0.75,1),0) -> 20475 | Z17: =Rounddown(Round(Round((Z$9+Z$10*($A17-1))*(1+(EnemyHPSlider-1)+(EnemyHPDanger-1)+(EnemyJackHP-1)),0)*IF($A17>20,(1+Max(0,((($A17-20)*(($A17-20)+1))/2)/100)*(2+Max(0,($A17-35)*0.2))*2),1),0)*IF(EnemyBuffed=TRUE,2.5,1)*IF(AND($B$2=5,$A17<=20),0.75,1),0) -> 20475 | AA17: =Rounddown(Round(Round((AA$9+AA$10*($A17-1))*(1+(EnemyHPSlider-1)+(EnemyHPDanger-1)+(EnemyJackHP-1)),0)*IF($A17>20,(1+Max(0,((($A17-20)*(($A17-20)+1))/2)/100)*(2+Max(0,($A17-35)*0.2))*2),1),0)*IF(EnemyBuffed=TRUE,2.5,1),0) -> 168
A18: 8 | B18: =Rounddown(Round(Round((B$9+B$10*($A18-1))*(1+(EnemyHPSlider-1)+(EnemyHPDanger-1)+(EnemyJackHP-1)),0)*IF($A18>20,(1+Max(0,((($A18-20)*(($A18-20)+1))/2)/100)*(2+Max(0,($A18-35)*0.2))*2),1),0)*IF(EnemyBuffed=TRUE,2.5,1),0) -> 63 | C18: =Rounddown(Round(Round((C$9+C$10*($A18-1))*(1+(EnemyHPSlider-1)+(EnemyHPDanger-1)+(EnemyJackHP-1)),0)*IF($A18>20,(1+Max(0,((($A18-20)*(($A18-20)+1))/2)/100)*(2+Max(0,($A18-35)*0.2))*2),1),0)*IF(EnemyBuffed=TRUE,2.5,1),0) -> 24 | D18: =Rounddown(Round(Round((D$9+D$10*($A18-1))*(1+(EnemyHPSlider-1)+(EnemyHPDanger-1)+(EnemyJackHP-1)),0)*IF($A18>20,(1+Max(0,((($A18-20)*(($A18-20)+1))/2)/100)*(2+Max(0,($A18-35)*0.2))*2),1),0)*IF(EnemyBuffed=TRUE,2.5,1),0) -> 11 | E18: =Rounddown(Round(Round((E$9+E$10*($A18-1))*(1+(EnemyHPSlider-1)+(EnemyHPDanger-1)+(EnemyJackHP-1)),0)*IF($A18>20,(1+Max(0,((($A18-20)*(($A18-20)+1))/2)/100)*(2+Max(0,($A18-35)*0.2))*2),1),0)*IF(EnemyBuffed=TRUE,2.5,1),0) -> 21 | F18: =Rounddown(Round(Round((F$9+F$10*($A18-1))*(1+(EnemyHPSlider-1)+(EnemyHPDanger-1)+(EnemyJackHP-1)),0)*IF($A18>20,(1+Max(0,((($A18-20)*(($A18-20)+1))/2)/100)*(2+Max(0,($A18-35)*0.2))*2),1),0)*IF(EnemyBuffed=TRUE,2.5,1),0) -> 30 | G18: =Rounddown(Round(Round((G$9+G$10*($A18-1))*(1+(EnemyHPSlider-1)+(EnemyHPDanger-1)+(EnemyJackHP-1)),0)*IF($A18>20,(1+Max(0,((($A18-20)*(($A18-20)+1))/2)/100)*(2+Max(0,($A18-35)*0.2))*2),1),0)*IF(EnemyBuffed=TRUE,2.5,1),0) -> 249 | H18: =Rounddown(Round(Round((H$9+H$10*($A18-1))*(1+(EnemyHPSlider-1)+(EnemyHPDanger-1)+(EnemyJackHP-1)),0)*IF($A18>20,(1+Max(0,((($A18-20)*(($A18-20)+1))/2)/100)*(2+Max(0,($A18-35)*0.2))*2),1),0)*IF(EnemyBuffed=TRUE,2.5,1),0) -> 136 | I18: =Rounddown(Round(Round((I$9+I$10*($A18-1))*(1+(EnemyHPSlider-1)+(EnemyHPDanger-1)+(EnemyJackHP-1)),0)*IF($A18>20,(1+Max(0,((($A18-20)*(($A18-20)+1))/2)/100)*(2+Max(0,($A18-35)*0.2))*2),1),0)*IF(EnemyBuffed=TRUE,2.5,1),0) -> 57 | ... X18: =Rounddown(Round(Round((X$9+X$10*($A18-1))*(1+(EnemyHPSlider-1)+(EnemyHPDanger-1)+(EnemyJackHP-1)),0)*IF($A18>20,(1+Max(0,((($A18-20)*(($A18-20)+1))/2)/100)*(2+Max(0,($A18-35)*0.2))*2),1),0)*IF(EnemyBuffed=TRUE,2.5,1),0) -> 6861 | Y18: =Rounddown(Round(Round((Y$9+Y$10*($A18-1))*(1+(EnemyHPSlider-1)+(EnemyHPDanger-1)+(EnemyJackHP-1)),0)*IF($A18>20,(1+Max(0,((($A18-20)*(($A18-20)+1))/2)/100)*(2+Max(0,($A18-35)*0.2))*2),1),0)*IF(EnemyBuffed=TRUE,2.5,1)*IF(AND($B$2=5,$A18<=20),0.75,1),0) -> 21262 | Z18: =Rounddown(Round(Round((Z$9+Z$10*($A18-1))*(1+(EnemyHPSlider-1)+(EnemyHPDanger-1)+(EnemyJackHP-1)),0)*IF($A18>20,(1+Max(0,((($A18-20)*(($A18-20)+1))/2)/100)*(2+Max(0,($A18-35)*0.2))*2),1),0)*IF(EnemyBuffed=TRUE,2.5,1)*IF(AND($B$2=5,$A18<=20),0.75,1),0) -> 21262 | AA18: =Rounddown(Round(Round((AA$9+AA$10*($A18-1))*(1+(EnemyHPSlider-1)+(EnemyHPDanger-1)+(EnemyJackHP-1)),0)*IF($A18>20,(1+Max(0,((($A18-20)*(($A18-20)+1))/2)/100)*(2+Max(0,($A18-35)*0.2))*2),1),0)*IF(EnemyBuffed=TRUE,2.5,1),0) -> 189
A19: 9 | B19: =Rounddown(Round(Round((B$9+B$10*($A19-1))*(1+(EnemyHPSlider-1)+(EnemyHPDanger-1)+(EnemyJackHP-1)),0)*IF($A19>20,(1+Max(0,((($A19-20)*(($A19-20)+1))/2)/100)*(2+Max(0,($A19-35)*0.2))*2),1),0)*IF(EnemyBuffed=TRUE,2.5,1),0) -> 70 | C19: =Rounddown(Round(Round((C$9+C$10*($A19-1))*(1+(EnemyHPSlider-1)+(EnemyHPDanger-1)+(EnemyJackHP-1)),0)*IF($A19>20,(1+Max(0,((($A19-20)*(($A19-20)+1))/2)/100)*(2+Max(0,($A19-35)*0.2))*2),1),0)*IF(EnemyBuffed=TRUE,2.5,1),0) -> 27 | D19: =Rounddown(Round(Round((D$9+D$10*($A19-1))*(1+(EnemyHPSlider-1)+(EnemyHPDanger-1)+(EnemyJackHP-1)),0)*IF($A19>20,(1+Max(0,((($A19-20)*(($A19-20)+1))/2)/100)*(2+Max(0,($A19-35)*0.2))*2),1),0)*IF(EnemyBuffed=TRUE,2.5,1),0) -> 13 | E19: =Rounddown(Round(Round((E$9+E$10*($A19-1))*(1+(EnemyHPSlider-1)+(EnemyHPDanger-1)+(EnemyJackHP-1)),0)*IF($A19>20,(1+Max(0,((($A19-20)*(($A19-20)+1))/2)/100)*(2+Max(0,($A19-35)*0.2))*2),1),0)*IF(EnemyBuffed=TRUE,2.5,1),0) -> 22 | F19: =Rounddown(Round(Round((F$9+F$10*($A19-1))*(1+(EnemyHPSlider-1)+(EnemyHPDanger-1)+(EnemyJackHP-1)),0)*IF($A19>20,(1+Max(0,((($A19-20)*(($A19-20)+1))/2)/100)*(2+Max(0,($A19-35)*0.2))*2),1),0)*IF(EnemyBuffed=TRUE,2.5,1),0) -> 34 | G19: =Rounddown(Round(Round((G$9+G$10*($A19-1))*(1+(EnemyHPSlider-1)+(EnemyHPDanger-1)+(EnemyJackHP-1)),0)*IF($A19>20,(1+Max(0,((($A19-20)*(($A19-20)+1))/2)/100)*(2+Max(0,($A19-35)*0.2))*2),1),0)*IF(EnemyBuffed=TRUE,2.5,1),0) -> 283 | H19: =Rounddown(Round(Round((H$9+H$10*($A19-1))*(1+(EnemyHPSlider-1)+(EnemyHPDanger-1)+(EnemyJackHP-1)),0)*IF($A19>20,(1+Max(0,((($A19-20)*(($A19-20)+1))/2)/100)*(2+Max(0,($A19-35)*0.2))*2),1),0)*IF(EnemyBuffed=TRUE,2.5,1),0) -> 151 | I19: =Rounddown(Round(Round((I$9+I$10*($A19-1))*(1+(EnemyHPSlider-1)+(EnemyHPDanger-1)+(EnemyJackHP-1)),0)*IF($A19>20,(1+Max(0,((($A19-20)*(($A19-20)+1))/2)/100)*(2+Max(0,($A19-35)*0.2))*2),1),0)*IF(EnemyBuffed=TRUE,2.5,1),0) -> 62 | ... X19: =Rounddown(Round(Round((X$9+X$10*($A19-1))*(1+(EnemyHPSlider-1)+(EnemyHPDanger-1)+(EnemyJackHP-1)),0)*IF($A19>20,(1+Max(0,((($A19-20)*(($A19-20)+1))/2)/100)*(2+Max(0,($A19-35)*0.2))*2),1),0)*IF(EnemyBuffed=TRUE,2.5,1),0) -> 7841 | Y19: =Rounddown(Round(Round((Y$9+Y$10*($A19-1))*(1+(EnemyHPSlider-1)+(EnemyHPDanger-1)+(EnemyJackHP-1)),0)*IF($A19>20,(1+Max(0,((($A19-20)*(($A19-20)+1))/2)/100)*(2+Max(0,($A19-35)*0.2))*2),1),0)*IF(EnemyBuffed=TRUE,2.5,1)*IF(AND($B$2=5,$A19<=20),0.75,1),0) -> 22050 | Z19: =Rounddown(Round(Round((Z$9+Z$10*($A19-1))*(1+(EnemyHPSlider-1)+(EnemyHPDanger-1)+(EnemyJackHP-1)),0)*IF($A19>20,(1+Max(0,((($A19-20)*(($A19-20)+1))/2)/100)*(2+Max(0,($A19-35)*0.2))*2),1),0)*IF(EnemyBuffed=TRUE,2.5,1)*IF(AND($B$2=5,$A19<=20),0.75,1),0) -> 22050 | AA19: =Rounddown(Round(Round((AA$9+AA$10*($A19-1))*(1+(EnemyHPSlider-1)+(EnemyHPDanger-1)+(EnemyJackHP-1)),0)*IF($A19>20,(1+Max(0,((($A19-20)*(($A19-20)+1))/2)/100)*(2+Max(0,($A19-35)*0.2))*2),1),0)*IF(EnemyBuffed=TRUE,2.5,1),0) -> 210
A20: 10 | B20: =Rounddown(Round(Round((B$9+B$10*($A20-1))*(1+(EnemyHPSlider-1)+(EnemyHPDanger-1)+(EnemyJackHP-1)),0)*IF($A20>20,(1+Max(0,((($A20-20)*(($A20-20)+1))/2)/100)*(2+Max(0,($A20-35)*0.2))*2),1),0)*IF(EnemyBuffed=TRUE,2.5,1),0) -> 77 | C20: =Rounddown(Round(Round((C$9+C$10*($A20-1))*(1+(EnemyHPSlider-1)+(EnemyHPDanger-1)+(EnemyJackHP-1)),0)*IF($A20>20,(1+Max(0,((($A20-20)*(($A20-20)+1))/2)/100)*(2+Max(0,($A20-35)*0.2))*2),1),0)*IF(EnemyBuffed=TRUE,2.5,1),0) -> 29 | D20: =Rounddown(Round(Round((D$9+D$10*($A20-1))*(1+(EnemyHPSlider-1)+(EnemyHPDanger-1)+(EnemyJackHP-1)),0)*IF($A20>20,(1+Max(0,((($A20-20)*(($A20-20)+1))/2)/100)*(2+Max(0,($A20-35)*0.2))*2),1),0)*IF(EnemyBuffed=TRUE,2.5,1),0) -> 14 | E20: =Rounddown(Round(Round((E$9+E$10*($A20-1))*(1+(EnemyHPSlider-1)+(EnemyHPDanger-1)+(EnemyJackHP-1)),0)*IF($A20>20,(1+Max(0,((($A20-20)*(($A20-20)+1))/2)/100)*(2+Max(0,($A20-35)*0.2))*2),1),0)*IF(EnemyBuffed=TRUE,2.5,1),0) -> 24 | F20: =Rounddown(Round(Round((F$9+F$10*($A20-1))*(1+(EnemyHPSlider-1)+(EnemyHPDanger-1)+(EnemyJackHP-1)),0)*IF($A20>20,(1+Max(0,((($A20-20)*(($A20-20)+1))/2)/100)*(2+Max(0,($A20-35)*0.2))*2),1),0)*IF(EnemyBuffed=TRUE,2.5,1),0) -> 37 | G20: =Rounddown(Round(Round((G$9+G$10*($A20-1))*(1+(EnemyHPSlider-1)+(EnemyHPDanger-1)+(EnemyJackHP-1)),0)*IF($A20>20,(1+Max(0,((($A20-20)*(($A20-20)+1))/2)/100)*(2+Max(0,($A20-35)*0.2))*2),1),0)*IF(EnemyBuffed=TRUE,2.5,1),0) -> 316 | H20: =Rounddown(Round(Round((H$9+H$10*($A20-1))*(1+(EnemyHPSlider-1)+(EnemyHPDanger-1)+(EnemyJackHP-1)),0)*IF($A20>20,(1+Max(0,((($A20-20)*(($A20-20)+1))/2)/100)*(2+Max(0,($A20-35)*0.2))*2),1),0)*IF(EnemyBuffed=TRUE,2.5,1),0) -> 167 | I20: =Rounddown(Round(Round((I$9+I$10*($A20-1))*(1+(EnemyHPSlider-1)+(EnemyHPDanger-1)+(EnemyJackHP-1)),0)*IF($A20>20,(1+Max(0,((($A20-20)*(($A20-20)+1))/2)/100)*(2+Max(0,($A20-35)*0.2))*2),1),0)*IF(EnemyBuffed=TRUE,2.5,1),0) -> 66 | ... X20: =Rounddown(Round(Round((X$9+X$10*($A20-1))*(1+(EnemyHPSlider-1)+(EnemyHPDanger-1)+(EnemyJackHP-1)),0)*IF($A20>20,(1+Max(0,((($A20-20)*(($A20-20)+1))/2)/100)*(2+Max(0,($A20-35)*0.2))*2),1),0)*IF(EnemyBuffed=TRUE,2.5,1),0) -> 8821 | Y20: =Rounddown(Round(Round((Y$9+Y$10*($A20-1))*(1+(EnemyHPSlider-1)+(EnemyHPDanger-1)+(EnemyJackHP-1)),0)*IF($A20>20,(1+Max(0,((($A20-20)*(($A20-20)+1))/2)/100)*(2+Max(0,($A20-35)*0.2))*2),1),0)*IF(EnemyBuffed=TRUE,2.5,1)*IF(AND($B$2=5,$A20<=20),0.75,1),0) -> 22837 | Z20: =Rounddown(Round(Round((Z$9+Z$10*($A20-1))*(1+(EnemyHPSlider-1)+(EnemyHPDanger-1)+(EnemyJackHP-1)),0)*IF($A20>20,(1+Max(0,((($A20-20)*(($A20-20)+1))/2)/100)*(2+Max(0,($A20-35)*0.2))*2),1),0)*IF(EnemyBuffed=TRUE,2.5,1)*IF(AND($B$2=5,$A20<=20),0.75,1),0) -> 22837 | AA20: =Rounddown(Round(Round((AA$9+AA$10*($A20-1))*(1+(EnemyHPSlider-1)+(EnemyHPDanger-1)+(EnemyJackHP-1)),0)*IF($A20>20,(1+Max(0,((($A20-20)*(($A20-20)+1))/2)/100)*(2+Max(0,($A20-35)*0.2))*2),1),0)*IF(EnemyBuffed=TRUE,2.5,1),0) -> 231
A21: 11 | B21: =Rounddown(Round(Round((B$9+B$10*($A21-1))*(1+(EnemyHPSlider-1)+(EnemyHPDanger-1)+(EnemyJackHP-1)),0)*IF($A21>20,(1+Max(0,((($A21-20)*(($A21-20)+1))/2)/100)*(2+Max(0,($A21-35)*0.2))*2),1),0)*IF(EnemyBuffed=TRUE,2.5,1),0) -> 84 | C21: =Rounddown(Round(Round((C$9+C$10*($A21-1))*(1+(EnemyHPSlider-1)+(EnemyHPDanger-1)+(EnemyJackHP-1)),0)*IF($A21>20,(1+Max(0,((($A21-20)*(($A21-20)+1))/2)/100)*(2+Max(0,($A21-35)*0.2))*2),1),0)*IF(EnemyBuffed=TRUE,2.5,1),0) -> 32 | D21: =Rounddown(Round(Round((D$9+D$10*($A21-1))*(1+(EnemyHPSlider-1)+(EnemyHPDanger-1)+(EnemyJackHP-1)),0)*IF($A21>20,(1+Max(0,((($A21-20)*(($A21-20)+1))/2)/100)*(2+Max(0,($A21-35)*0.2))*2),1),0)*IF(EnemyBuffed=TRUE,2.5,1),0) -> 15 | E21: =Rounddown(Round(Round((E$9+E$10*($A21-1))*(1+(EnemyHPSlider-1)+(EnemyHPDanger-1)+(EnemyJackHP-1)),0)*IF($A21>20,(1+Max(0,((($A21-20)*(($A21-20)+1))/2)/100)*(2+Max(0,($A21-35)*0.2))*2),1),0)*IF(EnemyBuffed=TRUE,2.5,1),0) -> 25 | F21: =Rounddown(Round(Round((F$9+F$10*($A21-1))*(1+(EnemyHPSlider-1)+(EnemyHPDanger-1)+(EnemyJackHP-1)),0)*IF($A21>20,(1+Max(0,((($A21-20)*(($A21-20)+1))/2)/100)*(2+Max(0,($A21-35)*0.2))*2),1),0)*IF(EnemyBuffed=TRUE,2.5,1),0) -> 41 | G21: =Rounddown(Round(Round((G$9+G$10*($A21-1))*(1+(EnemyHPSlider-1)+(EnemyHPDanger-1)+(EnemyJackHP-1)),0)*IF($A21>20,(1+Max(0,((($A21-20)*(($A21-20)+1))/2)/100)*(2+Max(0,($A21-35)*0.2))*2),1),0)*IF(EnemyBuffed=TRUE,2.5,1),0) -> 350 | H21: =Rounddown(Round(Round((H$9+H$10*($A21-1))*(1+(EnemyHPSlider-1)+(EnemyHPDanger-1)+(EnemyJackHP-1)),0)*IF($A21>20,(1+Max(0,((($A21-20)*(($A21-20)+1))/2)/100)*(2+Max(0,($A21-35)*0.2))*2),1),0)*IF(EnemyBuffed=TRUE,2.5,1),0) -> 182 | I21: =Rounddown(Round(Round((I$9+I$10*($A21-1))*(1+(EnemyHPSlider-1)+(EnemyHPDanger-1)+(EnemyJackHP-1)),0)*IF($A21>20,(1+Max(0,((($A21-20)*(($A21-20)+1))/2)/100)*(2+Max(0,($A21-35)*0.2))*2),1),0)*IF(EnemyBuffed=TRUE,2.5,1),0) -> 70 | ... X21: =Rounddown(Round(Round((X$9+X$10*($A21-1))*(1+(EnemyHPSlider-1)+(EnemyHPDanger-1)+(EnemyJackHP-1)),0)*IF($A21>20,(1+Max(0,((($A21-20)*(($A21-20)+1))/2)/100)*(2+Max(0,($A21-35)*0.2))*2),1),0)*IF(EnemyBuffed=TRUE,2.5,1),0) -> 9801 | Y21: =Rounddown(Round(Round((Y$9+Y$10*($A21-1))*(1+(EnemyHPSlider-1)+(EnemyHPDanger-1)+(EnemyJackHP-1)),0)*IF($A21>20,(1+Max(0,((($A21-20)*(($A21-20)+1))/2)/100)*(2+Max(0,($A21-35)*0.2))*2),1),0)*IF(EnemyBuffed=TRUE,2.5,1)*IF(AND($B$2=5,$A21<=20),0.75,1),0) -> 23625 | Z21: =Rounddown(Round(Round((Z$9+Z$10*($A21-1))*(1+(EnemyHPSlider-1)+(EnemyHPDanger-1)+(EnemyJackHP-1)),0)*IF($A21>20,(1+Max(0,((($A21-20)*(($A21-20)+1))/2)/100)*(2+Max(0,($A21-35)*0.2))*2),1),0)*IF(EnemyBuffed=TRUE,2.5,1)*IF(AND($B$2=5,$A21<=20),0.75,1),0) -> 23625 | AA21: =Rounddown(Round(Round((AA$9+AA$10*($A21-1))*(1+(EnemyHPSlider-1)+(EnemyHPDanger-1)+(EnemyJackHP-1)),0)*IF($A21>20,(1+Max(0,((($A21-20)*(($A21-20)+1))/2)/100)*(2+Max(0,($A21-35)*0.2))*2),1),0)*IF(EnemyBuffed=TRUE,2.5,1),0) -> 252
A22: 12 | B22: =Rounddown(Round(Round((B$9+B$10*($A22-1))*(1+(EnemyHPSlider-1)+(EnemyHPDanger-1)+(EnemyJackHP-1)),0)*IF($A22>20,(1+Max(0,((($A22-20)*(($A22-20)+1))/2)/100)*(2+Max(0,($A22-35)*0.2))*2),1),0)*IF(EnemyBuffed=TRUE,2.5,1),0) -> 91 | C22: =Rounddown(Round(Round((C$9+C$10*($A22-1))*(1+(EnemyHPSlider-1)+(EnemyHPDanger-1)+(EnemyJackHP-1)),0)*IF($A22>20,(1+Max(0,((($A22-20)*(($A22-20)+1))/2)/100)*(2+Max(0,($A22-35)*0.2))*2),1),0)*IF(EnemyBuffed=TRUE,2.5,1),0) -> 35 | D22: =Rounddown(Round(Round((D$9+D$10*($A22-1))*(1+(EnemyHPSlider-1)+(EnemyHPDanger-1)+(EnemyJackHP-1)),0)*IF($A22>20,(1+Max(0,((($A22-20)*(($A22-20)+1))/2)/100)*(2+Max(0,($A22-35)*0.2))*2),1),0)*IF(EnemyBuffed=TRUE,2.5,1),0) -> 17 | E22: =Rounddown(Round(Round((E$9+E$10*($A22-1))*(1+(EnemyHPSlider-1)+(EnemyHPDanger-1)+(EnemyJackHP-1)),0)*IF($A22>20,(1+Max(0,((($A22-20)*(($A22-20)+1))/2)/100)*(2+Max(0,($A22-35)*0.2))*2),1),0)*IF(EnemyBuffed=TRUE,2.5,1),0) -> 27 | F22: =Rounddown(Round(Round((F$9+F$10*($A22-1))*(1+(EnemyHPSlider-1)+(EnemyHPDanger-1)+(EnemyJackHP-1)),0)*IF($A22>20,(1+Max(0,((($A22-20)*(($A22-20)+1))/2)/100)*(2+Max(0,($A22-35)*0.2))*2),1),0)*IF(EnemyBuffed=TRUE,2.5,1),0) -> 44 | G22: =Rounddown(Round(Round((G$9+G$10*($A22-1))*(1+(EnemyHPSlider-1)+(EnemyHPDanger-1)+(EnemyJackHP-1)),0)*IF($A22>20,(1+Max(0,((($A22-20)*(($A22-20)+1))/2)/100)*(2+Max(0,($A22-35)*0.2))*2),1),0)*IF(EnemyBuffed=TRUE,2.5,1),0) -> 384 | H22: =Rounddown(Round(Round((H$9+H$10*($A22-1))*(1+(EnemyHPSlider-1)+(EnemyHPDanger-1)+(EnemyJackHP-1)),0)*IF($A22>20,(1+Max(0,((($A22-20)*(($A22-20)+1))/2)/100)*(2+Max(0,($A22-35)*0.2))*2),1),0)*IF(EnemyBuffed=TRUE,2.5,1),0) -> 197 | I22: =Rounddown(Round(Round((I$9+I$10*($A22-1))*(1+(EnemyHPSlider-1)+(EnemyHPDanger-1)+(EnemyJackHP-1)),0)*IF($A22>20,(1+Max(0,((($A22-20)*(($A22-20)+1))/2)/100)*(2+Max(0,($A22-35)*0.2))*2),1),0)*IF(EnemyBuffed=TRUE,2.5,1),0) -> 74 | ... X22: =Rounddown(Round(Round((X$9+X$10*($A22-1))*(1+(EnemyHPSlider-1)+(EnemyHPDanger-1)+(EnemyJackHP-1)),0)*IF($A22>20,(1+Max(0,((($A22-20)*(($A22-20)+1))/2)/100)*(2+Max(0,($A22-35)*0.2))*2),1),0)*IF(EnemyBuffed=TRUE,2.5,1),0) -> 10781 | Y22: =Rounddown(Round(Round((Y$9+Y$10*($A22-1))*(1+(EnemyHPSlider-1)+(EnemyHPDanger-1)+(EnemyJackHP-1)),0)*IF($A22>20,(1+Max(0,((($A22-20)*(($A22-20)+1))/2)/100)*(2+Max(0,($A22-35)*0.2))*2),1),0)*IF(EnemyBuffed=TRUE,2.5,1)*IF(AND($B$2=5,$A22<=20),0.75,1),0) -> 24412 | Z22: =Rounddown(Round(Round((Z$9+Z$10*($A22-1))*(1+(EnemyHPSlider-1)+(EnemyHPDanger-1)+(EnemyJackHP-1)),0)*IF($A22>20,(1+Max(0,((($A22-20)*(($A22-20)+1))/2)/100)*(2+Max(0,($A22-35)*0.2))*2),1),0)*IF(EnemyBuffed=TRUE,2.5,1)*IF(AND($B$2=5,$A22<=20),0.75,1),0) -> 24412 | AA22: =Rounddown(Round(Round((AA$9+AA$10*($A22-1))*(1+(EnemyHPSlider-1)+(EnemyHPDanger-1)+(EnemyJackHP-1)),0)*IF($A22>20,(1+Max(0,((($A22-20)*(($A22-20)+1))/2)/100)*(2+Max(0,($A22-35)*0.2))*2),1),0)*IF(EnemyBuffed=TRUE,2.5,1),0) -> 273
... A30: 20 | B30: =Rounddown(Round(Round((B$9+B$10*($A30-1))*(1+(EnemyHPSlider-1)+(EnemyHPDanger-1)+(EnemyJackHP-1)),0)*IF($A30>20,(1+Max(0,((($A30-20)*(($A30-20)+1))/2)/100)*(2+Max(0,($A30-35)*0.2))*2),1),0)*IF(EnemyBuffed=TRUE,2.5,1),0) -> 147 | C30: =Rounddown(Round(Round((C$9+C$10*($A30-1))*(1+(EnemyHPSlider-1)+(EnemyHPDanger-1)+(EnemyJackHP-1)),0)*IF($A30>20,(1+Max(0,((($A30-20)*(($A30-20)+1))/2)/100)*(2+Max(0,($A30-35)*0.2))*2),1),0)*IF(EnemyBuffed=TRUE,2.5,1),0) -> 57 | D30: =Rounddown(Round(Round((D$9+D$10*($A30-1))*(1+(EnemyHPSlider-1)+(EnemyHPDanger-1)+(EnemyJackHP-1)),0)*IF($A30>20,(1+Max(0,((($A30-20)*(($A30-20)+1))/2)/100)*(2+Max(0,($A30-35)*0.2))*2),1),0)*IF(EnemyBuffed=TRUE,2.5,1),0) -> 28 | E30: =Rounddown(Round(Round((E$9+E$10*($A30-1))*(1+(EnemyHPSlider-1)+(EnemyHPDanger-1)+(EnemyJackHP-1)),0)*IF($A30>20,(1+Max(0,((($A30-20)*(($A30-20)+1))/2)/100)*(2+Max(0,($A30-35)*0.2))*2),1),0)*IF(EnemyBuffed=TRUE,2.5,1),0) -> 38 | F30: =Rounddown(Round(Round((F$9+F$10*($A30-1))*(1+(EnemyHPSlider-1)+(EnemyHPDanger-1)+(EnemyJackHP-1)),0)*IF($A30>20,(1+Max(0,((($A30-20)*(($A30-20)+1))/2)/100)*(2+Max(0,($A30-35)*0.2))*2),1),0)*IF(EnemyBuffed=TRUE,2.5,1),0) -> 72 | G30: =Rounddown(Round(Round((G$9+G$10*($A30-1))*(1+(EnemyHPSlider-1)+(EnemyHPDanger-1)+(EnemyJackHP-1)),0)*IF($A30>20,(1+Max(0,((($A30-20)*(($A30-20)+1))/2)/100)*(2+Max(0,($A30-35)*0.2))*2),1),0)*IF(EnemyBuffed=TRUE,2.5,1),0) -> 652 | H30: =Rounddown(Round(Round((H$9+H$10*($A30-1))*(1+(EnemyHPSlider-1)+(EnemyHPDanger-1)+(EnemyJackHP-1)),0)*IF($A30>20,(1+Max(0,((($A30-20)*(($A30-20)+1))/2)/100)*(2+Max(0,($A30-35)*0.2))*2),1),0)*IF(EnemyBuffed=TRUE,2.5,1),0) -> 321 | I30: =Rounddown(Round(Round((I$9+I$10*($A30-1))*(1+(EnemyHPSlider-1)+(EnemyHPDanger-1)+(EnemyJackHP-1)),0)*IF($A30>20,(1+Max(0,((($A30-20)*(($A30-20)+1))/2)/100)*(2+Max(0,($A30-35)*0.2))*2),1),0)*IF(EnemyBuffed=TRUE,2.5,1),0) -> 108 | ... X30: =Rounddown(Round(Round((X$9+X$10*($A30-1))*(1+(EnemyHPSlider-1)+(EnemyHPDanger-1)+(EnemyJackHP-1)),0)*IF($A30>20,(1+Max(0,((($A30-20)*(($A30-20)+1))/2)/100)*(2+Max(0,($A30-35)*0.2))*2),1),0)*IF(EnemyBuffed=TRUE,2.5,1),0) -> 18621 | Y30: =Rounddown(Round(Round((Y$9+Y$10*($A30-1))*(1+(EnemyHPSlider-1)+(EnemyHPDanger-1)+(EnemyJackHP-1)),0)*IF($A30>20,(1+Max(0,((($A30-20)*(($A30-20)+1))/2)/100)*(2+Max(0,($A30-35)*0.2))*2),1),0)*IF(EnemyBuffed=TRUE,2.5,1)*IF(AND($B$2=5,$A30<=20),0.75,1),0) -> 30712 | Z30: =Rounddown(Round(Round((Z$9+Z$10*($A30-1))*(1+(EnemyHPSlider-1)+(EnemyHPDanger-1)+(EnemyJackHP-1)),0)*IF($A30>20,(1+Max(0,((($A30-20)*(($A30-20)+1))/2)/100)*(2+Max(0,($A30-35)*0.2))*2),1),0)*IF(EnemyBuffed=TRUE,2.5,1)*IF(AND($B$2=5,$A30<=20),0.75,1),0) -> 30712 | AA30: =Rounddown(Round(Round((AA$9+AA$10*($A30-1))*(1+(EnemyHPSlider-1)+(EnemyHPDanger-1)+(EnemyJackHP-1)),0)*IF($A30>20,(1+Max(0,((($A30-20)*(($A30-20)+1))/2)/100)*(2+Max(0,($A30-35)*0.2))*2),1),0)*IF(EnemyBuffed=TRUE,2.5,1),0) -> 441
A31: =$G$2 -> 400 | B31: =Rounddown(Round(Round((B$9+B$10*($A31-1))*(1+(EnemyHPSlider-1)+(EnemyHPDanger-1)+(EnemyJackHP-1)),0)*IF($A31>20,(1+Max(0,((($A31-20)*(($A31-20)+1))/2)/100)*(2+Max(0,($A31-35)*0.2))*2.25),1),0)*IF(EnemyBuffed=TRUE,2.5,1),0) -> 342900664 | C31: =Rounddown(Round(Round((C$9+C$10*($A31-1))*(1+(EnemyHPSlider-1)+(EnemyHPDanger-1)+(EnemyJackHP-1)),0)*IF($A31>20,(1+Max(0,((($A31-20)*(($A31-20)+1))/2)/100)*(2+Max(0,($A31-35)*0.2))*2.25),1),0)*IF(EnemyBuffed=TRUE,2.5,1),0) -> 136940379 | D31: =Rounddown(Round(Round((D$9+D$10*($A31-1))*(1+(EnemyHPSlider-1)+(EnemyHPDanger-1)+(EnemyJackHP-1)),0)*IF($A31>20,(1+Max(0,((($A31-20)*(($A31-20)+1))/2)/100)*(2+Max(0,($A31-35)*0.2))*2.25),1),0)*IF(EnemyBuffed=TRUE,2.5,1),0) -> 68409110 | E31: =Rounddown(Round(Round((E$9+E$10*($A31-1))*(1+(EnemyHPSlider-1)+(EnemyHPDanger-1)+(EnemyJackHP-1)),0)*IF($A31>20,(1+Max(0,((($A31-20)*(($A31-20)+1))/2)/100)*(2+Max(0,($A31-35)*0.2))*2.25),1),0)*IF(EnemyBuffed=TRUE,2.5,1),0) -> 69630701 | F31: =Rounddown(Round(Round((F$9+F$10*($A31-1))*(1+(EnemyHPSlider-1)+(EnemyHPDanger-1)+(EnemyJackHP-1)),0)*IF($A31>20,(1+Max(0,((($A31-20)*(($A31-20)+1))/2)/100)*(2+Max(0,($A31-35)*0.2))*2.25),1),0)*IF(EnemyBuffed=TRUE,2.5,1),0) -> 171267093 | G31: =Rounddown(Round(Round((G$9+G$10*($A31-1))*(1+(EnemyHPSlider-1)+(EnemyHPDanger-1)+(EnemyJackHP-1)),0)*IF($A31>20,(1+Max(0,((($A31-20)*(($A31-20)+1))/2)/100)*(2+Max(0,($A31-35)*0.2))*2.25),1),0)*IF(EnemyBuffed=TRUE,2.5,1),0) -> 1639375458 | H31: =Rounddown(Round(Round((H$9+H$10*($A31-1))*(1+(EnemyHPSlider-1)+(EnemyHPDanger-1)+(EnemyJackHP-1)),0)*IF($A31>20,(1+Max(0,((($A31-20)*(($A31-20)+1))/2)/100)*(2+Max(0,($A31-35)*0.2))*2.25),1),0)*IF(EnemyBuffed=TRUE,2.5,1),0) -> 754088279 | I31: =Rounddown(Round(Round((I$9+I$10*($A31-1))*(1+(EnemyHPSlider-1)+(EnemyHPDanger-1)+(EnemyJackHP-1)),0)*IF($A31>20,(1+Max(0,((($A31-20)*(($A31-20)+1))/2)/100)*(2+Max(0,($A31-35)*0.2))*2.25),1),0)*IF(EnemyBuffed=TRUE,2.5,1),0) -> 208159149 | ... X31: =Rounddown(Round(Round((X$9+X$10*($A31-1))*(1+(EnemyHPSlider-1)+(EnemyHPDanger-1)+(EnemyJackHP-1)),0)*IF($A31>20,(1+Max(0,((($A31-20)*(($A31-20)+1))/2)/100)*(2+Max(0,($A31-35)*0.2))*2.25),1),0)*IF(EnemyBuffed=TRUE,2.5,1),0) -> 47766783217 | Y31: =Rounddown(Round(Round((Y$9+Y$10*($A31-1))*(1+(EnemyHPSlider-1)+(EnemyHPDanger-1)+(EnemyJackHP-1)),0)*IF($A31>20,(1+Max(0,((($A31-20)*(($A31-20)+1))/2)/100)*(2+Max(0,($A31-35)*0.2))*2),1),0)*IF(EnemyBuffed=TRUE,2.5,1)*IF(AND($B$2=5,$A31<=20),0.75,1),0) -> 47772410700 | Z31: =Rounddown(Round(Round((Z$9+Z$10*($A31-1))*(1+(EnemyHPSlider-1)+(EnemyHPDanger-1)+(EnemyJackHP-1)),0)*IF($A31>20,(1+Max(0,((($A31-20)*(($A31-20)+1))/2)/100)*(2+Max(0,($A31-35)*0.2))*2),1),0)*IF(EnemyBuffed=TRUE,2.5,1)*IF(AND($B$2=5,$A31<=20),0.75,1),0) -> 47772410700 | AA31: =Rounddown(Round(Round((AA$9+AA$10*($A31-1))*(1+(EnemyHPSlider-1)+(EnemyHPDanger-1)+(EnemyJackHP-1)),0)*IF($A31>20,(1+Max(0,((($A31-20)*(($A31-20)+1))/2)/100)*(2+Max(0,($A31-35)*0.2))*2.25),1),0)*IF(EnemyBuffed=TRUE,2.5,1),0) -> 1028701992
A32: 伤害 | B32: 近战伤害（护甲结算后）
A33: 波数 | B33: 树 | C33: 异形幼体 | D33: 追猎者 | E33: 喷射者 | F33: 冲锋者 | G33: 追击者 | H33: 蛮兵 | I33: 增益者 | J33: 苍蝇 | K33: 治疗者 | L33: 掠夺者 | M33: 头盔异形 | N33: 鳍异形 | O33: 孵化者 | P33: 瘾君子 | Q33: 尖角蛮兵 | R33: 尖角冲锋者 | S33: 切割者之卵 | T33: 切割者 | U33: 触手 | V33: 犀牛 | W33: 屠夫 | X33: 武僧 | Y33: 掠食者 | Z33: 祈求者 | AA33: 七鳃鳗
A34: 基础伤害 | B34: 0 | C34: 1 | D34: 1 | E34: 1 | F34: 1 | G34: 1 | H34: 2 | I34: 1 | J34: 1 | K34: 1 | L34: 1 | M34: 1 | N34: 1 | O34: 1 | P34: 1 | Q34: 1 | R34: 1 | S34: 1 | T34: 1 | U34: 1 | V34: 1 | W34: 1 | X34: 1 | Y34: 1 | Z34: 1 | AA34: 1
A35: 伤害/波 | B35: 0 | C35: 0.6 | D35: 0.6 | E35: 0.6 | F35: 0.85 | G35: 1.2 | H35: 0.85 | I35: 0.6 | J35: 0.85 | K35: 0.85 | L35: 0.85 | M35: 1 | N35: 1 | O35: 0.85 | P35: 1 | Q35: 1.15 | R35: 1.1 | S35: 0.6 | T35: 1.15 | U35: 1 | V35: 1.5 | W35: 1.5 | X35: 1.5 | Y35: 1.5 | Z35: 1.5 | AA35: 0.75
A36: 1 | B36: 0 | C36: =Rounddown(Round(Round((C$34+C$35*($A36-1))*(1+(EnemyDamageSlider-1)+(EnemyDMGDanger-1)+(EnemyJackDMG-1)),0)*IF($A36>20,(1+Max(0,((($A36-20)*(($A36-20)+1))/2)/100)*(2+Max(0,($A36-35)*0.2))),1),0)*IF(EnemyBuffed=TRUE,1.25,1),0) & " (" & MAX(ROUND(Rounddown(Round(Round((C$34+C$35*($A36-1))*(1+(EnemyDamageSlider-1)+(EnemyDMGDanger-1)+(EnemyJackDMG-1)),0)*IF($A36>20,(1+Max(0,((($A36-20)*(($A36-20)+1))/2)/100)*(2+Max(0,($A36-35)*0.2))),1),0)*IF(EnemyBuffed=TRUE,1.25,1),0)*EnemyDMGTaken,0),1) & ")" -> 1 (1) | D36: =Rounddown(Round(Round((D$34+D$35*($A36-1))*(1+(EnemyDamageSlider-1)+(EnemyDMGDanger-1)+(EnemyJackDMG-1)),0)*IF($A36>20,(1+Max(0,((($A36-20)*(($A36-20)+1))/2)/100)*(2+Max(0,($A36-35)*0.2))),1),0)*IF(EnemyBuffed=TRUE,1.25,1),0) & " (" & MAX(ROUND(Rounddown(Round(Round((D$34+D$35*($A36-1))*(1+(EnemyDamageSlider-1)+(EnemyDMGDanger-1)+(EnemyJackDMG-1)),0)*IF($A36>20,(1+Max(0,((($A36-20)*(($A36-20)+1))/2)/100)*(2+Max(0,($A36-35)*0.2))),1),0)*IF(EnemyBuffed=TRUE,1.25,1),0)*EnemyDMGTaken,0),1) & ")" -> 1 (1) | E36: =Rounddown(Round(Round((E$34+E$35*($A36-1))*(1+(EnemyDamageSlider-1)+(EnemyDMGDanger-1)+(EnemyJackDMG-1)),0)*IF($A36>20,(1+Max(0,((($A36-20)*(($A36-20)+1))/2)/100)*(2+Max(0,($A36-35)*0.2))),1),0)*IF(EnemyBuffed=TRUE,1.25,1),0) & " (" & MAX(ROUND(Rounddown(Round(Round((E$34+E$35*($A36-1))*(1+(EnemyDamageSlider-1)+(EnemyDMGDanger-1)+(EnemyJackDMG-1)),0)*IF($A36>20,(1+Max(0,((($A36-20)*(($A36-20)+1))/2)/100)*(2+Max(0,($A36-35)*0.2))),1),0)*IF(EnemyBuffed=TRUE,1.25,1),0)*EnemyDMGTaken,0),1) & ")" -> 1 (1) | F36: =Rounddown(Round(Round((F$34+F$35*($A36-1))*(1+(EnemyDamageSlider-1)+(EnemyDMGDanger-1)+(EnemyJackDMG-1)),0)*IF($A36>20,(1+Max(0,((($A36-20)*(($A36-20)+1))/2)/100)*(2+Max(0,($A36-35)*0.2))),1),0)*IF(EnemyBuffed=TRUE,1.25,1),0) & " (" & MAX(ROUND(Rounddown(Round(Round((F$34+F$35*($A36-1))*(1+(EnemyDamageSlider-1)+(EnemyDMGDanger-1)+(EnemyJackDMG-1)),0)*IF($A36>20,(1+Max(0,((($A36-20)*(($A36-20)+1))/2)/100)*(2+Max(0,($A36-35)*0.2))),1),0)*IF(EnemyBuffed=TRUE,1.25,1),0)*EnemyDMGTaken,0),1) & ")" -> 1 (1) | G36: =Rounddown(Round(Round((G$34+G$35*($A36-1))*(1+(EnemyDamageSlider-1)+(EnemyDMGDanger-1)+(EnemyJackDMG-1)),0)*IF($A36>20,(1+Max(0,((($A36-20)*(($A36-20)+1))/2)/100)*(2+Max(0,($A36-35)*0.2))),1),0)*IF(EnemyBuffed=TRUE,1.25,1),0) & " (" & MAX(ROUND(Rounddown(Round(Round((G$34+G$35*($A36-1))*(1+(EnemyDamageSlider-1)+(EnemyDMGDanger-1)+(EnemyJackDMG-1)),0)*IF($A36>20,(1+Max(0,((($A36-20)*(($A36-20)+1))/2)/100)*(2+Max(0,($A36-35)*0.2))),1),0)*IF(EnemyBuffed=TRUE,1.25,1),0)*EnemyDMGTaken,0),1) & ")" -> 1 (1) | H36: =Rounddown(Round(Round((H$34+H$35*($A36-1))*(1+(EnemyDamageSlider-1)+(EnemyDMGDanger-1)+(EnemyJackDMG-1)),0)*IF($A36>20,(1+Max(0,((($A36-20)*(($A36-20)+1))/2)/100)*(2+Max(0,($A36-35)*0.2))),1),0)*IF(EnemyBuffed=TRUE,1.25,1),0) & " (" & MAX(ROUND(Rounddown(Round(Round((H$34+H$35*($A36-1))*(1+(EnemyDamageSlider-1)+(EnemyDMGDanger-1)+(EnemyJackDMG-1)),0)*IF($A36>20,(1+Max(0,((($A36-20)*(($A36-20)+1))/2)/100)*(2+Max(0,($A36-35)*0.2))),1),0)*IF(EnemyBuffed=TRUE,1.25,1),0)*EnemyDMGTaken,0),1) & ")" -> 3 (3) | I36: =Rounddown(Round(Round((I$34+I$35*($A36-1))*(1+(EnemyDamageSlider-1)+(EnemyDMGDanger-1)+(EnemyJackDMG-1)),0)*IF($A36>20,(1+Max(0,((($A36-20)*(($A36-20)+1))/2)/100)*(2+Max(0,($A36-35)*0.2))),1),0)*IF(EnemyBuffed=TRUE,1.25,1),0) & " (" & MAX(ROUND(Rounddown(Round(Round((I$34+I$35*($A36-1))*(1+(EnemyDamageSlider-1)+(EnemyDMGDanger-1)+(EnemyJackDMG-1)),0)*IF($A36>20,(1+Max(0,((($A36-20)*(($A36-20)+1))/2)/100)*(2+Max(0,($A36-35)*0.2))),1),0)*IF(EnemyBuffed=TRUE,1.25,1),0)*EnemyDMGTaken,0),1) & ")" -> 1 (1) | J36: =Rounddown(Round(Round((J$34+J$35*($A36-1))*(1+(EnemyDamageSlider-1)+(EnemyDMGDanger-1)+(EnemyJackDMG-1)),0)*IF($A36>20,(1+Max(0,((($A36-20)*(($A36-20)+1))/2)/100)*(2+Max(0,($A36-35)*0.2))),1),0)*IF(EnemyBuffed=TRUE,1.25,1),0) & " (" & MAX(ROUND(Rounddown(Round(Round((J$34+J$35*($A36-1))*(1+(EnemyDamageSlider-1)+(EnemyDMGDanger-1)+(EnemyJackDMG-1)),0)*IF($A36>20,(1+Max(0,((($A36-20)*(($A36-20)+1))/2)/100)*(2+Max(0,($A36-35)*0.2))),1),0)*IF(EnemyBuffed=TRUE,1.25,1),0)*EnemyDMGTaken,0),1) & ")" -> 1 (1) | ... AA36: =Rounddown(Round(Round((AA$34+AA$35*($A36-1))*(1+(EnemyDamageSlider-1)+(EnemyDMGDanger-1)+(EnemyJackDMG-1)),0)*IF($A36>20,(1+Max(0,((($A36-20)*(($A36-20)+1))/2)/100)*(2+Max(0,($A36-35)*0.2))),1),0)*IF(EnemyBuffed=TRUE,1.25,1),0) & " (" & MAX(ROUND(Rounddown(Round(Round((AA$34+AA$35*($A36-1))*(1+(EnemyDamageSlider-1)+(EnemyDMGDanger-1)+(EnemyJackDMG-1)),0)*IF($A36>20,(1+Max(0,((($A36-20)*(($A36-20)+1))/2)/100)*(2+Max(0,($A36-35)*0.2))),1),0)*IF(EnemyBuffed=TRUE,1.25,1),0)*EnemyDMGTaken,0),1) & ")" -> 1 (1)
A37: 2 | B37: 0 | C37: =Rounddown(Round(Round((C$34+C$35*($A37-1))*(1+(EnemyDamageSlider-1)+(EnemyDMGDanger-1)+(EnemyJackDMG-1)),0)*IF($A37>20,(1+Max(0,((($A37-20)*(($A37-20)+1))/2)/100)*(2+Max(0,($A37-35)*0.2))),1),0)*IF(EnemyBuffed=TRUE,1.25,1),0) & " (" & MAX(ROUND(Rounddown(Round(Round((C$34+C$35*($A37-1))*(1+(EnemyDamageSlider-1)+(EnemyDMGDanger-1)+(EnemyJackDMG-1)),0)*IF($A37>20,(1+Max(0,((($A37-20)*(($A37-20)+1))/2)/100)*(2+Max(0,($A37-35)*0.2))),1),0)*IF(EnemyBuffed=TRUE,1.25,1),0)*EnemyDMGTaken,0),1) & ")" -> 2 (2) | D37: =Rounddown(Round(Round((D$34+D$35*($A37-1))*(1+(EnemyDamageSlider-1)+(EnemyDMGDanger-1)+(EnemyJackDMG-1)),0)*IF($A37>20,(1+Max(0,((($A37-20)*(($A37-20)+1))/2)/100)*(2+Max(0,($A37-35)*0.2))),1),0)*IF(EnemyBuffed=TRUE,1.25,1),0) & " (" & MAX(ROUND(Rounddown(Round(Round((D$34+D$35*($A37-1))*(1+(EnemyDamageSlider-1)+(EnemyDMGDanger-1)+(EnemyJackDMG-1)),0)*IF($A37>20,(1+Max(0,((($A37-20)*(($A37-20)+1))/2)/100)*(2+Max(0,($A37-35)*0.2))),1),0)*IF(EnemyBuffed=TRUE,1.25,1),0)*EnemyDMGTaken,0),1) & ")" -> 2 (2) | E37: =Rounddown(Round(Round((E$34+E$35*($A37-1))*(1+(EnemyDamageSlider-1)+(EnemyDMGDanger-1)+(EnemyJackDMG-1)),0)*IF($A37>20,(1+Max(0,((($A37-20)*(($A37-20)+1))/2)/100)*(2+Max(0,($A37-35)*0.2))),1),0)*IF(EnemyBuffed=TRUE,1.25,1),0) & " (" & MAX(ROUND(Rounddown(Round(Round((E$34+E$35*($A37-1))*(1+(EnemyDamageSlider-1)+(EnemyDMGDanger-1)+(EnemyJackDMG-1)),0)*IF($A37>20,(1+Max(0,((($A37-20)*(($A37-20)+1))/2)/100)*(2+Max(0,($A37-35)*0.2))),1),0)*IF(EnemyBuffed=TRUE,1.25,1),0)*EnemyDMGTaken,0),1) & ")" -> 2 (2) | F37: =Rounddown(Round(Round((F$34+F$35*($A37-1))*(1+(EnemyDamageSlider-1)+(EnemyDMGDanger-1)+(EnemyJackDMG-1)),0)*IF($A37>20,(1+Max(0,((($A37-20)*(($A37-20)+1))/2)/100)*(2+Max(0,($A37-35)*0.2))),1),0)*IF(EnemyBuffed=TRUE,1.25,1),0) & " (" & MAX(ROUND(Rounddown(Round(Round((F$34+F$35*($A37-1))*(1+(EnemyDamageSlider-1)+(EnemyDMGDanger-1)+(EnemyJackDMG-1)),0)*IF($A37>20,(1+Max(0,((($A37-20)*(($A37-20)+1))/2)/100)*(2+Max(0,($A37-35)*0.2))),1),0)*IF(EnemyBuffed=TRUE,1.25,1),0)*EnemyDMGTaken,0),1) & ")" -> 3 (3) | G37: =Rounddown(Round(Round((G$34+G$35*($A37-1))*(1+(EnemyDamageSlider-1)+(EnemyDMGDanger-1)+(EnemyJackDMG-1)),0)*IF($A37>20,(1+Max(0,((($A37-20)*(($A37-20)+1))/2)/100)*(2+Max(0,($A37-35)*0.2))),1),0)*IF(EnemyBuffed=TRUE,1.25,1),0) & " (" & MAX(ROUND(Rounddown(Round(Round((G$34+G$35*($A37-1))*(1+(EnemyDamageSlider-1)+(EnemyDMGDanger-1)+(EnemyJackDMG-1)),0)*IF($A37>20,(1+Max(0,((($A37-20)*(($A37-20)+1))/2)/100)*(2+Max(0,($A37-35)*0.2))),1),0)*IF(EnemyBuffed=TRUE,1.25,1),0)*EnemyDMGTaken,0),1) & ")" -> 3 (3) | H37: =Rounddown(Round(Round((H$34+H$35*($A37-1))*(1+(EnemyDamageSlider-1)+(EnemyDMGDanger-1)+(EnemyJackDMG-1)),0)*IF($A37>20,(1+Max(0,((($A37-20)*(($A37-20)+1))/2)/100)*(2+Max(0,($A37-35)*0.2))),1),0)*IF(EnemyBuffed=TRUE,1.25,1),0) & " (" & MAX(ROUND(Rounddown(Round(Round((H$34+H$35*($A37-1))*(1+(EnemyDamageSlider-1)+(EnemyDMGDanger-1)+(EnemyJackDMG-1)),0)*IF($A37>20,(1+Max(0,((($A37-20)*(($A37-20)+1))/2)/100)*(2+Max(0,($A37-35)*0.2))),1),0)*IF(EnemyBuffed=TRUE,1.25,1),0)*EnemyDMGTaken,0),1) & ")" -> 4 (4) | I37: =Rounddown(Round(Round((I$34+I$35*($A37-1))*(1+(EnemyDamageSlider-1)+(EnemyDMGDanger-1)+(EnemyJackDMG-1)),0)*IF($A37>20,(1+Max(0,((($A37-20)*(($A37-20)+1))/2)/100)*(2+Max(0,($A37-35)*0.2))),1),0)*IF(EnemyBuffed=TRUE,1.25,1),0) & " (" & MAX(ROUND(Rounddown(Round(Round((I$34+I$35*($A37-1))*(1+(EnemyDamageSlider-1)+(EnemyDMGDanger-1)+(EnemyJackDMG-1)),0)*IF($A37>20,(1+Max(0,((($A37-20)*(($A37-20)+1))/2)/100)*(2+Max(0,($A37-35)*0.2))),1),0)*IF(EnemyBuffed=TRUE,1.25,1),0)*EnemyDMGTaken,0),1) & ")" -> 2 (2) | J37: =Rounddown(Round(Round((J$34+J$35*($A37-1))*(1+(EnemyDamageSlider-1)+(EnemyDMGDanger-1)+(EnemyJackDMG-1)),0)*IF($A37>20,(1+Max(0,((($A37-20)*(($A37-20)+1))/2)/100)*(2+Max(0,($A37-35)*0.2))),1),0)*IF(EnemyBuffed=TRUE,1.25,1),0) & " (" & MAX(ROUND(Rounddown(Round(Round((J$34+J$35*($A37-1))*(1+(EnemyDamageSlider-1)+(EnemyDMGDanger-1)+(EnemyJackDMG-1)),0)*IF($A37>20,(1+Max(0,((($A37-20)*(($A37-20)+1))/2)/100)*(2+Max(0,($A37-35)*0.2))),1),0)*IF(EnemyBuffed=TRUE,1.25,1),0)*EnemyDMGTaken,0),1) & ")" -> 3 (3) | ... AA37: =Rounddown(Round(Round((AA$34+AA$35*($A37-1))*(1+(EnemyDamageSlider-1)+(EnemyDMGDanger-1)+(EnemyJackDMG-1)),0)*IF($A37>20,(1+Max(0,((($A37-20)*(($A37-20)+1))/2)/100)*(2+Max(0,($A37-35)*0.2))),1),0)*IF(EnemyBuffed=TRUE,1.25,1),0) & " (" & MAX(ROUND(Rounddown(Round(Round((AA$34+AA$35*($A37-1))*(1+(EnemyDamageSlider-1)+(EnemyDMGDanger-1)+(EnemyJackDMG-1)),0)*IF($A37>20,(1+Max(0,((($A37-20)*(($A37-20)+1))/2)/100)*(2+Max(0,($A37-35)*0.2))),1),0)*IF(EnemyBuffed=TRUE,1.25,1),0)*EnemyDMGTaken,0),1) & ")" -> 2 (2)
A38: 3 | B38: 0 | C38: =Rounddown(Round(Round((C$34+C$35*($A38-1))*(1+(EnemyDamageSlider-1)+(EnemyDMGDanger-1)+(EnemyJackDMG-1)),0)*IF($A38>20,(1+Max(0,((($A38-20)*(($A38-20)+1))/2)/100)*(2+Max(0,($A38-35)*0.2))),1),0)*IF(EnemyBuffed=TRUE,1.25,1),0) & " (" & MAX(ROUND(Rounddown(Round(Round((C$34+C$35*($A38-1))*(1+(EnemyDamageSlider-1)+(EnemyDMGDanger-1)+(EnemyJackDMG-1)),0)*IF($A38>20,(1+Max(0,((($A38-20)*(($A38-20)+1))/2)/100)*(2+Max(0,($A38-35)*0.2))),1),0)*IF(EnemyBuffed=TRUE,1.25,1),0)*EnemyDMGTaken,0),1) & ")" -> 3 (3) | D38: =Rounddown(Round(Round((D$34+D$35*($A38-1))*(1+(EnemyDamageSlider-1)+(EnemyDMGDanger-1)+(EnemyJackDMG-1)),0)*IF($A38>20,(1+Max(0,((($A38-20)*(($A38-20)+1))/2)/100)*(2+Max(0,($A38-35)*0.2))),1),0)*IF(EnemyBuffed=TRUE,1.25,1),0) & " (" & MAX(ROUND(Rounddown(Round(Round((D$34+D$35*($A38-1))*(1+(EnemyDamageSlider-1)+(EnemyDMGDanger-1)+(EnemyJackDMG-1)),0)*IF($A38>20,(1+Max(0,((($A38-20)*(($A38-20)+1))/2)/100)*(2+Max(0,($A38-35)*0.2))),1),0)*IF(EnemyBuffed=TRUE,1.25,1),0)*EnemyDMGTaken,0),1) & ")" -> 3 (3) | E38: =Rounddown(Round(Round((E$34+E$35*($A38-1))*(1+(EnemyDamageSlider-1)+(EnemyDMGDanger-1)+(EnemyJackDMG-1)),0)*IF($A38>20,(1+Max(0,((($A38-20)*(($A38-20)+1))/2)/100)*(2+Max(0,($A38-35)*0.2))),1),0)*IF(EnemyBuffed=TRUE,1.25,1),0) & " (" & MAX(ROUND(Rounddown(Round(Round((E$34+E$35*($A38-1))*(1+(EnemyDamageSlider-1)+(EnemyDMGDanger-1)+(EnemyJackDMG-1)),0)*IF($A38>20,(1+Max(0,((($A38-20)*(($A38-20)+1))/2)/100)*(2+Max(0,($A38-35)*0.2))),1),0)*IF(EnemyBuffed=TRUE,1.25,1),0)*EnemyDMGTaken,0),1) & ")" -> 3 (3) | F38: =Rounddown(Round(Round((F$34+F$35*($A38-1))*(1+(EnemyDamageSlider-1)+(EnemyDMGDanger-1)+(EnemyJackDMG-1)),0)*IF($A38>20,(1+Max(0,((($A38-20)*(($A38-20)+1))/2)/100)*(2+Max(0,($A38-35)*0.2))),1),0)*IF(EnemyBuffed=TRUE,1.25,1),0) & " (" & MAX(ROUND(Rounddown(Round(Round((F$34+F$35*($A38-1))*(1+(EnemyDamageSlider-1)+(EnemyDMGDanger-1)+(EnemyJackDMG-1)),0)*IF($A38>20,(1+Max(0,((($A38-20)*(($A38-20)+1))/2)/100)*(2+Max(0,($A38-35)*0.2))),1),0)*IF(EnemyBuffed=TRUE,1.25,1),0)*EnemyDMGTaken,0),1) & ")" -> 4 (4) | G38: =Rounddown(Round(Round((G$34+G$35*($A38-1))*(1+(EnemyDamageSlider-1)+(EnemyDMGDanger-1)+(EnemyJackDMG-1)),0)*IF($A38>20,(1+Max(0,((($A38-20)*(($A38-20)+1))/2)/100)*(2+Max(0,($A38-35)*0.2))),1),0)*IF(EnemyBuffed=TRUE,1.25,1),0) & " (" & MAX(ROUND(Rounddown(Round(Round((G$34+G$35*($A38-1))*(1+(EnemyDamageSlider-1)+(EnemyDMGDanger-1)+(EnemyJackDMG-1)),0)*IF($A38>20,(1+Max(0,((($A38-20)*(($A38-20)+1))/2)/100)*(2+Max(0,($A38-35)*0.2))),1),0)*IF(EnemyBuffed=TRUE,1.25,1),0)*EnemyDMGTaken,0),1) & ")" -> 5 (5) | H38: =Rounddown(Round(Round((H$34+H$35*($A38-1))*(1+(EnemyDamageSlider-1)+(EnemyDMGDanger-1)+(EnemyJackDMG-1)),0)*IF($A38>20,(1+Max(0,((($A38-20)*(($A38-20)+1))/2)/100)*(2+Max(0,($A38-35)*0.2))),1),0)*IF(EnemyBuffed=TRUE,1.25,1),0) & " (" & MAX(ROUND(Rounddown(Round(Round((H$34+H$35*($A38-1))*(1+(EnemyDamageSlider-1)+(EnemyDMGDanger-1)+(EnemyJackDMG-1)),0)*IF($A38>20,(1+Max(0,((($A38-20)*(($A38-20)+1))/2)/100)*(2+Max(0,($A38-35)*0.2))),1),0)*IF(EnemyBuffed=TRUE,1.25,1),0)*EnemyDMGTaken,0),1) & ")" -> 5 (5) | I38: =Rounddown(Round(Round((I$34+I$35*($A38-1))*(1+(EnemyDamageSlider-1)+(EnemyDMGDanger-1)+(EnemyJackDMG-1)),0)*IF($A38>20,(1+Max(0,((($A38-20)*(($A38-20)+1))/2)/100)*(2+Max(0,($A38-35)*0.2))),1),0)*IF(EnemyBuffed=TRUE,1.25,1),0) & " (" & MAX(ROUND(Rounddown(Round(Round((I$34+I$35*($A38-1))*(1+(EnemyDamageSlider-1)+(EnemyDMGDanger-1)+(EnemyJackDMG-1)),0)*IF($A38>20,(1+Max(0,((($A38-20)*(($A38-20)+1))/2)/100)*(2+Max(0,($A38-35)*0.2))),1),0)*IF(EnemyBuffed=TRUE,1.25,1),0)*EnemyDMGTaken,0),1) & ")" -> 3 (3) | J38: =Rounddown(Round(Round((J$34+J$35*($A38-1))*(1+(EnemyDamageSlider-1)+(EnemyDMGDanger-1)+(EnemyJackDMG-1)),0)*IF($A38>20,(1+Max(0,((($A38-20)*(($A38-20)+1))/2)/100)*(2+Max(0,($A38-35)*0.2))),1),0)*IF(EnemyBuffed=TRUE,1.25,1),0) & " (" & MAX(ROUND(Rounddown(Round(Round((J$34+J$35*($A38-1))*(1+(EnemyDamageSlider-1)+(EnemyDMGDanger-1)+(EnemyJackDMG-1)),0)*IF($A38>20,(1+Max(0,((($A38-20)*(($A38-20)+1))/2)/100)*(2+Max(0,($A38-35)*0.2))),1),0)*IF(EnemyBuffed=TRUE,1.25,1),0)*EnemyDMGTaken,0),1) & ")" -> 4 (4) | ... AA38: =Rounddown(Round(Round((AA$34+AA$35*($A38-1))*(1+(EnemyDamageSlider-1)+(EnemyDMGDanger-1)+(EnemyJackDMG-1)),0)*IF($A38>20,(1+Max(0,((($A38-20)*(($A38-20)+1))/2)/100)*(2+Max(0,($A38-35)*0.2))),1),0)*IF(EnemyBuffed=TRUE,1.25,1),0) & " (" & MAX(ROUND(Rounddown(Round(Round((AA$34+AA$35*($A38-1))*(1+(EnemyDamageSlider-1)+(EnemyDMGDanger-1)+(EnemyJackDMG-1)),0)*IF($A38>20,(1+Max(0,((($A38-20)*(($A38-20)+1))/2)/100)*(2+Max(0,($A38-35)*0.2))),1),0)*IF(EnemyBuffed=TRUE,1.25,1),0)*EnemyDMGTaken,0),1) & ")" -> 4 (4)
A39: 4 | B39: 0 | C39: =Rounddown(Round(Round((C$34+C$35*($A39-1))*(1+(EnemyDamageSlider-1)+(EnemyDMGDanger-1)+(EnemyJackDMG-1)),0)*IF($A39>20,(1+Max(0,((($A39-20)*(($A39-20)+1))/2)/100)*(2+Max(0,($A39-35)*0.2))),1),0)*IF(EnemyBuffed=TRUE,1.25,1),0) & " (" & MAX(ROUND(Rounddown(Round(Round((C$34+C$35*($A39-1))*(1+(EnemyDamageSlider-1)+(EnemyDMGDanger-1)+(EnemyJackDMG-1)),0)*IF($A39>20,(1+Max(0,((($A39-20)*(($A39-20)+1))/2)/100)*(2+Max(0,($A39-35)*0.2))),1),0)*IF(EnemyBuffed=TRUE,1.25,1),0)*EnemyDMGTaken,0),1) & ")" -> 4 (4) | D39: =Rounddown(Round(Round((D$34+D$35*($A39-1))*(1+(EnemyDamageSlider-1)+(EnemyDMGDanger-1)+(EnemyJackDMG-1)),0)*IF($A39>20,(1+Max(0,((($A39-20)*(($A39-20)+1))/2)/100)*(2+Max(0,($A39-35)*0.2))),1),0)*IF(EnemyBuffed=TRUE,1.25,1),0) & " (" & MAX(ROUND(Rounddown(Round(Round((D$34+D$35*($A39-1))*(1+(EnemyDamageSlider-1)+(EnemyDMGDanger-1)+(EnemyJackDMG-1)),0)*IF($A39>20,(1+Max(0,((($A39-20)*(($A39-20)+1))/2)/100)*(2+Max(0,($A39-35)*0.2))),1),0)*IF(EnemyBuffed=TRUE,1.25,1),0)*EnemyDMGTaken,0),1) & ")" -> 4 (4) | E39: =Rounddown(Round(Round((E$34+E$35*($A39-1))*(1+(EnemyDamageSlider-1)+(EnemyDMGDanger-1)+(EnemyJackDMG-1)),0)*IF($A39>20,(1+Max(0,((($A39-20)*(($A39-20)+1))/2)/100)*(2+Max(0,($A39-35)*0.2))),1),0)*IF(EnemyBuffed=TRUE,1.25,1),0) & " (" & MAX(ROUND(Rounddown(Round(Round((E$34+E$35*($A39-1))*(1+(EnemyDamageSlider-1)+(EnemyDMGDanger-1)+(EnemyJackDMG-1)),0)*IF($A39>20,(1+Max(0,((($A39-20)*(($A39-20)+1))/2)/100)*(2+Max(0,($A39-35)*0.2))),1),0)*IF(EnemyBuffed=TRUE,1.25,1),0)*EnemyDMGTaken,0),1) & ")" -> 4 (4) | F39: =Rounddown(Round(Round((F$34+F$35*($A39-1))*(1+(EnemyDamageSlider-1)+(EnemyDMGDanger-1)+(EnemyJackDMG-1)),0)*IF($A39>20,(1+Max(0,((($A39-20)*(($A39-20)+1))/2)/100)*(2+Max(0,($A39-35)*0.2))),1),0)*IF(EnemyBuffed=TRUE,1.25,1),0) & " (" & MAX(ROUND(Rounddown(Round(Round((F$34+F$35*($A39-1))*(1+(EnemyDamageSlider-1)+(EnemyDMGDanger-1)+(EnemyJackDMG-1)),0)*IF($A39>20,(1+Max(0,((($A39-20)*(($A39-20)+1))/2)/100)*(2+Max(0,($A39-35)*0.2))),1),0)*IF(EnemyBuffed=TRUE,1.25,1),0)*EnemyDMGTaken,0),1) & ")" -> 5 (5) | G39: =Rounddown(Round(Round((G$34+G$35*($A39-1))*(1+(EnemyDamageSlider-1)+(EnemyDMGDanger-1)+(EnemyJackDMG-1)),0)*IF($A39>20,(1+Max(0,((($A39-20)*(($A39-20)+1))/2)/100)*(2+Max(0,($A39-35)*0.2))),1),0)*IF(EnemyBuffed=TRUE,1.25,1),0) & " (" & MAX(ROUND(Rounddown(Round(Round((G$34+G$35*($A39-1))*(1+(EnemyDamageSlider-1)+(EnemyDMGDanger-1)+(EnemyJackDMG-1)),0)*IF($A39>20,(1+Max(0,((($A39-20)*(($A39-20)+1))/2)/100)*(2+Max(0,($A39-35)*0.2))),1),0)*IF(EnemyBuffed=TRUE,1.25,1),0)*EnemyDMGTaken,0),1) & ")" -> 6 (6) | H39: =Rounddown(Round(Round((H$34+H$35*($A39-1))*(1+(EnemyDamageSlider-1)+(EnemyDMGDanger-1)+(EnemyJackDMG-1)),0)*IF($A39>20,(1+Max(0,((($A39-20)*(($A39-20)+1))/2)/100)*(2+Max(0,($A39-35)*0.2))),1),0)*IF(EnemyBuffed=TRUE,1.25,1),0) & " (" & MAX(ROUND(Rounddown(Round(Round((H$34+H$35*($A39-1))*(1+(EnemyDamageSlider-1)+(EnemyDMGDanger-1)+(EnemyJackDMG-1)),0)*IF($A39>20,(1+Max(0,((($A39-20)*(($A39-20)+1))/2)/100)*(2+Max(0,($A39-35)*0.2))),1),0)*IF(EnemyBuffed=TRUE,1.25,1),0)*EnemyDMGTaken,0),1) & ")" -> 6 (6) | I39: =Rounddown(Round(Round((I$34+I$35*($A39-1))*(1+(EnemyDamageSlider-1)+(EnemyDMGDanger-1)+(EnemyJackDMG-1)),0)*IF($A39>20,(1+Max(0,((($A39-20)*(($A39-20)+1))/2)/100)*(2+Max(0,($A39-35)*0.2))),1),0)*IF(EnemyBuffed=TRUE,1.25,1),0) & " (" & MAX(ROUND(Rounddown(Round(Round((I$34+I$35*($A39-1))*(1+(EnemyDamageSlider-1)+(EnemyDMGDanger-1)+(EnemyJackDMG-1)),0)*IF($A39>20,(1+Max(0,((($A39-20)*(($A39-20)+1))/2)/100)*(2+Max(0,($A39-35)*0.2))),1),0)*IF(EnemyBuffed=TRUE,1.25,1),0)*EnemyDMGTaken,0),1) & ")" -> 4 (4) | J39: =Rounddown(Round(Round((J$34+J$35*($A39-1))*(1+(EnemyDamageSlider-1)+(EnemyDMGDanger-1)+(EnemyJackDMG-1)),0)*IF($A39>20,(1+Max(0,((($A39-20)*(($A39-20)+1))/2)/100)*(2+Max(0,($A39-35)*0.2))),1),0)*IF(EnemyBuffed=TRUE,1.25,1),0) & " (" & MAX(ROUND(Rounddown(Round(Round((J$34+J$35*($A39-1))*(1+(EnemyDamageSlider-1)+(EnemyDMGDanger-1)+(EnemyJackDMG-1)),0)*IF($A39>20,(1+Max(0,((($A39-20)*(($A39-20)+1))/2)/100)*(2+Max(0,($A39-35)*0.2))),1),0)*IF(EnemyBuffed=TRUE,1.25,1),0)*EnemyDMGTaken,0),1) & ")" -> 5 (5) | ... AA39: =Rounddown(Round(Round((AA$34+AA$35*($A39-1))*(1+(EnemyDamageSlider-1)+(EnemyDMGDanger-1)+(EnemyJackDMG-1)),0)*IF($A39>20,(1+Max(0,((($A39-20)*(($A39-20)+1))/2)/100)*(2+Max(0,($A39-35)*0.2))),1),0)*IF(EnemyBuffed=TRUE,1.25,1),0) & " (" & MAX(ROUND(Rounddown(Round(Round((AA$34+AA$35*($A39-1))*(1+(EnemyDamageSlider-1)+(EnemyDMGDanger-1)+(EnemyJackDMG-1)),0)*IF($A39>20,(1+Max(0,((($A39-20)*(($A39-20)+1))/2)/100)*(2+Max(0,($A39-35)*0.2))),1),0)*IF(EnemyBuffed=TRUE,1.25,1),0)*EnemyDMGTaken,0),1) & ")" -> 5 (5)
A40: 5 | B40: 0 | C40: =Rounddown(Round(Round((C$34+C$35*($A40-1))*(1+(EnemyDamageSlider-1)+(EnemyDMGDanger-1)+(EnemyJackDMG-1)),0)*IF($A40>20,(1+Max(0,((($A40-20)*(($A40-20)+1))/2)/100)*(2+Max(0,($A40-35)*0.2))),1),0)*IF(EnemyBuffed=TRUE,1.25,1),0) & " (" & MAX(ROUND(Rounddown(Round(Round((C$34+C$35*($A40-1))*(1+(EnemyDamageSlider-1)+(EnemyDMGDanger-1)+(EnemyJackDMG-1)),0)*IF($A40>20,(1+Max(0,((($A40-20)*(($A40-20)+1))/2)/100)*(2+Max(0,($A40-35)*0.2))),1),0)*IF(EnemyBuffed=TRUE,1.25,1),0)*EnemyDMGTaken,0),1) & ")" -> 5 (5) | D40: =Rounddown(Round(Round((D$34+D$35*($A40-1))*(1+(EnemyDamageSlider-1)+(EnemyDMGDanger-1)+(EnemyJackDMG-1)),0)*IF($A40>20,(1+Max(0,((($A40-20)*(($A40-20)+1))/2)/100)*(2+Max(0,($A40-35)*0.2))),1),0)*IF(EnemyBuffed=TRUE,1.25,1),0) & " (" & MAX(ROUND(Rounddown(Round(Round((D$34+D$35*($A40-1))*(1+(EnemyDamageSlider-1)+(EnemyDMGDanger-1)+(EnemyJackDMG-1)),0)*IF($A40>20,(1+Max(0,((($A40-20)*(($A40-20)+1))/2)/100)*(2+Max(0,($A40-35)*0.2))),1),0)*IF(EnemyBuffed=TRUE,1.25,1),0)*EnemyDMGTaken,0),1) & ")" -> 5 (5) | E40: =Rounddown(Round(Round((E$34+E$35*($A40-1))*(1+(EnemyDamageSlider-1)+(EnemyDMGDanger-1)+(EnemyJackDMG-1)),0)*IF($A40>20,(1+Max(0,((($A40-20)*(($A40-20)+1))/2)/100)*(2+Max(0,($A40-35)*0.2))),1),0)*IF(EnemyBuffed=TRUE,1.25,1),0) & " (" & MAX(ROUND(Rounddown(Round(Round((E$34+E$35*($A40-1))*(1+(EnemyDamageSlider-1)+(EnemyDMGDanger-1)+(EnemyJackDMG-1)),0)*IF($A40>20,(1+Max(0,((($A40-20)*(($A40-20)+1))/2)/100)*(2+Max(0,($A40-35)*0.2))),1),0)*IF(EnemyBuffed=TRUE,1.25,1),0)*EnemyDMGTaken,0),1) & ")" -> 5 (5) | F40: =Rounddown(Round(Round((F$34+F$35*($A40-1))*(1+(EnemyDamageSlider-1)+(EnemyDMGDanger-1)+(EnemyJackDMG-1)),0)*IF($A40>20,(1+Max(0,((($A40-20)*(($A40-20)+1))/2)/100)*(2+Max(0,($A40-35)*0.2))),1),0)*IF(EnemyBuffed=TRUE,1.25,1),0) & " (" & MAX(ROUND(Rounddown(Round(Round((F$34+F$35*($A40-1))*(1+(EnemyDamageSlider-1)+(EnemyDMGDanger-1)+(EnemyJackDMG-1)),0)*IF($A40>20,(1+Max(0,((($A40-20)*(($A40-20)+1))/2)/100)*(2+Max(0,($A40-35)*0.2))),1),0)*IF(EnemyBuffed=TRUE,1.25,1),0)*EnemyDMGTaken,0),1) & ")" -> 6 (6) | G40: =Rounddown(Round(Round((G$34+G$35*($A40-1))*(1+(EnemyDamageSlider-1)+(EnemyDMGDanger-1)+(EnemyJackDMG-1)),0)*IF($A40>20,(1+Max(0,((($A40-20)*(($A40-20)+1))/2)/100)*(2+Max(0,($A40-35)*0.2))),1),0)*IF(EnemyBuffed=TRUE,1.25,1),0) & " (" & MAX(ROUND(Rounddown(Round(Round((G$34+G$35*($A40-1))*(1+(EnemyDamageSlider-1)+(EnemyDMGDanger-1)+(EnemyJackDMG-1)),0)*IF($A40>20,(1+Max(0,((($A40-20)*(($A40-20)+1))/2)/100)*(2+Max(0,($A40-35)*0.2))),1),0)*IF(EnemyBuffed=TRUE,1.25,1),0)*EnemyDMGTaken,0),1) & ")" -> 8 (8) | H40: =Rounddown(Round(Round((H$34+H$35*($A40-1))*(1+(EnemyDamageSlider-1)+(EnemyDMGDanger-1)+(EnemyJackDMG-1)),0)*IF($A40>20,(1+Max(0,((($A40-20)*(($A40-20)+1))/2)/100)*(2+Max(0,($A40-35)*0.2))),1),0)*IF(EnemyBuffed=TRUE,1.25,1),0) & " (" & MAX(ROUND(Rounddown(Round(Round((H$34+H$35*($A40-1))*(1+(EnemyDamageSlider-1)+(EnemyDMGDanger-1)+(EnemyJackDMG-1)),0)*IF($A40>20,(1+Max(0,((($A40-20)*(($A40-20)+1))/2)/100)*(2+Max(0,($A40-35)*0.2))),1),0)*IF(EnemyBuffed=TRUE,1.25,1),0)*EnemyDMGTaken,0),1) & ")" -> 8 (8) | I40: =Rounddown(Round(Round((I$34+I$35*($A40-1))*(1+(EnemyDamageSlider-1)+(EnemyDMGDanger-1)+(EnemyJackDMG-1)),0)*IF($A40>20,(1+Max(0,((($A40-20)*(($A40-20)+1))/2)/100)*(2+Max(0,($A40-35)*0.2))),1),0)*IF(EnemyBuffed=TRUE,1.25,1),0) & " (" & MAX(ROUND(Rounddown(Round(Round((I$34+I$35*($A40-1))*(1+(EnemyDamageSlider-1)+(EnemyDMGDanger-1)+(EnemyJackDMG-1)),0)*IF($A40>20,(1+Max(0,((($A40-20)*(($A40-20)+1))/2)/100)*(2+Max(0,($A40-35)*0.2))),1),0)*IF(EnemyBuffed=TRUE,1.25,1),0)*EnemyDMGTaken,0),1) & ")" -> 5 (5) | J40: =Rounddown(Round(Round((J$34+J$35*($A40-1))*(1+(EnemyDamageSlider-1)+(EnemyDMGDanger-1)+(EnemyJackDMG-1)),0)*IF($A40>20,(1+Max(0,((($A40-20)*(($A40-20)+1))/2)/100)*(2+Max(0,($A40-35)*0.2))),1),0)*IF(EnemyBuffed=TRUE,1.25,1),0) & " (" & MAX(ROUND(Rounddown(Round(Round((J$34+J$35*($A40-1))*(1+(EnemyDamageSlider-1)+(EnemyDMGDanger-1)+(EnemyJackDMG-1)),0)*IF($A40>20,(1+Max(0,((($A40-20)*(($A40-20)+1))/2)/100)*(2+Max(0,($A40-35)*0.2))),1),0)*IF(EnemyBuffed=TRUE,1.25,1),0)*EnemyDMGTaken,0),1) & ")" -> 6 (6) | ... AA40: =Rounddown(Round(Round((AA$34+AA$35*($A40-1))*(1+(EnemyDamageSlider-1)+(EnemyDMGDanger-1)+(EnemyJackDMG-1)),0)*IF($A40>20,(1+Max(0,((($A40-20)*(($A40-20)+1))/2)/100)*(2+Max(0,($A40-35)*0.2))),1),0)*IF(EnemyBuffed=TRUE,1.25,1),0) & " (" & MAX(ROUND(Rounddown(Round(Round((AA$34+AA$35*($A40-1))*(1+(EnemyDamageSlider-1)+(EnemyDMGDanger-1)+(EnemyJackDMG-1)),0)*IF($A40>20,(1+Max(0,((($A40-20)*(($A40-20)+1))/2)/100)*(2+Max(0,($A40-35)*0.2))),1),0)*IF(EnemyBuffed=TRUE,1.25,1),0)*EnemyDMGTaken,0),1) & ")" -> 6 (6)
A41: 6 | B41: 0 | C41: =Rounddown(Round(Round((C$34+C$35*($A41-1))*(1+(EnemyDamageSlider-1)+(EnemyDMGDanger-1)+(EnemyJackDMG-1)),0)*IF($A41>20,(1+Max(0,((($A41-20)*(($A41-20)+1))/2)/100)*(2+Max(0,($A41-35)*0.2))),1),0)*IF(EnemyBuffed=TRUE,1.25,1),0) & " (" & MAX(ROUND(Rounddown(Round(Round((C$34+C$35*($A41-1))*(1+(EnemyDamageSlider-1)+(EnemyDMGDanger-1)+(EnemyJackDMG-1)),0)*IF($A41>20,(1+Max(0,((($A41-20)*(($A41-20)+1))/2)/100)*(2+Max(0,($A41-35)*0.2))),1),0)*IF(EnemyBuffed=TRUE,1.25,1),0)*EnemyDMGTaken,0),1) & ")" -> 6 (6) | D41: =Rounddown(Round(Round((D$34+D$35*($A41-1))*(1+(EnemyDamageSlider-1)+(EnemyDMGDanger-1)+(EnemyJackDMG-1)),0)*IF($A41>20,(1+Max(0,((($A41-20)*(($A41-20)+1))/2)/100)*(2+Max(0,($A41-35)*0.2))),1),0)*IF(EnemyBuffed=TRUE,1.25,1),0) & " (" & MAX(ROUND(Rounddown(Round(Round((D$34+D$35*($A41-1))*(1+(EnemyDamageSlider-1)+(EnemyDMGDanger-1)+(EnemyJackDMG-1)),0)*IF($A41>20,(1+Max(0,((($A41-20)*(($A41-20)+1))/2)/100)*(2+Max(0,($A41-35)*0.2))),1),0)*IF(EnemyBuffed=TRUE,1.25,1),0)*EnemyDMGTaken,0),1) & ")" -> 6 (6) | E41: =Rounddown(Round(Round((E$34+E$35*($A41-1))*(1+(EnemyDamageSlider-1)+(EnemyDMGDanger-1)+(EnemyJackDMG-1)),0)*IF($A41>20,(1+Max(0,((($A41-20)*(($A41-20)+1))/2)/100)*(2+Max(0,($A41-35)*0.2))),1),0)*IF(EnemyBuffed=TRUE,1.25,1),0) & " (" & MAX(ROUND(Rounddown(Round(Round((E$34+E$35*($A41-1))*(1+(EnemyDamageSlider-1)+(EnemyDMGDanger-1)+(EnemyJackDMG-1)),0)*IF($A41>20,(1+Max(0,((($A41-20)*(($A41-20)+1))/2)/100)*(2+Max(0,($A41-35)*0.2))),1),0)*IF(EnemyBuffed=TRUE,1.25,1),0)*EnemyDMGTaken,0),1) & ")" -> 6 (6) | F41: =Rounddown(Round(Round((F$34+F$35*($A41-1))*(1+(EnemyDamageSlider-1)+(EnemyDMGDanger-1)+(EnemyJackDMG-1)),0)*IF($A41>20,(1+Max(0,((($A41-20)*(($A41-20)+1))/2)/100)*(2+Max(0,($A41-35)*0.2))),1),0)*IF(EnemyBuffed=TRUE,1.25,1),0) & " (" & MAX(ROUND(Rounddown(Round(Round((F$34+F$35*($A41-1))*(1+(EnemyDamageSlider-1)+(EnemyDMGDanger-1)+(EnemyJackDMG-1)),0)*IF($A41>20,(1+Max(0,((($A41-20)*(($A41-20)+1))/2)/100)*(2+Max(0,($A41-35)*0.2))),1),0)*IF(EnemyBuffed=TRUE,1.25,1),0)*EnemyDMGTaken,0),1) & ")" -> 7 (7) | G41: =Rounddown(Round(Round((G$34+G$35*($A41-1))*(1+(EnemyDamageSlider-1)+(EnemyDMGDanger-1)+(EnemyJackDMG-1)),0)*IF($A41>20,(1+Max(0,((($A41-20)*(($A41-20)+1))/2)/100)*(2+Max(0,($A41-35)*0.2))),1),0)*IF(EnemyBuffed=TRUE,1.25,1),0) & " (" & MAX(ROUND(Rounddown(Round(Round((G$34+G$35*($A41-1))*(1+(EnemyDamageSlider-1)+(EnemyDMGDanger-1)+(EnemyJackDMG-1)),0)*IF($A41>20,(1+Max(0,((($A41-20)*(($A41-20)+1))/2)/100)*(2+Max(0,($A41-35)*0.2))),1),0)*IF(EnemyBuffed=TRUE,1.25,1),0)*EnemyDMGTaken,0),1) & ")" -> 10 (10) | H41: =Rounddown(Round(Round((H$34+H$35*($A41-1))*(1+(EnemyDamageSlider-1)+(EnemyDMGDanger-1)+(EnemyJackDMG-1)),0)*IF($A41>20,(1+Max(0,((($A41-20)*(($A41-20)+1))/2)/100)*(2+Max(0,($A41-35)*0.2))),1),0)*IF(EnemyBuffed=TRUE,1.25,1),0) & " (" & MAX(ROUND(Rounddown(Round(Round((H$34+H$35*($A41-1))*(1+(EnemyDamageSlider-1)+(EnemyDMGDanger-1)+(EnemyJackDMG-1)),0)*IF($A41>20,(1+Max(0,((($A41-20)*(($A41-20)+1))/2)/100)*(2+Max(0,($A41-35)*0.2))),1),0)*IF(EnemyBuffed=TRUE,1.25,1),0)*EnemyDMGTaken,0),1) & ")" -> 9 (9) | I41: =Rounddown(Round(Round((I$34+I$35*($A41-1))*(1+(EnemyDamageSlider-1)+(EnemyDMGDanger-1)+(EnemyJackDMG-1)),0)*IF($A41>20,(1+Max(0,((($A41-20)*(($A41-20)+1))/2)/100)*(2+Max(0,($A41-35)*0.2))),1),0)*IF(EnemyBuffed=TRUE,1.25,1),0) & " (" & MAX(ROUND(Rounddown(Round(Round((I$34+I$35*($A41-1))*(1+(EnemyDamageSlider-1)+(EnemyDMGDanger-1)+(EnemyJackDMG-1)),0)*IF($A41>20,(1+Max(0,((($A41-20)*(($A41-20)+1))/2)/100)*(2+Max(0,($A41-35)*0.2))),1),0)*IF(EnemyBuffed=TRUE,1.25,1),0)*EnemyDMGTaken,0),1) & ")" -> 6 (6) | J41: =Rounddown(Round(Round((J$34+J$35*($A41-1))*(1+(EnemyDamageSlider-1)+(EnemyDMGDanger-1)+(EnemyJackDMG-1)),0)*IF($A41>20,(1+Max(0,((($A41-20)*(($A41-20)+1))/2)/100)*(2+Max(0,($A41-35)*0.2))),1),0)*IF(EnemyBuffed=TRUE,1.25,1),0) & " (" & MAX(ROUND(Rounddown(Round(Round((J$34+J$35*($A41-1))*(1+(EnemyDamageSlider-1)+(EnemyDMGDanger-1)+(EnemyJackDMG-1)),0)*IF($A41>20,(1+Max(0,((($A41-20)*(($A41-20)+1))/2)/100)*(2+Max(0,($A41-35)*0.2))),1),0)*IF(EnemyBuffed=TRUE,1.25,1),0)*EnemyDMGTaken,0),1) & ")" -> 7 (7) | ... AA41: =Rounddown(Round(Round((AA$34+AA$35*($A41-1))*(1+(EnemyDamageSlider-1)+(EnemyDMGDanger-1)+(EnemyJackDMG-1)),0)*IF($A41>20,(1+Max(0,((($A41-20)*(($A41-20)+1))/2)/100)*(2+Max(0,($A41-35)*0.2))),1),0)*IF(EnemyBuffed=TRUE,1.25,1),0) & " (" & MAX(ROUND(Rounddown(Round(Round((AA$34+AA$35*($A41-1))*(1+(EnemyDamageSlider-1)+(EnemyDMGDanger-1)+(EnemyJackDMG-1)),0)*IF($A41>20,(1+Max(0,((($A41-20)*(($A41-20)+1))/2)/100)*(2+Max(0,($A41-35)*0.2))),1),0)*IF(EnemyBuffed=TRUE,1.25,1),0)*EnemyDMGTaken,0),1) & ")" -> 7 (7)
A42: 7 | B42: 0 | C42: =Rounddown(Round(Round((C$34+C$35*($A42-1))*(1+(EnemyDamageSlider-1)+(EnemyDMGDanger-1)+(EnemyJackDMG-1)),0)*IF($A42>20,(1+Max(0,((($A42-20)*(($A42-20)+1))/2)/100)*(2+Max(0,($A42-35)*0.2))),1),0)*IF(EnemyBuffed=TRUE,1.25,1),0) & " (" & MAX(ROUND(Rounddown(Round(Round((C$34+C$35*($A42-1))*(1+(EnemyDamageSlider-1)+(EnemyDMGDanger-1)+(EnemyJackDMG-1)),0)*IF($A42>20,(1+Max(0,((($A42-20)*(($A42-20)+1))/2)/100)*(2+Max(0,($A42-35)*0.2))),1),0)*IF(EnemyBuffed=TRUE,1.25,1),0)*EnemyDMGTaken,0),1) & ")" -> 6 (6) | D42: =Rounddown(Round(Round((D$34+D$35*($A42-1))*(1+(EnemyDamageSlider-1)+(EnemyDMGDanger-1)+(EnemyJackDMG-1)),0)*IF($A42>20,(1+Max(0,((($A42-20)*(($A42-20)+1))/2)/100)*(2+Max(0,($A42-35)*0.2))),1),0)*IF(EnemyBuffed=TRUE,1.25,1),0) & " (" & MAX(ROUND(Rounddown(Round(Round((D$34+D$35*($A42-1))*(1+(EnemyDamageSlider-1)+(EnemyDMGDanger-1)+(EnemyJackDMG-1)),0)*IF($A42>20,(1+Max(0,((($A42-20)*(($A42-20)+1))/2)/100)*(2+Max(0,($A42-35)*0.2))),1),0)*IF(EnemyBuffed=TRUE,1.25,1),0)*EnemyDMGTaken,0),1) & ")" -> 6 (6) | E42: =Rounddown(Round(Round((E$34+E$35*($A42-1))*(1+(EnemyDamageSlider-1)+(EnemyDMGDanger-1)+(EnemyJackDMG-1)),0)*IF($A42>20,(1+Max(0,((($A42-20)*(($A42-20)+1))/2)/100)*(2+Max(0,($A42-35)*0.2))),1),0)*IF(EnemyBuffed=TRUE,1.25,1),0) & " (" & MAX(ROUND(Rounddown(Round(Round((E$34+E$35*($A42-1))*(1+(EnemyDamageSlider-1)+(EnemyDMGDanger-1)+(EnemyJackDMG-1)),0)*IF($A42>20,(1+Max(0,((($A42-20)*(($A42-20)+1))/2)/100)*(2+Max(0,($A42-35)*0.2))),1),0)*IF(EnemyBuffed=TRUE,1.25,1),0)*EnemyDMGTaken,0),1) & ")" -> 6 (6) | F42: =Rounddown(Round(Round((F$34+F$35*($A42-1))*(1+(EnemyDamageSlider-1)+(EnemyDMGDanger-1)+(EnemyJackDMG-1)),0)*IF($A42>20,(1+Max(0,((($A42-20)*(($A42-20)+1))/2)/100)*(2+Max(0,($A42-35)*0.2))),1),0)*IF(EnemyBuffed=TRUE,1.25,1),0) & " (" & MAX(ROUND(Rounddown(Round(Round((F$34+F$35*($A42-1))*(1+(EnemyDamageSlider-1)+(EnemyDMGDanger-1)+(EnemyJackDMG-1)),0)*IF($A42>20,(1+Max(0,((($A42-20)*(($A42-20)+1))/2)/100)*(2+Max(0,($A42-35)*0.2))),1),0)*IF(EnemyBuffed=TRUE,1.25,1),0)*EnemyDMGTaken,0),1) & ")" -> 9 (9) | G42: =Rounddown(Round(Round((G$34+G$35*($A42-1))*(1+(EnemyDamageSlider-1)+(EnemyDMGDanger-1)+(EnemyJackDMG-1)),0)*IF($A42>20,(1+Max(0,((($A42-20)*(($A42-20)+1))/2)/100)*(2+Max(0,($A42-35)*0.2))),1),0)*IF(EnemyBuffed=TRUE,1.25,1),0) & " (" & MAX(ROUND(Rounddown(Round(Round((G$34+G$35*($A42-1))*(1+(EnemyDamageSlider-1)+(EnemyDMGDanger-1)+(EnemyJackDMG-1)),0)*IF($A42>20,(1+Max(0,((($A42-20)*(($A42-20)+1))/2)/100)*(2+Max(0,($A42-35)*0.2))),1),0)*IF(EnemyBuffed=TRUE,1.25,1),0)*EnemyDMGTaken,0),1) & ")" -> 11 (11) | H42: =Rounddown(Round(Round((H$34+H$35*($A42-1))*(1+(EnemyDamageSlider-1)+(EnemyDMGDanger-1)+(EnemyJackDMG-1)),0)*IF($A42>20,(1+Max(0,((($A42-20)*(($A42-20)+1))/2)/100)*(2+Max(0,($A42-35)*0.2))),1),0)*IF(EnemyBuffed=TRUE,1.25,1),0) & " (" & MAX(ROUND(Rounddown(Round(Round((H$34+H$35*($A42-1))*(1+(EnemyDamageSlider-1)+(EnemyDMGDanger-1)+(EnemyJackDMG-1)),0)*IF($A42>20,(1+Max(0,((($A42-20)*(($A42-20)+1))/2)/100)*(2+Max(0,($A42-35)*0.2))),1),0)*IF(EnemyBuffed=TRUE,1.25,1),0)*EnemyDMGTaken,0),1) & ")" -> 10 (10) | I42: =Rounddown(Round(Round((I$34+I$35*($A42-1))*(1+(EnemyDamageSlider-1)+(EnemyDMGDanger-1)+(EnemyJackDMG-1)),0)*IF($A42>20,(1+Max(0,((($A42-20)*(($A42-20)+1))/2)/100)*(2+Max(0,($A42-35)*0.2))),1),0)*IF(EnemyBuffed=TRUE,1.25,1),0) & " (" & MAX(ROUND(Rounddown(Round(Round((I$34+I$35*($A42-1))*(1+(EnemyDamageSlider-1)+(EnemyDMGDanger-1)+(EnemyJackDMG-1)),0)*IF($A42>20,(1+Max(0,((($A42-20)*(($A42-20)+1))/2)/100)*(2+Max(0,($A42-35)*0.2))),1),0)*IF(EnemyBuffed=TRUE,1.25,1),0)*EnemyDMGTaken,0),1) & ")" -> 6 (6) | J42: =Rounddown(Round(Round((J$34+J$35*($A42-1))*(1+(EnemyDamageSlider-1)+(EnemyDMGDanger-1)+(EnemyJackDMG-1)),0)*IF($A42>20,(1+Max(0,((($A42-20)*(($A42-20)+1))/2)/100)*(2+Max(0,($A42-35)*0.2))),1),0)*IF(EnemyBuffed=TRUE,1.25,1),0) & " (" & MAX(ROUND(Rounddown(Round(Round((J$34+J$35*($A42-1))*(1+(EnemyDamageSlider-1)+(EnemyDMGDanger-1)+(EnemyJackDMG-1)),0)*IF($A42>20,(1+Max(0,((($A42-20)*(($A42-20)+1))/2)/100)*(2+Max(0,($A42-35)*0.2))),1),0)*IF(EnemyBuffed=TRUE,1.25,1),0)*EnemyDMGTaken,0),1) & ")" -> 9 (9) | ... AA42: =Rounddown(Round(Round((AA$34+AA$35*($A42-1))*(1+(EnemyDamageSlider-1)+(EnemyDMGDanger-1)+(EnemyJackDMG-1)),0)*IF($A42>20,(1+Max(0,((($A42-20)*(($A42-20)+1))/2)/100)*(2+Max(0,($A42-35)*0.2))),1),0)*IF(EnemyBuffed=TRUE,1.25,1),0) & " (" & MAX(ROUND(Rounddown(Round(Round((AA$34+AA$35*($A42-1))*(1+(EnemyDamageSlider-1)+(EnemyDMGDanger-1)+(EnemyJackDMG-1)),0)*IF($A42>20,(1+Max(0,((($A42-20)*(($A42-20)+1))/2)/100)*(2+Max(0,($A42-35)*0.2))),1),0)*IF(EnemyBuffed=TRUE,1.25,1),0)*EnemyDMGTaken,0),1) & ")" -> 8 (8)
